Workbook

Sheet Summary
A1: NCO-2004 to exposure: DGE concordance vs ILO correspondence table
A3: Setting
A4: Agreement threshold (absolute difference in exposure score) | B4: 0.05 | C4: Edit this cell. Groups whose two scores differ by more than this are marked "Check".
A6: Coverage
A7: NCO-2004 groups in either source | B7: =COUNTA(Comparison!A2:A120) -> 119
A8: Groups scored via DGE concordance | B8: =COUNT(Comparison!J2:J120) -> 111
A9: Groups scored via ILO table | B9: =COUNT(Comparison!K2:K120) -> 115
A10: Groups scored by both | B10: =COUNT(Comparison!L2:L120) -> 108
A11: Groups only in DGE | B11: =COUNTIF(Comparison!N2:N120,"DGE only") -> 3
A12: Groups only in ILO table | B12: =COUNTIF(Comparison!N2:N120,"ILO only") -> 7
A13: Agreement (groups scored by both)
A14: Correlation of the two scores | B14: =CORREL(Comparison!J2:J120,Comparison!K2:K120) -> 0.93515529
A15: Mean absolute difference | B15: =AVERAGE(Comparison!M2:M120) -> 0.02732474
A16: Largest absolute difference | B16: =MAX(Comparison!M2:M120) -> 0.22
A17: Groups that agree (within threshold) | B17: =COUNTIF(Comparison!N2:N120,"Agree") -> 89
A18: Groups to check (beyond threshold) | B18: =COUNTIF(Comparison!N2:N120,"Check") -> 19
A19: Share that agree | B19: =IFERROR(B17/B9,0) -> 0.77391304
A20: Code numbering
A21: DGE occupations with an NCO-2004 code | B21: =COUNTIF('DGE links'!F2:F3451,"?*") -> 2688
A22: ...of which keep the same 3-digit number in NCO-2015 | B22: =COUNTIF('DGE links'!G2:G3451,"Yes") -> 581
A23: Share keeping the same 3-digit number | B23: =IFERROR(B22/B21,0) -> 0.21614583
A25: How to read this workbook
A26: Comparison: one row per NCO-2004 group. "Exposure: DGE route" averages the NCO-2015 group scores of the occupations DGE lists under that old group (each old occupation counts once). "Exposure: ILO route" averages the ILO scores of the ISCO-08 jobs the ILO table links to that ISCO-88 group.
A27: DGE links: India's own concordance, one row per occupation and NCO-2004 code. ILO links: the ILO ISCO-08 to ISCO-88 table, one row per link.
A28: Why both: NCO-2004 is based on ISCO-88 but departs from it in places (e.g. farm labourers are 920 in NCO-2004 and 921 in ISCO-88; general managers are 130). "DGE only" and "ILO only" rows are often these renumbered groups.
A29: Colour key: blue = input values from the sources; green = formulas pulling from another sheet; yellow = setting you can change.

Sheet Comparison
A1: NCO-2004 group | B1: Main NCO-2015 group (DGE) | C1: Main NCO-2015 group title | D1: NCO-2015 groups reached via DGE | E1: ISCO-08 groups reached via ILO table | F1: Groups reached by both | G1: Overlap (shared / all groups reached) | H1: DGE occupations | I1: ISCO-08 jobs linked | J1: Exposure: DGE route | K1: Exposure: ILO route | L1: Difference (DGE - ILO) | M1: Absolute difference | N1: Agreement | O1: Score used in dataset | P1: Source of score used
A2: 011 | E2: 011 021 031 | H2: =SUMPRODUCT(('DGE links'!$F$2:$F$3451=A2)*1) -> 0 | I2: =SUMPRODUCT(('ILO links'!$G$2:$G$674=A2)*'ILO links'!$J$2:$J$674) -> 3 | J2: =IFERROR(SUMPRODUCT(('DGE links'!$F$2:$F$3451=A2)*'DGE links'!$H$2:$H$3451*'DGE links'!$I$2:$I$3451*'DGE links'!$J$2:$J$3451)/SUMPRODUCT(('DGE links'!$F$2:$F$3451=A2)*'DGE links'!$H$2:$H$3451*'DGE links'!$J$2:$J$3451),"") | K2: =IFERROR(AVERAGEIFS('ILO links'!$H$2:$H$674,'ILO links'!$G$2:$G$674,A2,'ILO links'!$J$2:$J$674,1),"") | L2: =IF(AND(ISNUMBER(J2),ISNUMBER(K2)),J2-K2,"") | M2: =IF(ISNUMBER(L2),ABS(L2),"") | N2: =IF(ISNUMBER(M2),IF(M2<=Summary!$B$4,"Agree","Check"),IF(ISNUMBER(J2),"DGE only",IF(ISNUMBER(K2),"ILO only","Not scored"))) -> Not scored | O2: =IF(ISNUMBER(J2),J2,IF(ISNUMBER(K2),K2,"")) | P2: =IF(ISNUMBER(J2),"DGE",IF(ISNUMBER(K2),"ILO table",""))
A3: 111 | B3: 111 | C3: Legislators and senior officials | D3: 111 | E3: 111 | F3: 111 | G3: 1 | H3: =SUMPRODUCT(('DGE links'!$F$2:$F$3451=A3)*1) -> 4 | I3: =SUMPRODUCT(('ILO links'!$G$2:$G$674=A3)*'ILO links'!$J$2:$J$674) -> 1 | J3: =IFERROR(SUMPRODUCT(('DGE links'!$F$2:$F$3451=A3)*'DGE links'!$H$2:$H$3451*'DGE links'!$I$2:$I$3451*'DGE links'!$J$2:$J$3451)/SUMPRODUCT(('DGE links'!$F$2:$F$3451=A3)*'DGE links'!$H$2:$H$3451*'DGE links'!$J$2:$J$3451),"") -> 0.3225 | K3: =IFERROR(AVERAGEIFS('ILO links'!$H$2:$H$674,'ILO links'!$G$2:$G$674,A3,'ILO links'!$J$2:$J$674,1),"") -> 0.31 | L3: =IF(AND(ISNUMBER(J3),ISNUMBER(K3)),J3-K3,"") -> 0.0125 | M3: =IF(ISNUMBER(L3),ABS(L3),"") -> 0.0125 | N3: =IF(ISNUMBER(M3),IF(M3<=Summary!$B$4,"Agree","Check"),IF(ISNUMBER(J3),"DGE only",IF(ISNUMBER(K3),"ILO only","Not scored"))) -> Agree | O3: =IF(ISNUMBER(J3),J3,IF(ISNUMBER(K3),K3,"")) -> 0.3225 | P3: =IF(ISNUMBER(J3),"DGE",IF(ISNUMBER(K3),"ILO table","")) -> DGE
A4: 112 | B4: 111 | C4: Legislators and senior officials | D4: 111 | E4: 111 | F4: 111 | G4: 1 | H4: =SUMPRODUCT(('DGE links'!$F$2:$F$3451=A4)*1) -> 9 | I4: =SUMPRODUCT(('ILO links'!$G$2:$G$674=A4)*'ILO links'!$J$2:$J$674) -> 1 | J4: =IFERROR(SUMPRODUCT(('DGE links'!$F$2:$F$3451=A4)*'DGE links'!$H$2:$H$3451*'DGE links'!$I$2:$I$3451*'DGE links'!$J$2:$J$3451)/SUMPRODUCT(('DGE links'!$F$2:$F$3451=A4)*'DGE links'!$H$2:$H$3451*'DGE links'!$J$2:$J$3451),"") -> 0.3225 | K4: =IFERROR(AVERAGEIFS('ILO links'!$H$2:$H$674,'ILO links'!$G$2:$G$674,A4,'ILO links'!$J$2:$J$674,1),"") -> 0.38 | L4: =IF(AND(ISNUMBER(J4),ISNUMBER(K4)),J4-K4,"") -> -0.0575 | M4: =IF(ISNUMBER(L4),ABS(L4),"") -> 0.0575 | N4: =IF(ISNUMBER(M4),IF(M4<=Summary!$B$4,"Agree","Check"),IF(ISNUMBER(J4),"DGE only",IF(ISNUMBER(K4),"ILO only","Not scored"))) -> Check | O4: =IF(ISNUMBER(J4),J4,IF(ISNUMBER(K4),K4,"")) -> 0.3225 | P4: =IF(ISNUMBER(J4),"DGE",IF(ISNUMBER(K4),"ILO table","")) -> DGE
A5: 113 | E5: 111 | H5: =SUMPRODUCT(('DGE links'!$F$2:$F$3451=A5)*1) -> 0 | I5: =SUMPRODUCT(('ILO links'!$G$2:$G$674=A5)*'ILO links'!$J$2:$J$674) -> 1 | J5: =IFERROR(SUMPRODUCT(('DGE links'!$F$2:$F$3451=A5)*'DGE links'!$H$2:$H$3451*'DGE links'!$I$2:$I$3451*'DGE links'!$J$2:$J$3451)/SUMPRODUCT(('DGE links'!$F$2:$F$3451=A5)*'DGE links'!$H$2:$H$3451*'DGE links'!$J$2:$J$3451),"") | K5: =IFERROR(AVERAGEIFS('ILO links'!$H$2:$H$674,'ILO links'!$G$2:$G$674,A5,'ILO links'!$J$2:$J$674,1),"") -> 0.23 | L5: =IF(AND(ISNUMBER(J5),ISNUMBER(K5)),J5-K5,"") | M5: =IF(ISNUMBER(L5),ABS(L5),"") | N5: =IF(ISNUMBER(M5),IF(M5<=Summary!$B$4,"Agree","Check"),IF(ISNUMBER(J5),"DGE only",IF(ISNUMBER(K5),"ILO only","Not scored"))) -> ILO only | O5: =IF(ISNUMBER(J5),J5,IF(ISNUMBER(K5),K5,"")) -> 0.23 | P5: =IF(ISNUMBER(J5),"DGE",IF(ISNUMBER(K5),"ILO table","")) -> ILO table
A6: 114 | B6: 111 | C6: Legislators and senior officials | D6: 111 | E6: 111 | F6: 111 | G6: 1 | H6: =SUMPRODUCT(('DGE links'!$F$2:$F$3451=A6)*1) -> 4 | I6: =SUMPRODUCT(('ILO links'!$G$2:$G$674=A6)*'ILO links'!$J$2:$J$674) -> 1 | J6: =IFERROR(SUMPRODUCT(('DGE links'!$F$2:$F$3451=A6)*'DGE links'!$H$2:$H$3451*'DGE links'!$I$2:$I$3451*'DGE links'!$J$2:$J$3451)/SUMPRODUCT(('DGE links'!$F$2:$F$3451=A6)*'DGE links'!$H$2:$H$3451*'DGE links'!$J$2:$J$3451),"") -> 0.3225 | K6: =IFERROR(AVERAGEIFS('ILO links'!$H$2:$H$674,'ILO links'!$G$2:$G$674,A6,'ILO links'!$J$2:$J$674,1),"") -> 0.37 | L6: =IF(AND(ISNUMBER(J6),ISNUMBER(K6)),J6-K6,"") -> -0.0475 | M6: =IF(ISNUMBER(L6),ABS(L6),"") -> 0.0475 | N6: =IF(ISNUMBER(M6),IF(M6<=Summary!$B$4,"Agree","Check"),IF(ISNUMBER(J6),"DGE only",IF(ISNUMBER(K6),"ILO only","Not scored"))) -> Agree | O6: =IF(ISNUMBER(J6),J6,IF(ISNUMBER(K6),K6,"")) -> 0.3225 | P6: =IF(ISNUMBER(J6),"DGE",IF(ISNUMBER(K6),"ILO table","")) -> DGE
A7: 121 | B7: 112 | C7: Managing directors and chief executives | D7: 112 | E7: 112 | F7: 112 | G7: 1 | H7: =SUMPRODUCT(('DGE links'!$F$2:$F$3451=A7)*1) -> 40 | I7: =SUMPRODUCT(('ILO links'!$G$2:$G$674=A7)*'ILO links'!$J$2:$J$674) -> 1 | J7: =IFERROR(SUMPRODUCT(('DGE links'!$F$2:$F$3451=A7)*'DGE links'!$H$2:$H$3451*'DGE links'!$I$2:$I$3451*'DGE links'!$J$2:$J$3451)/SUMPRODUCT(('DGE links'!$F$2:$F$3451=A7)*'DGE links'!$H$2:$H$3451*'DGE links'!$J$2:$J$3451),"") -> 0.38 | K7: =IFERROR(AVERAGEIFS('ILO links'!$H$2:$H$674,'ILO links'!$G$2:$G$674,A7,'ILO links'!$J$2:$J$674,1),"") -> 0.38 | L7: =IF(AND(ISNUMBER(J7),ISNUMBER(K7)),J7-K7,"") -> 0 | M7: =IF(ISNUMBER(L7),ABS(L7),"") -> 0 | N7: =IF(ISNUMBER(M7),IF(M7<=Summary!$B$4,"Agree","Check"),IF(ISNUMBER(J7),"DGE only",IF(ISNUMBER(K7),"ILO only","Not scored"))) -> Agree | O7: =IF(ISNUMBER(J7),J7,IF(ISNUMBER(K7),K7,"")) -> 0.38 | P7: =IF(ISNUMBER(J7),"DGE",IF(ISNUMBER(K7),"ILO table","")) -> DGE
A8: 122 | B8: 132 | C8: Manufacturing, mining, construction, and distribution managers | D8: 121 131 132 133 134 141 142 265 | E8: 121 131 132 133 134 141 142 143 265 312 | F8: 121 131 132 133 134 141 142 265 | G8: 0.8 | H8: =SUMPRODUCT(('DGE links'!$F$2:$F$3451=A8)*1) -> 61 | I8: =SUMPRODUCT(('ILO links'!$G$2:$G$674=A8)*'ILO links'!$J$2:$J$674) -> 22 | J8: =IFERROR(SUMPRODUCT(('DGE links'!$F$2:$F$3451=A8)*'DGE links'!$H$2:$H$3451*'DGE links'!$I$2:$I$3451*'DGE links'!$J$2:$J$3451)/SUMPRODUCT(('DGE links'!$F$2:$F$3451=A8)*'DGE links'!$H$2:$H$3451*'DGE links'!$J$2:$J$3451),"") -> 0.34646557 | K8: =IFERROR(AVERAGEIFS('ILO links'!$H$2:$H$674,'ILO links'!$G$2:$G$674,A8,'ILO links'!$J$2:$J$674,1),"") -> 0.36 | L8: =IF(AND(ISNUMBER(J8),ISNUMBER(K8)),J8-K8,"") -> -0.013534426 | M8: =IF(ISNUMBER(L8),ABS(L8),"") -> 0.013534426 | N8: =IF(ISNUMBER(M8),IF(M8<=Summary!$B$4,"Agree","Check"),IF(ISNUMBER(J8),"DGE only",IF(ISNUMBER(K8),"ILO only","Not scored"))) -> Agree | O8: =IF(ISNUMBER(J8),J8,IF(ISNUMBER(K8),K8,"")) -> 0.34646557 | P8: =IF(ISNUMBER(J8),"DGE",IF(ISNUMBER(K8),"ILO table","")) -> DGE
A9: 123 | B9: 121 | C9: Business services and administration managers | D9: 121 122 132 | E9: 121 122 132 133 | F9: 121 122 132 | G9: 0.75 | H9: =SUMPRODUCT(('DGE links'!$F$2:$F$3451=A9)*1) -> 14 | I9: =SUMPRODUCT(('ILO links'!$G$2:$G$674=A9)*'ILO links'!$J$2:$J$674) -> 9 | J9: =IFERROR(SUMPRODUCT(('DGE links'!$F$2:$F$3451=A9)*'DGE links'!$H$2:$H$3451*'DGE links'!$I$2:$I$3451*'DGE links'!$J$2:$J$3451)/SUMPRODUCT(('DGE links'!$F$2:$F$3451=A9)*'DGE links'!$H$2:$H$3451*'DGE links'!$J$2:$J$3451),"") -> 0.38607143 | K9: =IFERROR(AVERAGEIFS('ILO links'!$H$2:$H$674,'ILO links'!$G$2:$G$674,A9,'ILO links'!$J$2:$J$674,1),"") -> 0.39222222 | L9: =IF(AND(ISNUMBER(J9),ISNUMBER(K9)),J9-K9,"") -> -0.0061507937 | M9: =IF(ISNUMBER(L9),ABS(L9),"") -> 0.0061507937 | N9: =IF(ISNUMBER(M9),IF(M9<=Summary!$B$4,"Agree","Check"),IF(ISNUMBER(J9),"DGE only",IF(ISNUMBER(K9),"ILO only","Not scored"))) -> Agree | O9: =IF(ISNUMBER(J9),J9,IF(ISNUMBER(K9),K9,"")) -> 0.38607143 | P9: =IF(ISNUMBER(J9),"DGE",IF(ISNUMBER(K9),"ILO table","")) -> DGE
A10: 130 | B10: 132 | C10: Manufacturing, mining, construction, and distribution managers | D10: 121 131 132 133 141 142 143 | H10: =SUMPRODUCT(('DGE links'!$F$2:$F$3451=A10)*1) -> 28 | I10: =SUMPRODUCT(('ILO links'!$G$2:$G$674=A10)*'ILO links'!$J$2:$J$674) -> 0 | J10: =IFERROR(SUMPRODUCT(('DGE links'!$F$2:$F$3451=A10)*'DGE links'!$H$2:$H$3451*'DGE links'!$I$2:$I$3451*'DGE links'!$J$2:$J$3451)/SUMPRODUCT(('DGE links'!$F$2:$F$3451=A10)*'DGE links'!$H$2:$H$3451*'DGE links'!$J$2:$J$3451),"") -> 0.34660714 | K10: =IFERROR(AVERAGEIFS('ILO links'!$H$2:$H$674,'ILO links'!$G$2:$G$674,A10,'ILO links'!$J$2:$J$674,1),"") | L10: =IF(AND(ISNUMBER(J10),ISNUMBER(K10)),J10-K10,"") | M10: =IF(ISNUMBER(L10),ABS(L10),"") | N10: =IF(ISNUMBER(M10),IF(M10<=Summary!$B$4,"Agree","Check"),IF(ISNUMBER(J10),"DGE only",IF(ISNUMBER(K10),"ILO only","Not scored"))) -> DGE only | O10: =IF(ISNUMBER(J10),J10,IF(ISNUMBER(K10),K10,"")) -> 0.34660714 | P10: =IF(ISNUMBER(J10),"DGE",IF(ISNUMBER(K10),"ILO table","")) -> DGE
A11: 131 | E11: 121 122 132 133 134 141 142 143 522 611 612 613 | H11: =SUMPRODUCT(('DGE links'!$F$2:$F$3451=A11)*1) -> 0 | I11: =SUMPRODUCT(('ILO links'!$G$2:$G$674=A11)*'ILO links'!$J$2:$J$674) -> 31 | J11: =IFERROR(SUMPRODUCT(('DGE links'!$F$2:$F$3451=A11)*'DGE links'!$H$2:$H$3451*'DGE links'!$I$2:$I$3451*'DGE links'!$J$2:$J$3451)/SUMPRODUCT(('DGE links'!$F$2:$F$3451=A11)*'DGE links'!$H$2:$H$3451*'DGE links'!$J$2:$J$3451),"") | K11: =IFERROR(AVERAGEIFS('ILO links'!$H$2:$H$674,'ILO links'!$G$2:$G$674,A11,'ILO links'!$J$2:$J$674,1),"") -> 0.333 | L11: =IF(AND(ISNUMBER(J11),ISNUMBER(K11)),J11-K11,"") | M11: =IF(ISNUMBER(L11),ABS(L11),"") | N11: =IF(ISNUMBER(M11),IF(M11<=Summary!$B$4,"Agree","Check"),IF(ISNUMBER(J11),"DGE only",IF(ISNUMBER(K11),"ILO only","Not scored"))) -> ILO only | O11: =IF(ISNUMBER(J11),J11,IF(ISNUMBER(K11),K11,"")) -> 0.333 | P11: =IF(ISNUMBER(J11),"DGE",IF(ISNUMBER(K11),"ILO table","")) -> ILO table
A12: 211 | B12: 211 | C12: Physical and earth science professionals | D12: 211 226 | E12: 211 226 | F12: 211 226 | G12: 1 | H12: =SUMPRODUCT(('DGE links'!$F$2:$F$3451=A12)*1) -> 34 | I12: =SUMPRODUCT(('ILO links'!$G$2:$G$674=A12)*'ILO links'!$J$2:$J$674) -> 5 | J12: =IFERROR(SUMPRODUCT(('DGE links'!$F$2:$F$3451=A12)*'DGE links'!$H$2:$H$3451*'DGE links'!$I$2:$I$3451*'DGE links'!$J$2:$J$3451)/SUMPRODUCT(('DGE links'!$F$2:$F$3451=A12)*'DGE links'!$H$2:$H$3451*'DGE links'!$J$2:$J$3451),"") -> 0.41291515 | K12: =IFERROR(AVERAGEIFS('ILO links'!$H$2:$H$674,'ILO links'!$G$2:$G$674,A12,'ILO links'!$J$2:$J$674,1),"") -> 0.4 | L12: =IF(AND(ISNUMBER(J12),ISNUMBER(K12)),J12-K12,"") -> 0.012915152 | M12: =IF(ISNUMBER(L12),ABS(L12),"") -> 0.012915152 | N12: =IF(ISNUMBER(M12),IF(M12<=Summary!$B$4,"Agree","Check"),IF(ISNUMBER(J12),"DGE only",IF(ISNUMBER(K12),"ILO only","Not scored"))) -> Agree | O12: =IF(ISNUMBER(J12),J12,IF(ISNUMBER(K12),K12,"")) -> 0.41291515 | P12: =IF(ISNUMBER(J12),"DGE",IF(ISNUMBER(K12),"ILO table","")) -> DGE
A13: 212 | B13: 212 | C13: Mathematicians, actuaries and statisticians | D13: 212 | E13: 212 | F13: 212 | G13: 1 | H13: =SUMPRODUCT(('DGE links'!$F$2:$F$3451=A13)*1) -> 6 | I13: =SUMPRODUCT(('ILO links'!$G$2:$G$674=A13)*'ILO links'!$J$2:$J$674) -> 1 | J13: =IFERROR(SUMPRODUCT(('DGE links'!$F$2:$F$3451=A13)*'DGE links'!$H$2:$H$3451*'DGE links'!$I$2:$I$3451*'DGE links'!$J$2:$J$3451)/SUMPRODUCT(('DGE links'!$F$2:$F$3451=A13)*'DGE links'!$H$2:$H$3451*'DGE links'!$J$2:$J$3451),"") -> 0.56 | K13: =IFERROR(AVERAGEIFS('ILO links'!$H$2:$H$674,'ILO links'!$G$2:$G$674,A13,'ILO links'!$J$2:$J$674,1),"") -> 0.56 | L13: =IF(AND(ISNUMBER(J13),ISNUMBER(K13)),J13-K13,"") -> 0 | M13: =IF(ISNUMBER(L13),ABS(L13),"") -> 0 | N13: =IF(ISNUMBER(M13),IF(M13<=Summary!$B$4,"Agree","Check"),IF(ISNUMBER(J13),"DGE only",IF(ISNUMBER(K13),"ILO only","Not scored"))) -> Agree | O13: =IF(ISNUMBER(J13),J13,IF(ISNUMBER(K13),K13,"")) -> 0.56 | P13: =IF(ISNUMBER(J13),"DGE",IF(ISNUMBER(K13),"ILO table","")) -> DGE
A14: 213 | B14: 251 | C14: Software and applications developers and analysts | D14: 251 252 | E14: 251 252 351 | F14: 251 252 | G14: 0.66666667 | H14: =SUMPRODUCT(('DGE links'!$F$2:$F$3451=A14)*1) -> 15 | I14: =SUMPRODUCT(('ILO links'!$G$2:$G$674=A14)*'ILO links'!$J$2:$J$674) -> 10 | J14: =IFERROR(SUMPRODUCT(('DGE links'!$F$2:$F$3451=A14)*'DGE links'!$H$2:$H$3451*'DGE links'!$I$2:$I$3451*'DGE links'!$J$2:$J$3451)/SUMPRODUCT(('DGE links'!$F$2:$F$3451=A14)*'DGE links'!$H$2:$H$3451*'DGE links'!$J$2:$J$3451),"") -> 0.54425 | K14: =IFERROR(AVERAGEIFS('ILO links'!$H$2:$H$674,'ILO links'!$G$2:$G$674,A14,'ILO links'!$J$2:$J$674,1),"") -> 0.532 | L14: =IF(AND(ISNUMBER(J14),ISNUMBER(K14)),J14-K14,"") -> 0.01225 | M14: =IF(ISNUMBER(L14),ABS(L14),"") -> 0.01225 | N14: =IF(ISNUMBER(M14),IF(M14<=Summary!$B$4,"Agree","Check"),IF(ISNUMBER(J14),"DGE only",IF(ISNUMBER(K14),"ILO only","Not scored"))) -> Agree | O14: =IF(ISNUMBER(J14),J14,IF(ISNUMBER(K14),K14,"")) -> 0.54425 | P14: =IF(ISNUMBER(J14),"DGE",IF(ISNUMBER(K14),"ILO table","")) -> DGE
A15: 214 | B15: 214 | C15: Engineering professionals (excluding electrotechnology) | D15: 214 215 216 | E15: 214 215 216 | F15: 214 215 216 | G15: 1 | H15: =SUMPRODUCT(('DGE links'!$F$2:$F$3451=A15)*1) -> 102 | I15: =SUMPRODUCT(('ILO links'!$G$2:$G$674=A15)*'ILO links'!$J$2:$J$674) -> 14 | J15: =IFERROR(SUMPRODUCT(('DGE links'!$F$2:$F$3451=A15)*'DGE links'!$H$2:$H$3451*'DGE links'!$I$2:$I$3451*'DGE links'!$J$2:$J$3451)/SUMPRODUCT(('DGE links'!$F$2:$F$3451=A15)*'DGE links'!$H$2:$H$3451*'DGE links'!$J$2:$J$3451),"") -> 0.34814902 | K15: =IFERROR(AVERAGEIFS('ILO links'!$H$2:$H$674,'ILO links'!$G$2:$G$674,A15,'ILO links'!$J$2:$J$674,1),"") -> 0.365 | L15: =IF(AND(ISNUMBER(J15),ISNUMBER(K15)),J15-K15,"") -> -0.01685098 | M15: =IF(ISNUMBER(L15),ABS(L15),"") -> 0.01685098 | N15: =IF(ISNUMBER(M15),IF(M15<=Summary!$B$4,"Agree","Check"),IF(ISNUMBER(J15),"DGE only",IF(ISNUMBER(K15),"ILO only","Not scored"))) -> Agree | O15: =IF(ISNUMBER(J15),J15,IF(ISNUMBER(K15),K15,"")) -> 0.34814902 | P15: =IF(ISNUMBER(J15),"DGE",IF(ISNUMBER(K15),"ILO table","")) -> DGE
A16: 221 | B16: 213 | C16: Life science professionals | D16: 213 221 225 | E16: 213 221 225 | F16: 213 221 225 | G16: 1 | H16: =SUMPRODUCT(('DGE links'!$F$2:$F$3451=A16)*1) -> 38 | I16: =SUMPRODUCT(('ILO links'!$G$2:$G$674=A16)*'ILO links'!$J$2:$J$674) -> 5 | J16: =IFERROR(SUMPRODUCT(('DGE links'!$F$2:$F$3451=A16)*'DGE links'!$H$2:$H$3451*'DGE links'!$I$2:$I$3451*'DGE links'!$J$2:$J$3451)/SUMPRODUCT(('DGE links'!$F$2:$F$3451=A16)*'DGE links'!$H$2:$H$3451*'DGE links'!$J$2:$J$3451),"") -> 0.33840541 | K16: =IFERROR(AVERAGEIFS('ILO links'!$H$2:$H$674,'ILO links'!$G$2:$G$674,A16,'ILO links'!$J$2:$J$674,1),"") -> 0.296 | L16: =IF(AND(ISNUMBER(J16),ISNUMBER(K16)),J16-K16,"") -> 0.042405405 | M16: =IF(ISNUMBER(L16),ABS(L16),"") -> 0.042405405 | N16: =IF(ISNUMBER(M16),IF(M16<=Summary!$B$4,"Agree","Check"),IF(ISNUMBER(J16),"DGE only",IF(ISNUMBER(K16),"ILO only","Not scored"))) -> Agree | O16: =IF(ISNUMBER(J16),J16,IF(ISNUMBER(K16),K16,"")) -> 0.33840541 | P16: =IF(ISNUMBER(J16),"DGE",IF(ISNUMBER(K16),"ILO table","")) -> DGE
A17: 222 | B17: 221 | C17: Medical doctors | D17: 221 223 225 226 | E17: 221 225 226 | F17: 221 225 226 | G17: 0.75 | H17: =SUMPRODUCT(('DGE links'!$F$2:$F$3451=A17)*1) -> 43 | I17: =SUMPRODUCT(('ILO links'!$G$2:$G$674=A17)*'ILO links'!$J$2:$J$674) -> 7 | J17: =IFERROR(SUMPRODUCT(('DGE links'!$F$2:$F$3451=A17)*'DGE links'!$H$2:$H$3451*'DGE links'!$I$2:$I$3451*'DGE links'!$J$2:$J$3451)/SUMPRODUCT(('DGE links'!$F$2:$F$3451=A17)*'DGE links'!$H$2:$H$3451*'DGE links'!$J$2:$J$3451),"") -> 0.26001395 | K17: =IFERROR(AVERAGEIFS('ILO links'!$H$2:$H$674,'ILO links'!$G$2:$G$674,A17,'ILO links'!$J$2:$J$674,1),"") -> 0.23714286 | L17: =IF(AND(ISNUMBER(J17),ISNUMBER(K17)),J17-K17,"") -> 0.022871096 | M17: =IF(ISNUMBER(L17),ABS(L17),"") -> 0.022871096 | N17: =IF(ISNUMBER(M17),IF(M17<=Summary!$B$4,"Agree","Check"),IF(ISNUMBER(J17),"DGE only",IF(ISNUMBER(K17),"ILO only","Not scored"))) -> Agree | O17: =IF(ISNUMBER(J17),J17,IF(ISNUMBER(K17),K17,"")) -> 0.26001395 | P17: =IF(ISNUMBER(J17),"DGE",IF(ISNUMBER(K17),"ILO table","")) -> DGE
A18: 223 | B18: 222 | C18: Nursing and midwifery professionals | D18: 222 | E18: 134 222 322 | F18: 222 | G18: 0.33333333 | H18: =SUMPRODUCT(('DGE links'!$F$2:$F$3451=A18)*1) -> 2 | I18: =SUMPRODUCT(('ILO links'!$G$2:$G$674=A18)*'ILO links'!$J$2:$J$674) -> 6 | J18: =IFERROR(SUMPRODUCT(('DGE links'!$F$2:$F$3451=A18)*'DGE links'!$H$2:$H$3451*'DGE links'!$I$2:$I$3451*'DGE links'!$J$2:$J$3451)/SUMPRODUCT(('DGE links'!$F$2:$F$3451=A18)*'DGE links'!$H$2:$H$3451*'DGE links'!$J$2:$J$3451),"") -> 0.275 | K18: =IFERROR(AVERAGEIFS('ILO links'!$H$2:$H$674,'ILO links'!$G$2:$G$674,A18,'ILO links'!$J$2:$J$674,1),"") -> 0.27833333 | L18: =IF(AND(ISNUMBER(J18),ISNUMBER(K18)),J18-K18,"") -> -0.0033333333 | M18: =IF(ISNUMBER(L18),ABS(L18),"") -> 0.0033333333 | N18: =IF(ISNUMBER(M18),IF(M18<=Summary!$B$4,"Agree","Check"),IF(ISNUMBER(J18),"DGE only",IF(ISNUMBER(K18),"ILO only","Not scored"))) -> Agree | O18: =IF(ISNUMBER(J18),J18,IF(ISNUMBER(K18),K18,"")) -> 0.275 | P18: =IF(ISNUMBER(J18),"DGE",IF(ISNUMBER(K18),"ILO table","")) -> DGE
A19: 231 | B19: 231 | C19: University and higher education teachers | D19: 231 | E19: 231 232 | F19: 231 | G19: 0.5 | H19: =SUMPRODUCT(('DGE links'!$F$2:$F$3451=A19)*1) -> 13 | I19: =SUMPRODUCT(('ILO links'!$G$2:$G$674=A19)*'ILO links'!$J$2:$J$674) -> 2 | J19: =IFERROR(SUMPRODUCT(('DGE links'!$F$2:$F$3451=A19)*'DGE links'!$H$2:$H$3451*'DGE links'!$I$2:$I$3451*'DGE links'!$J$2:$J$3451)/SUMPRODUCT(('DGE links'!$F$2:$F$3451=A19)*'DGE links'!$H$2:$H$3451*'DGE links'!$J$2:$J$3451),"") -> 0.37 | K19: =IFERROR(AVERAGEIFS('ILO links'!$H$2:$H$674,'ILO links'!$G$2:$G$674,A19,'ILO links'!$J$2:$J$674,1),"") -> 0.36 | L19: =IF(AND(ISNUMBER(J19),ISNUMBER(K19)),J19-K19,"") -> 0.01 | M19: =IF(ISNUMBER(L19),ABS(L19),"") -> 0.01 | N19: =IF(ISNUMBER(M19),IF(M19<=Summary!$B$4,"Agree","Check"),IF(ISNUMBER(J19),"DGE only",IF(ISNUMBER(K19),"ILO only","Not scored"))) -> Agree | O19: =IF(ISNUMBER(J19),J19,IF(ISNUMBER(K19),K19,"")) -> 0.37 | P19: =IF(ISNUMBER(J19),"DGE",IF(ISNUMBER(K19),"ILO table","")) -> DGE
A20: 232 | B20: 233 | C20: Secondary education teachers | D20: 233 | E20: 232 233 | F20: 233 | G20: 0.5 | H20: =SUMPRODUCT(('DGE links'!$F$2:$F$3451=A20)*1) -> 5 | I20: =SUMPRODUCT(('ILO links'!$G$2:$G$674=A20)*'ILO links'!$J$2:$J$674) -> 2 | J20: =IFERROR(SUMPRODUCT(('DGE links'!$F$2:$F$3451=A20)*'DGE links'!$H$2:$H$3451*'DGE links'!$I$2:$I$3451*'DGE links'!$J$2:$J$3451)/SUMPRODUCT(('DGE links'!$F$2:$F$3451=A20)*'DGE links'!$H$2:$H$3451*'DGE links'!$J$2:$J$3451),"") -> 0.3 | K20: =IFERROR(AVERAGEIFS('ILO links'!$H$2:$H$674,'ILO links'!$G$2:$G$674,A20,'ILO links'!$J$2:$J$674,1),"") -> 0.325 | L20: =IF(AND(ISNUMBER(J20),ISNUMBER(K20)),J20-K20,"") -> -0.025 | M20: =IF(ISNUMBER(L20),ABS(L20),"") -> 0.025 | N20: =IF(ISNUMBER(M20),IF(M20<=Summary!$B$4,"Agree","Check"),IF(ISNUMBER(J20),"DGE only",IF(ISNUMBER(K20),"ILO only","Not scored"))) -> Agree | O20: =IF(ISNUMBER(J20),J20,IF(ISNUMBER(K20),K20,"")) -> 0.3 | P20: =IF(ISNUMBER(J20),"DGE",IF(ISNUMBER(K20),"ILO table","")) -> DGE
A21: 233 | B21: 235 | C21: Other teaching professionals | D21: 235 | E21: 234 | G21: 0 | H21: =SUMPRODUCT(('DGE links'!$F$2:$F$3451=A21)*1) -> 4 | I21: =SUMPRODUCT(('ILO links'!$G$2:$G$674=A21)*'ILO links'!$J$2:$J$674) -> 2 | J21: =IFERROR(SUMPRODUCT(('DGE links'!$F$2:$F$3451=A21)*'DGE links'!$H$2:$H$3451*'DGE links'!$I$2:$I$3451*'DGE links'!$J$2:$J$3451)/SUMPRODUCT(('DGE links'!$F$2:$F$3451=A21)*'DGE links'!$H$2:$H$3451*'DGE links'!$J$2:$J$3451),"") -> 0.3586 | K21: =IFERROR(AVERAGEIFS('ILO links'!$H$2:$H$674,'ILO links'!$G$2:$G$674,A21,'ILO links'!$J$2:$J$674,1),"") -> 0.235 | L21: =IF(AND(ISNUMBER(J21),ISNUMBER(K21)),J21-K21,"") -> 0.1236 | M21: =IF(ISNUMBER(L21),ABS(L21),"") -> 0.1236 | N21: =IF(ISNUMBER(M21),IF(M21<=Summary!$B$4,"Agree","Check"),IF(ISNUMBER(J21),"DGE only",IF(ISNUMBER(K21),"ILO only","Not scored"))) -> Check | O21: =IF(ISNUMBER(J21),J21,IF(ISNUMBER(K21),K21,"")) -> 0.3586 | P21: =IF(ISNUMBER(J21),"DGE",IF(ISNUMBER(K21),"ILO table","")) -> DGE
A22: 234 | E22: 235 | H22: =SUMPRODUCT(('DGE links'!$F$2:$F$3451=A22)*1) -> 0 | I22: =SUMPRODUCT(('ILO links'!$G$2:$G$674=A22)*'ILO links'!$J$2:$J$674) -> 1 | J22: =IFERROR(SUMPRODUCT(('DGE links'!$F$2:$F$3451=A22)*'DGE links'!$H$2:$H$3451*'DGE links'!$I$2:$I$3451*'DGE links'!$J$2:$J$3451)/SUMPRODUCT(('DGE links'!$F$2:$F$3451=A22)*'DGE links'!$H$2:$H$3451*'DGE links'!$J$2:$J$3451),"") | K22: =IFERROR(AVERAGEIFS('ILO links'!$H$2:$H$674,'ILO links'!$G$2:$G$674,A22,'ILO links'!$J$2:$J$674,1),"") -> 0.28 | L22: =IF(AND(ISNUMBER(J22),ISNUMBER(K22)),J22-K22,"") | M22: =IF(ISNUMBER(L22),ABS(L22),"") | N22: =IF(ISNUMBER(M22),IF(M22<=Summary!$B$4,"Agree","Check"),IF(ISNUMBER(J22),"DGE only",IF(ISNUMBER(K22),"ILO only","Not scored"))) -> ILO only | O22: =IF(ISNUMBER(J22),J22,IF(ISNUMBER(K22),K22,"")) -> 0.28 | P22: =IF(ISNUMBER(J22),"DGE",IF(ISNUMBER(K22),"ILO table","")) -> ILO table
A23: 235 | E23: 235 | H23: =SUMPRODUCT(('DGE links'!$F$2:$F$3451=A23)*1) -> 0 | I23: =SUMPRODUCT(('ILO links'!$G$2:$G$674=A23)*'ILO links'!$J$2:$J$674) -> 6 | J23: =IFERROR(SUMPRODUCT(('DGE links'!$F$2:$F$3451=A23)*'DGE links'!$H$2:$H$3451*'DGE links'!$I$2:$I$3451*'DGE links'!$J$2:$J$3451)/SUMPRODUCT(('DGE links'!$F$2:$F$3451=A23)*'DGE links'!$H$2:$H$3451*'DGE links'!$J$2:$J$3451),"") | K23: =IFERROR(AVERAGEIFS('ILO links'!$H$2:$H$674,'ILO links'!$G$2:$G$674,A23,'ILO links'!$J$2:$J$674,1),"") -> 0.37166667 | L23: =IF(AND(ISNUMBER(J23),ISNUMBER(K23)),J23-K23,"") | M23: =IF(ISNUMBER(L23),ABS(L23),"") | N23: =IF(ISNUMBER(M23),IF(M23<=Summary!$B$4,"Agree","Check"),IF(ISNUMBER(J23),"DGE only",IF(ISNUMBER(K23),"ILO only","Not scored"))) -> ILO only | O23: =IF(ISNUMBER(J23),J23,IF(ISNUMBER(K23),K23,"")) -> 0.37166667 | P23: =IF(ISNUMBER(J23),"DGE",IF(ISNUMBER(K23),"ILO table","")) -> ILO table
A24: 241 | B24: 241 | C24: Finance professionals | D24: 241 242 243 333 | E24: 226 241 242 243 333 | F24: 241 242 243 333 | G24: 0.8 | H24: =SUMPRODUCT(('DGE links'!$F$2:$F$3451=A24)*1) -> 21 | I24: =SUMPRODUCT(('ILO links'!$G$2:$G$674=A24)*'ILO links'!$J$2:$J$674) -> 11 | J24: =IFERROR(SUMPRODUCT(('DGE links'!$F$2:$F$3451=A24)*'DGE links'!$H$2:$H$3451*'DGE links'!$I$2:$I$3451*'DGE links'!$J$2:$J$3451)/SUMPRODUCT(('DGE links'!$F$2:$F$3451=A24)*'DGE links'!$H$2:$H$3451*'DGE links'!$J$2:$J$3451),"") -> 0.50057619 | K24: =IFERROR(AVERAGEIFS('ILO links'!$H$2:$H$674,'ILO links'!$G$2:$G$674,A24,'ILO links'!$J$2:$J$674,1),"") -> 0.46727273 | L24: =IF(AND(ISNUMBER(J24),ISNUMBER(K24)),J24-K24,"") -> 0.033303463 | M24: =IF(ISNUMBER(L24),ABS(L24),"") -> 0.033303463 | N24: =IF(ISNUMBER(M24),IF(M24<=Summary!$B$4,"Agree","Check"),IF(ISNUMBER(J24),"DGE only",IF(ISNUMBER(K24),"ILO only","Not scored"))) -> Agree | O24: =IF(ISNUMBER(J24),J24,IF(ISNUMBER(K24),K24,"")) -> 0.50057619 | P24: =IF(ISNUMBER(J24),"DGE",IF(ISNUMBER(K24),"ILO table","")) -> DGE
A25: 242 | B25: 261 | C25: Legal professionals | D25: 261 | E25: 261 | F25: 261 | G25: 1 | H25: =SUMPRODUCT(('DGE links'!$F$2:$F$3451=A25)*1) -> 35 | I25: =SUMPRODUCT(('ILO links'!$G$2:$G$674=A25)*'ILO links'!$J$2:$J$674) -> 3 | J25: =IFERROR(SUMPRODUCT(('DGE links'!$F$2:$F$3451=A25)*'DGE links'!$H$2:$H$3451*'DGE links'!$I$2:$I$3451*'DGE links'!$J$2:$J$3451)/SUMPRODUCT(('DGE links'!$F$2:$F$3451=A25)*'DGE links'!$H$2:$H$3451*'DGE links'!$J$2:$J$3451),"") -> 0.3467 | K25: =IFERROR(AVERAGEIFS('ILO links'!$H$2:$H$674,'ILO links'!$G$2:$G$674,A25,'ILO links'!$J$2:$J$674,1),"") -> 0.34666667 | L25: =IF(AND(ISNUMBER(J25),ISNUMBER(K25)),J25-K25,"") -> 3.3333333e-05 | M25: =IF(ISNUMBER(L25),ABS(L25),"") -> 3.3333333e-05 | N25: =IF(ISNUMBER(M25),IF(M25<=Summary!$B$4,"Agree","Check"),IF(ISNUMBER(J25),"DGE only",IF(ISNUMBER(K25),"ILO only","Not scored"))) -> Agree | O25: =IF(ISNUMBER(J25),J25,IF(ISNUMBER(K25),K25,"")) -> 0.3467 | P25: =IF(ISNUMBER(J25),"DGE",IF(ISNUMBER(K25),"ILO table","")) -> DGE
A26: 243 | B26: 262 | C26: Librarians, archivists and curators | D26: 262 | E26: 262 | F26: 262 | G26: 1 | H26: =SUMPRODUCT(('DGE links'!$F$2:$F$3451=A26)*1) -> 13 | I26: =SUMPRODUCT(('ILO links'!$G$2:$G$674=A26)*'ILO links'!$J$2:$J$674) -> 2 | J26: =IFERROR(SUMPRODUCT(('DGE links'!$F$2:$F$3451=A26)*'DGE links'!$H$2:$H$3451*'DGE links'!$I$2:$I$3451*'DGE links'!$J$2:$J$3451)/SUMPRODUCT(('DGE links'!$F$2:$F$3451=A26)*'DGE links'!$H$2:$H$3451*'DGE links'!$J$2:$J$3451),"") -> 0.51 | K26: =IFERROR(AVERAGEIFS('ILO links'!$H$2:$H$674,'ILO links'!$G$2:$G$674,A26,'ILO links'!$J$2:$J$674,1),"") -> 0.51 | L26: =IF(AND(ISNUMBER(J26),ISNUMBER(K26)),J26-K26,"") -> 0 | M26: =IF(ISNUMBER(L26),ABS(L26),"") -> 0 | N26: =IF(ISNUMBER(M26),IF(M26<=Summary!$B$4,"Agree","Check"),IF(ISNUMBER(J26),"DGE only",IF(ISNUMBER(K26),"ILO only","Not scored"))) -> Agree | O26: =IF(ISNUMBER(J26),J26,IF(ISNUMBER(K26),K26,"")) -> 0.51 | P26: =IF(ISNUMBER(J26),"DGE",IF(ISNUMBER(K26),"ILO table","")) -> DGE
A27: 244 | B27: 263 | C27: Social and religious professionals | D27: 263 264 | E27: 263 264 | F27: 263 264 | G27: 1 | H27: =SUMPRODUCT(('DGE links'!$F$2:$F$3451=A27)*1) -> 49 | I27: =SUMPRODUCT(('ILO links'!$G$2:$G$674=A27)*'ILO links'!$J$2:$J$674) -> 6 | J27: =IFERROR(SUMPRODUCT(('DGE links'!$F$2:$F$3451=A27)*'DGE links'!$H$2:$H$3451*'DGE links'!$I$2:$I$3451*'DGE links'!$J$2:$J$3451)/SUMPRODUCT(('DGE links'!$F$2:$F$3451=A27)*'DGE links'!$H$2:$H$3451*'DGE links'!$J$2:$J$3451),"") -> 0.40387755 | K27: =IFERROR(AVERAGEIFS('ILO links'!$H$2:$H$674,'ILO links'!$G$2:$G$674,A27,'ILO links'!$J$2:$J$674,1),"") -> 0.46 | L27: =IF(AND(ISNUMBER(J27),ISNUMBER(K27)),J27-K27,"") -> -0.056122449 | M27: =IF(ISNUMBER(L27),ABS(L27),"") -> 0.056122449 | N27: =IF(ISNUMBER(M27),IF(M27<=Summary!$B$4,"Agree","Check"),IF(ISNUMBER(J27),"DGE only",IF(ISNUMBER(K27),"ILO only","Not scored"))) -> Check | O27: =IF(ISNUMBER(J27),J27,IF(ISNUMBER(K27),K27,"")) -> 0.40387755 | P27: =IF(ISNUMBER(J27),"DGE",IF(ISNUMBER(K27),"ILO table","")) -> DGE
A28: 245 | B28: 265 | C28: Creative and performing artists | D28: 216 243 264 265 | E28: 264 265 | F28: 264 265 | G28: 0.5 | H28: =SUMPRODUCT(('DGE links'!$F$2:$F$3451=A28)*1) -> 44 | I28: =SUMPRODUCT(('ILO links'!$G$2:$G$674=A28)*'ILO links'!$J$2:$J$674) -> 7 | J28: =IFERROR(SUMPRODUCT(('DGE links'!$F$2:$F$3451=A28)*'DGE links'!$H$2:$H$3451*'DGE links'!$I$2:$I$3451*'DGE links'!$J$2:$J$3451)/SUMPRODUCT(('DGE links'!$F$2:$F$3451=A28)*'DGE links'!$H$2:$H$3451*'DGE links'!$J$2:$J$3451),"") -> 0.38607955 | K28: =IFERROR(AVERAGEIFS('ILO links'!$H$2:$H$674,'ILO links'!$G$2:$G$674,A28,'ILO links'!$J$2:$J$674,1),"") -> 0.35 | L28: =IF(AND(ISNUMBER(J28),ISNUMBER(K28)),J28-K28,"") -> 0.036079545 | M28: =IF(ISNUMBER(L28),ABS(L28),"") -> 0.036079545 | N28: =IF(ISNUMBER(M28),IF(M28<=Summary!$B$4,"Agree","Check"),IF(ISNUMBER(J28),"DGE only",IF(ISNUMBER(K28),"ILO only","Not scored"))) -> Agree | O28: =IF(ISNUMBER(J28),J28,IF(ISNUMBER(K28),K28,"")) -> 0.38607955 | P28: =IF(ISNUMBER(J28),"DGE",IF(ISNUMBER(K28),"ILO table","")) -> DGE
A29: 246 | B29: 263 | C29: Social and religious professionals | D29: 263 | E29: 263 | F29: 263 | G29: 1 | H29: =SUMPRODUCT(('DGE links'!$F$2:$F$3451=A29)*1) -> 3 | I29: =SUMPRODUCT(('ILO links'!$G$2:$G$674=A29)*'ILO links'!$J$2:$J$674) -> 1 | J29: =IFERROR(SUMPRODUCT(('DGE links'!$F$2:$F$3451=A29)*'DGE links'!$H$2:$H$3451*'DGE links'!$I$2:$I$3451*'DGE links'!$J$2:$J$3451)/SUMPRODUCT(('DGE links'!$F$2:$F$3451=A29)*'DGE links'!$H$2:$H$3451*'DGE links'!$J$2:$J$3451),"") -> 0.39 | K29: =IFERROR(AVERAGEIFS('ILO links'!$H$2:$H$674,'ILO links'!$G$2:$G$674,A29,'ILO links'!$J$2:$J$674,1),"") -> 0.17 | L29: =IF(AND(ISNUMBER(J29),ISNUMBER(K29)),J29-K29,"") -> 0.22 | M29: =IF(ISNUMBER(L29),ABS(L29),"") -> 0.22 | N29: =IF(ISNUMBER(M29),IF(M29<=Summary!$B$4,"Agree","Check"),IF(ISNUMBER(J29),"DGE only",IF(ISNUMBER(K29),"ILO only","Not scored"))) -> Check | O29: =IF(ISNUMBER(J29),J29,IF(ISNUMBER(K29),K29,"")) -> 0.39 | P29: =IF(ISNUMBER(J29),"DGE",IF(ISNUMBER(K29),"ILO table","")) -> DGE
A30: 311 | B30: 311 | C30: Physical and engineering science technicians | D30: 311 352 | E30: 311 352 | F30: 311 352 | G30: 1 | H30: =SUMPRODUCT(('DGE links'!$F$2:$F$3451=A30)*1) -> 63 | I30: =SUMPRODUCT(('ILO links'!$G$2:$G$674=A30)*'ILO links'!$J$2:$J$674) -> 10 | J30: =IFERROR(SUMPRODUCT(('DGE links'!$F$2:$F$3451=A30)*'DGE links'!$H$2:$H$3451*'DGE links'!$I$2:$I$3451*'DGE links'!$J$2:$J$3451)/SUMPRODUCT(('DGE links'!$F$2:$F$3451=A30)*'DGE links'!$H$2:$H$3451*'DGE links'!$J$2:$J$3451),"") -> 0.30233548 | K30: =IFERROR(AVERAGEIFS('ILO links'!$H$2:$H$674,'ILO links'!$G$2:$G$674,A30,'ILO links'!$J$2:$J$674,1),"") -> 0.311 | L30: =IF(AND(ISNUMBER(J30),ISNUMBER(K30)),J30-K30,"") -> -0.0086645161 | M30: =IF(ISNUMBER(L30),ABS(L30),"") -> 0.0086645161 | N30: =IF(ISNUMBER(M30),IF(M30<=Summary!$B$4,"Agree","Check"),IF(ISNUMBER(J30),"DGE only",IF(ISNUMBER(K30),"ILO only","Not scored"))) -> Agree | O30: =IF(ISNUMBER(J30),J30,IF(ISNUMBER(K30),K30,"")) -> 0.30233548 | P30: =IF(ISNUMBER(J30),"DGE",IF(ISNUMBER(K30),"ILO table","")) -> DGE
A31: 312 | B31: 351 | C31: Information and communications technology operations and user support technicians | D31: 351 | E31: 313 351 | F31: 351 | G31: 0.5 | H31: =SUMPRODUCT(('DGE links'!$F$2:$F$3451=A31)*1) -> 7 | I31: =SUMPRODUCT(('ILO links'!$G$2:$G$674=A31)*'ILO links'!$J$2:$J$674) -> 5 | J31: =IFERROR(SUMPRODUCT(('DGE links'!$F$2:$F$3451=A31)*'DGE links'!$H$2:$H$3451*'DGE links'!$I$2:$I$3451*'DGE links'!$J$2:$J$3451)/SUMPRODUCT(('DGE links'!$F$2:$F$3451=A31)*'DGE links'!$H$2:$H$3451*'DGE links'!$J$2:$J$3451),"") -> 0.465 | K31: =IFERROR(AVERAGEIFS('ILO links'!$H$2:$H$674,'ILO links'!$G$2:$G$674,A31,'ILO links'!$J$2:$J$674,1),"") -> 0.465 | L31: =IF(AND(ISNUMBER(J31),ISNUMBER(K31)),J31-K31,"") -> 0 | M31: =IF(ISNUMBER(L31),ABS(L31),"") -> 0 | N31: =IF(ISNUMBER(M31),IF(M31<=Summary!$B$4,"Agree","Check"),IF(ISNUMBER(J31),"DGE only",IF(ISNUMBER(K31),"ILO only","Not scored"))) -> Agree | O31: =IF(ISNUMBER(J31),J31,IF(ISNUMBER(K31),K31,"")) -> 0.465 | P31: =IF(ISNUMBER(J31),"DGE",IF(ISNUMBER(K31),"ILO table","")) -> DGE
A32: 313 | B32: 352 | C32: Telecommunications and broadcasting technicians | D32: 311 321 343 352 | E32: 321 343 352 | F32: 321 343 352 | G32: 0.75 | H32: =SUMPRODUCT(('DGE links'!$F$2:$F$3451=A32)*1) -> 29 | I32: =SUMPRODUCT(('ILO links'!$G$2:$G$674=A32)*'ILO links'!$J$2:$J$674) -> 4 | J32: =IFERROR(SUMPRODUCT(('DGE links'!$F$2:$F$3451=A32)*'DGE links'!$H$2:$H$3451*'DGE links'!$I$2:$I$3451*'DGE links'!$J$2:$J$3451)/SUMPRODUCT(('DGE links'!$F$2:$F$3451=A32)*'DGE links'!$H$2:$H$3451*'DGE links'!$J$2:$J$3451),"") -> 0.36995517 | K32: =IFERROR(AVERAGEIFS('ILO links'!$H$2:$H$674,'ILO links'!$G$2:$G$674,A32,'ILO links'!$J$2:$J$674,1),"") -> 0.3525 | L32: =IF(AND(ISNUMBER(J32),ISNUMBER(K32)),J32-K32,"") -> 0.017455172 | M32: =IF(ISNUMBER(L32),ABS(L32),"") -> 0.017455172 | N32: =IF(ISNUMBER(M32),IF(M32<=Summary!$B$4,"Agree","Check"),IF(ISNUMBER(J32),"DGE only",IF(ISNUMBER(K32),"ILO only","Not scored"))) -> Agree | O32: =IF(ISNUMBER(J32),J32,IF(ISNUMBER(K32),K32,"")) -> 0.36995517 | P32: =IF(ISNUMBER(J32),"DGE",IF(ISNUMBER(K32),"ILO table","")) -> DGE
A33: 314 | B33: 315 | C33: Ship and aircraft controllers and technicians | D33: 315 | E33: 315 | F33: 315 | G33: 1 | H33: =SUMPRODUCT(('DGE links'!$F$2:$F$3451=A33)*1) -> 29 | I33: =SUMPRODUCT(('ILO links'!$G$2:$G$674=A33)*'ILO links'!$J$2:$J$674) -> 5 | J33: =IFERROR(SUMPRODUCT(('DGE links'!$F$2:$F$3451=A33)*'DGE links'!$H$2:$H$3451*'DGE links'!$I$2:$I$3451*'DGE links'!$J$2:$J$3451)/SUMPRODUCT(('DGE links'!$F$2:$F$3451=A33)*'DGE links'!$H$2:$H$3451*'DGE links'!$J$2:$J$3451),"") -> 0.288 | K33: =IFERROR(AVERAGEIFS('ILO links'!$H$2:$H$674,'ILO links'!$G$2:$G$674,A33,'ILO links'!$J$2:$J$674,1),"") -> 0.288 | L33: =IF(AND(ISNUMBER(J33),ISNUMBER(K33)),J33-K33,"") -> 0 | M33: =IF(ISNUMBER(L33),ABS(L33),"") -> 0 | N33: =IF(ISNUMBER(M33),IF(M33<=Summary!$B$4,"Agree","Check"),IF(ISNUMBER(J33),"DGE only",IF(ISNUMBER(K33),"ILO only","Not scored"))) -> Agree | O33: =IF(ISNUMBER(J33),J33,IF(ISNUMBER(K33),K33,"")) -> 0.288 | P33: =IF(ISNUMBER(J33),"DGE",IF(ISNUMBER(K33),"ILO table","")) -> DGE
A34: 315 | B34: 311 | C34: Physical and engineering science technicians | D34: 226 311 754 | E34: 226 311 325 335 754 | F34: 226 311 754 | G34: 0.6 | H34: =SUMPRODUCT(('DGE links'!$F$2:$F$3451=A34)*1) -> 9 | I34: =SUMPRODUCT(('ILO links'!$G$2:$G$674=A34)*'ILO links'!$J$2:$J$674) -> 9 | J34: =IFERROR(SUMPRODUCT(('DGE links'!$F$2:$F$3451=A34)*'DGE links'!$H$2:$H$3451*'DGE links'!$I$2:$I$3451*'DGE links'!$J$2:$J$3451)/SUMPRODUCT(('DGE links'!$F$2:$F$3451=A34)*'DGE links'!$H$2:$H$3451*'DGE links'!$J$2:$J$3451),"") -> 0.2374 | K34: =IFERROR(AVERAGEIFS('ILO links'!$H$2:$H$674,'ILO links'!$G$2:$G$674,A34,'ILO links'!$J$2:$J$674,1),"") -> 0.29555556 | L34: =IF(AND(ISNUMBER(J34),ISNUMBER(K34)),J34-K34,"") -> -0.058155556 | M34: =IF(ISNUMBER(L34),ABS(L34),"") -> 0.058155556 | N34: =IF(ISNUMBER(M34),IF(M34<=Summary!$B$4,"Agree","Check"),IF(ISNUMBER(J34),"DGE only",IF(ISNUMBER(K34),"ILO only","Not scored"))) -> Check | O34: =IF(ISNUMBER(J34),J34,IF(ISNUMBER(K34),K34,"")) -> 0.2374 | P34: =IF(ISNUMBER(J34),"DGE",IF(ISNUMBER(K34),"ILO table","")) -> DGE
A35: 321 | B35: 325 | C35: Other health associate professionals | D35: 213 314 321 325 | E35: 213 314 321 | F35: 213 314 321 | G35: 0.75 | H35: =SUMPRODUCT(('DGE links'!$F$2:$F$3451=A35)*1) -> 11 | I35: =SUMPRODUCT(('ILO links'!$G$2:$G$674=A35)*'ILO links'!$J$2:$J$674) -> 5 | J35: =IFERROR(SUMPRODUCT(('DGE links'!$F$2:$F$3451=A35)*'DGE links'!$H$2:$H$3451*'DGE links'!$I$2:$I$3451*'DGE links'!$J$2:$J$3451)/SUMPRODUCT(('DGE links'!$F$2:$F$3451=A35)*'DGE links'!$H$2:$H$3451*'DGE links'!$J$2:$J$3451),"") -> 0.27633636 | K35: =IFERROR(AVERAGEIFS('ILO links'!$H$2:$H$674,'ILO links'!$G$2:$G$674,A35,'ILO links'!$J$2:$J$674,1),"") -> 0.29 | L35: =IF(AND(ISNUMBER(J35),ISNUMBER(K35)),J35-K35,"") -> -0.013663636 | M35: =IF(ISNUMBER(L35),ABS(L35),"") -> 0.013663636 | N35: =IF(ISNUMBER(M35),IF(M35<=Summary!$B$4,"Agree","Check"),IF(ISNUMBER(J35),"DGE only",IF(ISNUMBER(K35),"ILO only","Not scored"))) -> Agree | O35: =IF(ISNUMBER(J35),J35,IF(ISNUMBER(K35),K35,"")) -> 0.27633636 | P35: =IF(ISNUMBER(J35),"DGE",IF(ISNUMBER(K35),"ILO table","")) -> DGE
... A49: 347 | B49: 265 | C49: Creative and performing artists | D49: 216 265 342 343 | E49: 216 264 265 342 343 731 | F49: 216 265 342 343 | G49: 0.66666667 | H49: =SUMPRODUCT(('DGE links'!$F$2:$F$3451=A49)*1) -> 40 | I49: =SUMPRODUCT(('ILO links'!$G$2:$G$674=A49)*'ILO links'!$J$2:$J$674) -> 13 | J49: =IFERROR(SUMPRODUCT(('DGE links'!$F$2:$F$3451=A49)*'DGE links'!$H$2:$H$3451*'DGE links'!$I$2:$I$3451*'DGE links'!$J$2:$J$3451)/SUMPRODUCT(('DGE links'!$F$2:$F$3451=A49)*'DGE links'!$H$2:$H$3451*'DGE links'!$J$2:$J$3451),"") -> 0.3109925 | K49: =IFERROR(AVERAGEIFS('ILO links'!$H$2:$H$674,'ILO links'!$G$2:$G$674,A49,'ILO links'!$J$2:$J$674,1),"") -> 0.32461538 | L49: =IF(AND(ISNUMBER(J49),ISNUMBER(K49)),J49-K49,"") -> -0.013622885 | M49: =IF(ISNUMBER(L49),ABS(L49),"") -> 0.013622885 | N49: =IF(ISNUMBER(M49),IF(M49<=Summary!$B$4,"Agree","Check"),IF(ISNUMBER(J49),"DGE only",IF(ISNUMBER(K49),"ILO only","Not scored"))) -> Agree | O49: =IF(ISNUMBER(J49),J49,IF(ISNUMBER(K49),K49,"")) -> 0.3109925 | P49: =IF(ISNUMBER(J49),"DGE",IF(ISNUMBER(K49),"ILO table","")) -> DGE
A50: 348 | E50: 341 | H50: =SUMPRODUCT(('DGE links'!$F$2:$F$3451=A50)*1) -> 0 | I50: =SUMPRODUCT(('ILO links'!$G$2:$G$674=A50)*'ILO links'!$J$2:$J$674) -> 1 | J50: =IFERROR(SUMPRODUCT(('DGE links'!$F$2:$F$3451=A50)*'DGE links'!$H$2:$H$3451*'DGE links'!$I$2:$I$3451*'DGE links'!$J$2:$J$3451)/SUMPRODUCT(('DGE links'!$F$2:$F$3451=A50)*'DGE links'!$H$2:$H$3451*'DGE links'!$J$2:$J$3451),"") | K50: =IFERROR(AVERAGEIFS('ILO links'!$H$2:$H$674,'ILO links'!$G$2:$G$674,A50,'ILO links'!$J$2:$J$674,1),"") -> 0.12 | L50: =IF(AND(ISNUMBER(J50),ISNUMBER(K50)),J50-K50,"") | M50: =IF(ISNUMBER(L50),ABS(L50),"") | N50: =IF(ISNUMBER(M50),IF(M50<=Summary!$B$4,"Agree","Check"),IF(ISNUMBER(J50),"DGE only",IF(ISNUMBER(K50),"ILO only","Not scored"))) -> ILO only | O50: =IF(ISNUMBER(J50),J50,IF(ISNUMBER(K50),K50,"")) -> 0.12 | P50: =IF(ISNUMBER(J50),"DGE",IF(ISNUMBER(K50),"ILO table","")) -> ILO table
A51: 411 | B51: 413 | C51: Keyboard operators | D51: 412 413 | E51: 334 412 413 | F51: 412 413 | G51: 0.66666667 | H51: =SUMPRODUCT(('DGE links'!$F$2:$F$3451=A51)*1) -> 18 | I51: =SUMPRODUCT(('ILO links'!$G$2:$G$674=A51)*'ILO links'!$J$2:$J$674) -> 6 | J51: =IFERROR(SUMPRODUCT(('DGE links'!$F$2:$F$3451=A51)*'DGE links'!$H$2:$H$3451*'DGE links'!$I$2:$I$3451*'DGE links'!$J$2:$J$3451)/SUMPRODUCT(('DGE links'!$F$2:$F$3451=A51)*'DGE links'!$H$2:$H$3451*'DGE links'!$J$2:$J$3451),"") -> 0.65388889 | K51: =IFERROR(AVERAGEIFS('ILO links'!$H$2:$H$674,'ILO links'!$G$2:$G$674,A51,'ILO links'!$J$2:$J$674,1),"") -> 0.57333333 | L51: =IF(AND(ISNUMBER(J51),ISNUMBER(K51)),J51-K51,"") -> 0.080555556 | M51: =IF(ISNUMBER(L51),ABS(L51),"") -> 0.080555556 | N51: =IF(ISNUMBER(M51),IF(M51<=Summary!$B$4,"Agree","Check"),IF(ISNUMBER(J51),"DGE only",IF(ISNUMBER(K51),"ILO only","Not scored"))) -> Check | O51: =IF(ISNUMBER(J51),J51,IF(ISNUMBER(K51),K51,"")) -> 0.65388889 | P51: =IF(ISNUMBER(J51),"DGE",IF(ISNUMBER(K51),"ILO table","")) -> DGE
A52: 412 | B52: 431 | C52: Numerical clerks | D52: 431 | E52: 334 431 | F52: 431 | G52: 0.5 | H52: =SUMPRODUCT(('DGE links'!$F$2:$F$3451=A52)*1) -> 10 | I52: =SUMPRODUCT(('ILO links'!$G$2:$G$674=A52)*'ILO links'!$J$2:$J$674) -> 4 | J52: =IFERROR(SUMPRODUCT(('DGE links'!$F$2:$F$3451=A52)*'DGE links'!$H$2:$H$3451*'DGE links'!$I$2:$I$3451*'DGE links'!$J$2:$J$3451)/SUMPRODUCT(('DGE links'!$F$2:$F$3451=A52)*'DGE links'!$H$2:$H$3451*'DGE links'!$J$2:$J$3451),"") -> 0.63 | K52: =IFERROR(AVERAGEIFS('ILO links'!$H$2:$H$674,'ILO links'!$G$2:$G$674,A52,'ILO links'!$J$2:$J$674,1),"") -> 0.58 | L52: =IF(AND(ISNUMBER(J52),ISNUMBER(K52)),J52-K52,"") -> 0.05 | M52: =IF(ISNUMBER(L52),ABS(L52),"") -> 0.05 | N52: =IF(ISNUMBER(M52),IF(M52<=Summary!$B$4,"Agree","Check"),IF(ISNUMBER(J52),"DGE only",IF(ISNUMBER(K52),"ILO only","Not scored"))) -> Agree | O52: =IF(ISNUMBER(J52),J52,IF(ISNUMBER(K52),K52,"")) -> 0.63 | P52: =IF(ISNUMBER(J52),"DGE",IF(ISNUMBER(K52),"ILO table","")) -> DGE
A53: 413 | B53: 432 | C53: Material-recording and transport clerks | D53: 432 | E53: 334 432 | F53: 432 | G53: 0.5 | H53: =SUMPRODUCT(('DGE links'!$F$2:$F$3451=A53)*1) -> 10 | I53: =SUMPRODUCT(('ILO links'!$G$2:$G$674=A53)*'ILO links'!$J$2:$J$674) -> 4 | J53: =IFERROR(SUMPRODUCT(('DGE links'!$F$2:$F$3451=A53)*'DGE links'!$H$2:$H$3451*'DGE links'!$I$2:$I$3451*'DGE links'!$J$2:$J$3451)/SUMPRODUCT(('DGE links'!$F$2:$F$3451=A53)*'DGE links'!$H$2:$H$3451*'DGE links'!$J$2:$J$3451),"") -> 0.4367 | K53: =IFERROR(AVERAGEIFS('ILO links'!$H$2:$H$674,'ILO links'!$G$2:$G$674,A53,'ILO links'!$J$2:$J$674,1),"") -> 0.435 | L53: =IF(AND(ISNUMBER(J53),ISNUMBER(K53)),J53-K53,"") -> 0.0017 | M53: =IF(ISNUMBER(L53),ABS(L53),"") -> 0.0017 | N53: =IF(ISNUMBER(M53),IF(M53<=Summary!$B$4,"Agree","Check"),IF(ISNUMBER(J53),"DGE only",IF(ISNUMBER(K53),"ILO only","Not scored"))) -> Agree | O53: =IF(ISNUMBER(J53),J53,IF(ISNUMBER(K53),K53,"")) -> 0.4367 | P53: =IF(ISNUMBER(J53),"DGE",IF(ISNUMBER(K53),"ILO table","")) -> DGE
A54: 414 | B54: 441 | C54: Other clerical support workers | D54: 334 441 | E54: 325 334 441 | F54: 334 441 | G54: 0.66666667 | H54: =SUMPRODUCT(('DGE links'!$F$2:$F$3451=A54)*1) -> 18 | I54: =SUMPRODUCT(('ILO links'!$G$2:$G$674=A54)*'ILO links'!$J$2:$J$674) -> 7 | J54: =IFERROR(SUMPRODUCT(('DGE links'!$F$2:$F$3451=A54)*'DGE links'!$H$2:$H$3451*'DGE links'!$I$2:$I$3451*'DGE links'!$J$2:$J$3451)/SUMPRODUCT(('DGE links'!$F$2:$F$3451=A54)*'DGE links'!$H$2:$H$3451*'DGE links'!$J$2:$J$3451),"") -> 0.50968333 | K54: =IFERROR(AVERAGEIFS('ILO links'!$H$2:$H$674,'ILO links'!$G$2:$G$674,A54,'ILO links'!$J$2:$J$674,1),"") -> 0.46857143 | L54: =IF(AND(ISNUMBER(J54),ISNUMBER(K54)),J54-K54,"") -> 0.041111905 | M54: =IF(ISNUMBER(L54),ABS(L54),"") -> 0.041111905 | N54: =IF(ISNUMBER(M54),IF(M54<=Summary!$B$4,"Agree","Check"),IF(ISNUMBER(J54),"DGE only",IF(ISNUMBER(K54),"ILO only","Not scored"))) -> Agree | O54: =IF(ISNUMBER(J54),J54,IF(ISNUMBER(K54),K54,"")) -> 0.50968333 | P54: =IF(ISNUMBER(J54),"DGE",IF(ISNUMBER(K54),"ILO table","")) -> DGE
A55: 419 | B55: 411 | C55: General office clerks | D55: 411 441 | E55: 334 411 422 441 | F55: 411 441 | G55: 0.5 | H55: =SUMPRODUCT(('DGE links'!$F$2:$F$3451=A55)*1) -> 11 | I55: =SUMPRODUCT(('ILO links'!$G$2:$G$674=A55)*'ILO links'!$J$2:$J$674) -> 5 | J55: =IFERROR(SUMPRODUCT(('DGE links'!$F$2:$F$3451=A55)*'DGE links'!$H$2:$H$3451*'DGE links'!$I$2:$I$3451*'DGE links'!$J$2:$J$3451)/SUMPRODUCT(('DGE links'!$F$2:$F$3451=A55)*'DGE links'!$H$2:$H$3451*'DGE links'!$J$2:$J$3451),"") -> 0.55845455 | K55: =IFERROR(AVERAGEIFS('ILO links'!$H$2:$H$674,'ILO links'!$G$2:$G$674,A55,'ILO links'!$J$2:$J$674,1),"") -> 0.562 | L55: =IF(AND(ISNUMBER(J55),ISNUMBER(K55)),J55-K55,"") -> -0.0035454545 | M55: =IF(ISNUMBER(L55),ABS(L55),"") -> 0.0035454545 | N55: =IF(ISNUMBER(M55),IF(M55<=Summary!$B$4,"Agree","Check"),IF(ISNUMBER(J55),"DGE only",IF(ISNUMBER(K55),"ILO only","Not scored"))) -> Agree | O55: =IF(ISNUMBER(J55),J55,IF(ISNUMBER(K55),K55,"")) -> 0.55845455 | P55: =IF(ISNUMBER(J55),"DGE",IF(ISNUMBER(K55),"ILO table","")) -> DGE
A56: 421 | B56: 421 | C56: Tellers, money collectors and related clerks | D56: 421 422 | E56: 421 523 | F56: 421 | G56: 0.33333333 | H56: =SUMPRODUCT(('DGE links'!$F$2:$F$3451=A56)*1) -> 16 | I56: =SUMPRODUCT(('ILO links'!$G$2:$G$674=A56)*'ILO links'!$J$2:$J$674) -> 5 | J56: =IFERROR(SUMPRODUCT(('DGE links'!$F$2:$F$3451=A56)*'DGE links'!$H$2:$H$3451*'DGE links'!$I$2:$I$3451*'DGE links'!$J$2:$J$3451)/SUMPRODUCT(('DGE links'!$F$2:$F$3451=A56)*'DGE links'!$H$2:$H$3451*'DGE links'!$J$2:$J$3451),"") -> 0.49484375 | K56: =IFERROR(AVERAGEIFS('ILO links'!$H$2:$H$674,'ILO links'!$G$2:$G$674,A56,'ILO links'!$J$2:$J$674,1),"") -> 0.466 | L56: =IF(AND(ISNUMBER(J56),ISNUMBER(K56)),J56-K56,"") -> 0.02884375 | M56: =IF(ISNUMBER(L56),ABS(L56),"") -> 0.02884375 | N56: =IF(ISNUMBER(M56),IF(M56<=Summary!$B$4,"Agree","Check"),IF(ISNUMBER(J56),"DGE only",IF(ISNUMBER(K56),"ILO only","Not scored"))) -> Agree | O56: =IF(ISNUMBER(J56),J56,IF(ISNUMBER(K56),K56,"")) -> 0.49484375 | P56: =IF(ISNUMBER(J56),"DGE",IF(ISNUMBER(K56),"ILO table","")) -> DGE
A57: 422 | B57: 422 | C57: Client information workers | D57: 422 | E57: 334 422 | F57: 422 | G57: 0.5 | H57: =SUMPRODUCT(('DGE links'!$F$2:$F$3451=A57)*1) -> 8 | I57: =SUMPRODUCT(('ILO links'!$G$2:$G$674=A57)*'ILO links'!$J$2:$J$674) -> 8 | J57: =IFERROR(SUMPRODUCT(('DGE links'!$F$2:$F$3451=A57)*'DGE links'!$H$2:$H$3451*'DGE links'!$I$2:$I$3451*'DGE links'!$J$2:$J$3451)/SUMPRODUCT(('DGE links'!$F$2:$F$3451=A57)*'DGE links'!$H$2:$H$3451*'DGE links'!$J$2:$J$3451),"") -> 0.5375 | K57: =IFERROR(AVERAGEIFS('ILO links'!$H$2:$H$674,'ILO links'!$G$2:$G$674,A57,'ILO links'!$J$2:$J$674,1),"") -> 0.5225 | L57: =IF(AND(ISNUMBER(J57),ISNUMBER(K57)),J57-K57,"") -> 0.015 | M57: =IF(ISNUMBER(L57),ABS(L57),"") -> 0.015 | N57: =IF(ISNUMBER(M57),IF(M57<=Summary!$B$4,"Agree","Check"),IF(ISNUMBER(J57),"DGE only",IF(ISNUMBER(K57),"ILO only","Not scored"))) -> Agree | O57: =IF(ISNUMBER(J57),J57,IF(ISNUMBER(K57),K57,"")) -> 0.5375 | P57: =IF(ISNUMBER(J57),"DGE",IF(ISNUMBER(K57),"ILO table","")) -> DGE
A58: 511 | B58: 511 | C58: Travel attendants, conductors and guides | D58: 511 | E58: 511 | F58: 511 | G58: 1 | H58: =SUMPRODUCT(('DGE links'!$F$2:$F$3451=A58)*1) -> 21 | I58: =SUMPRODUCT(('ILO links'!$G$2:$G$674=A58)*'ILO links'!$J$2:$J$674) -> 3 | J58: =IFERROR(SUMPRODUCT(('DGE links'!$F$2:$F$3451=A58)*'DGE links'!$H$2:$H$3451*'DGE links'!$I$2:$I$3451*'DGE links'!$J$2:$J$3451)/SUMPRODUCT(('DGE links'!$F$2:$F$3451=A58)*'DGE links'!$H$2:$H$3451*'DGE links'!$J$2:$J$3451),"") -> 0.2633 | K58: =IFERROR(AVERAGEIFS('ILO links'!$H$2:$H$674,'ILO links'!$G$2:$G$674,A58,'ILO links'!$J$2:$J$674,1),"") -> 0.26333333 | L58: =IF(AND(ISNUMBER(J58),ISNUMBER(K58)),J58-K58,"") -> -3.3333333e-05 | M58: =IF(ISNUMBER(L58),ABS(L58),"") -> 3.3333333e-05 | N58: =IF(ISNUMBER(M58),IF(M58<=Summary!$B$4,"Agree","Check"),IF(ISNUMBER(J58),"DGE only",IF(ISNUMBER(K58),"ILO only","Not scored"))) -> Agree | O58: =IF(ISNUMBER(J58),J58,IF(ISNUMBER(K58),K58,"")) -> 0.2633 | P58: =IF(ISNUMBER(J58),"DGE",IF(ISNUMBER(K58),"ILO table","")) -> DGE
A59: 512 | B59: 515 | C59: Building and housekeeping supervisors | D59: 343 512 513 515 531 | E59: 343 512 513 515 941 | F59: 343 512 513 515 | G59: 0.66666667 | H59: =SUMPRODUCT(('DGE links'!$F$2:$F$3451=A59)*1) -> 25 | I59: =SUMPRODUCT(('ILO links'!$G$2:$G$674=A59)*'ILO links'!$J$2:$J$674) -> 7 | J59: =IFERROR(SUMPRODUCT(('DGE links'!$F$2:$F$3451=A59)*'DGE links'!$H$2:$H$3451*'DGE links'!$I$2:$I$3451*'DGE links'!$J$2:$J$3451)/SUMPRODUCT(('DGE links'!$F$2:$F$3451=A59)*'DGE links'!$H$2:$H$3451*'DGE links'!$J$2:$J$3451),"") -> 0.2332 | K59: =IFERROR(AVERAGEIFS('ILO links'!$H$2:$H$674,'ILO links'!$G$2:$G$674,A59,'ILO links'!$J$2:$J$674,1),"") -> 0.22428571 | L59: =IF(AND(ISNUMBER(J59),ISNUMBER(K59)),J59-K59,"") -> 0.0089142857 | M59: =IF(ISNUMBER(L59),ABS(L59),"") -> 0.0089142857 | N59: =IF(ISNUMBER(M59),IF(M59<=Summary!$B$4,"Agree","Check"),IF(ISNUMBER(J59),"DGE only",IF(ISNUMBER(K59),"ILO only","Not scored"))) -> Agree | O59: =IF(ISNUMBER(J59),J59,IF(ISNUMBER(K59),K59,"")) -> 0.2332 | P59: =IF(ISNUMBER(J59),"DGE",IF(ISNUMBER(K59),"ILO table","")) -> DGE
A60: 513 | B60: 531 | C60: Child care workers and teachers’ aides | D60: 441 531 532 | E60: 325 516 531 532 | F60: 531 532 | G60: 0.4 | H60: =SUMPRODUCT(('DGE links'!$F$2:$F$3451=A60)*1) -> 8 | I60: =SUMPRODUCT(('ILO links'!$G$2:$G$674=A60)*'ILO links'!$J$2:$J$674) -> 7 | J60: =IFERROR(SUMPRODUCT(('DGE links'!$F$2:$F$3451=A60)*'DGE links'!$H$2:$H$3451*'DGE links'!$I$2:$I$3451*'DGE links'!$J$2:$J$3451)/SUMPRODUCT(('DGE links'!$F$2:$F$3451=A60)*'DGE links'!$H$2:$H$3451*'DGE links'!$J$2:$J$3451),"") -> 0.320725 | K60: =IFERROR(AVERAGEIFS('ILO links'!$H$2:$H$674,'ILO links'!$G$2:$G$674,A60,'ILO links'!$J$2:$J$674,1),"") -> 0.19 | L60: =IF(AND(ISNUMBER(J60),ISNUMBER(K60)),J60-K60,"") -> 0.130725 | M60: =IF(ISNUMBER(L60),ABS(L60),"") -> 0.130725 | N60: =IF(ISNUMBER(M60),IF(M60<=Summary!$B$4,"Agree","Check"),IF(ISNUMBER(J60),"DGE only",IF(ISNUMBER(K60),"ILO only","Not scored"))) -> Check | O60: =IF(ISNUMBER(J60),J60,IF(ISNUMBER(K60),K60,"")) -> 0.320725 | P60: =IF(ISNUMBER(J60),"DGE",IF(ISNUMBER(K60),"ILO table","")) -> DGE
A61: 514 | B61: 514 | C61: Hairdressers, beauticians and related workers | D61: 514 516 | E61: 514 516 | F61: 514 516 | G61: 1 | H61: =SUMPRODUCT(('DGE links'!$F$2:$F$3451=A61)*1) -> 15 | I61: =SUMPRODUCT(('ILO links'!$G$2:$G$674=A61)*'ILO links'!$J$2:$J$674) -> 5 | J61: =IFERROR(SUMPRODUCT(('DGE links'!$F$2:$F$3451=A61)*'DGE links'!$H$2:$H$3451*'DGE links'!$I$2:$I$3451*'DGE links'!$J$2:$J$3451)/SUMPRODUCT(('DGE links'!$F$2:$F$3451=A61)*'DGE links'!$H$2:$H$3451*'DGE links'!$J$2:$J$3451),"") -> 0.18345333 | K61: =IFERROR(AVERAGEIFS('ILO links'!$H$2:$H$674,'ILO links'!$G$2:$G$674,A61,'ILO links'!$J$2:$J$674,1),"") -> 0.19 | L61: =IF(AND(ISNUMBER(J61),ISNUMBER(K61)),J61-K61,"") -> -0.0065466667 | M61: =IF(ISNUMBER(L61),ABS(L61),"") -> 0.0065466667 | N61: =IF(ISNUMBER(M61),IF(M61<=Summary!$B$4,"Agree","Check"),IF(ISNUMBER(J61),"DGE only",IF(ISNUMBER(K61),"ILO only","Not scored"))) -> Agree | O61: =IF(ISNUMBER(J61),J61,IF(ISNUMBER(K61),K61,"")) -> 0.18345333 | P61: =IF(ISNUMBER(J61),"DGE",IF(ISNUMBER(K61),"ILO table","")) -> DGE
A62: 515 | B62: 516 | C62: Other personal services workers | D62: 516 | E62: 516 | F62: 516 | G62: 1 | H62: =SUMPRODUCT(('DGE links'!$F$2:$F$3451=A62)*1) -> 3 | I62: =SUMPRODUCT(('ILO links'!$G$2:$G$674=A62)*'ILO links'!$J$2:$J$674) -> 1 | J62: =IFERROR(SUMPRODUCT(('DGE links'!$F$2:$F$3451=A62)*'DGE links'!$H$2:$H$3451*'DGE links'!$I$2:$I$3451*'DGE links'!$J$2:$J$3451)/SUMPRODUCT(('DGE links'!$F$2:$F$3451=A62)*'DGE links'!$H$2:$H$3451*'DGE links'!$J$2:$J$3451),"") -> 0.2067 | K62: =IFERROR(AVERAGEIFS('ILO links'!$H$2:$H$674,'ILO links'!$G$2:$G$674,A62,'ILO links'!$J$2:$J$674,1),"") -> 0.3 | L62: =IF(AND(ISNUMBER(J62),ISNUMBER(K62)),J62-K62,"") -> -0.0933 | M62: =IF(ISNUMBER(L62),ABS(L62),"") -> 0.0933 | N62: =IF(ISNUMBER(M62),IF(M62<=Summary!$B$4,"Agree","Check"),IF(ISNUMBER(J62),"DGE only",IF(ISNUMBER(K62),"ILO only","Not scored"))) -> Check | O62: =IF(ISNUMBER(J62),J62,IF(ISNUMBER(K62),K62,"")) -> 0.2067 | P62: =IF(ISNUMBER(J62),"DGE",IF(ISNUMBER(K62),"ILO table","")) -> DGE
... A71: 615 | B71: 622 | C71: Fishery workers, hunters and trappers | D71: 622 754 | E71: 622 754 | F71: 622 754 | G71: 1 | H71: =SUMPRODUCT(('DGE links'!$F$2:$F$3451=A71)*1) -> 23 | I71: =SUMPRODUCT(('ILO links'!$G$2:$G$674=A71)*'ILO links'!$J$2:$J$674) -> 5 | J71: =IFERROR(SUMPRODUCT(('DGE links'!$F$2:$F$3451=A71)*'DGE links'!$H$2:$H$3451*'DGE links'!$I$2:$I$3451*'DGE links'!$J$2:$J$3451)/SUMPRODUCT(('DGE links'!$F$2:$F$3451=A71)*'DGE links'!$H$2:$H$3451*'DGE links'!$J$2:$J$3451),"") -> 0.16652174 | K71: =IFERROR(AVERAGEIFS('ILO links'!$H$2:$H$674,'ILO links'!$G$2:$G$674,A71,'ILO links'!$J$2:$J$674,1),"") -> 0.164 | L71: =IF(AND(ISNUMBER(J71),ISNUMBER(K71)),J71-K71,"") -> 0.0025217391 | M71: =IF(ISNUMBER(L71),ABS(L71),"") -> 0.0025217391 | N71: =IF(ISNUMBER(M71),IF(M71<=Summary!$B$4,"Agree","Check"),IF(ISNUMBER(J71),"DGE only",IF(ISNUMBER(K71),"ILO only","Not scored"))) -> Agree | O71: =IF(ISNUMBER(J71),J71,IF(ISNUMBER(K71),K71,"")) -> 0.16652174 | P71: =IF(ISNUMBER(J71),"DGE",IF(ISNUMBER(K71),"ILO table","")) -> DGE
A72: 620 | B72: 631 | C72: Subsistence crop farmers | D72: 631 | H72: =SUMPRODUCT(('DGE links'!$F$2:$F$3451=A72)*1) -> 2 | I72: =SUMPRODUCT(('ILO links'!$G$2:$G$674=A72)*'ILO links'!$J$2:$J$674) -> 0 | J72: =IFERROR(SUMPRODUCT(('DGE links'!$F$2:$F$3451=A72)*'DGE links'!$H$2:$H$3451*'DGE links'!$I$2:$I$3451*'DGE links'!$J$2:$J$3451)/SUMPRODUCT(('DGE links'!$F$2:$F$3451=A72)*'DGE links'!$H$2:$H$3451*'DGE links'!$J$2:$J$3451),"") -> 0.13 | K72: =IFERROR(AVERAGEIFS('ILO links'!$H$2:$H$674,'ILO links'!$G$2:$G$674,A72,'ILO links'!$J$2:$J$674,1),"") | L72: =IF(AND(ISNUMBER(J72),ISNUMBER(K72)),J72-K72,"") | M72: =IF(ISNUMBER(L72),ABS(L72),"") | N72: =IF(ISNUMBER(M72),IF(M72<=Summary!$B$4,"Agree","Check"),IF(ISNUMBER(J72),"DGE only",IF(ISNUMBER(K72),"ILO only","Not scored"))) -> DGE only | O72: =IF(ISNUMBER(J72),J72,IF(ISNUMBER(K72),K72,"")) -> 0.13 | P72: =IF(ISNUMBER(J72),"DGE",IF(ISNUMBER(K72),"ILO table","")) -> DGE
A73: 621 | E73: 631 632 633 634 | H73: =SUMPRODUCT(('DGE links'!$F$2:$F$3451=A73)*1) -> 0 | I73: =SUMPRODUCT(('ILO links'!$G$2:$G$674=A73)*'ILO links'!$J$2:$J$674) -> 4 | J73: =IFERROR(SUMPRODUCT(('DGE links'!$F$2:$F$3451=A73)*'DGE links'!$H$2:$H$3451*'DGE links'!$I$2:$I$3451*'DGE links'!$J$2:$J$3451)/SUMPRODUCT(('DGE links'!$F$2:$F$3451=A73)*'DGE links'!$H$2:$H$3451*'DGE links'!$J$2:$J$3451),"") | K73: =IFERROR(AVERAGEIFS('ILO links'!$H$2:$H$674,'ILO links'!$G$2:$G$674,A73,'ILO links'!$J$2:$J$674,1),"") -> 0.125 | L73: =IF(AND(ISNUMBER(J73),ISNUMBER(K73)),J73-K73,"") | M73: =IF(ISNUMBER(L73),ABS(L73),"") | N73: =IF(ISNUMBER(M73),IF(M73<=Summary!$B$4,"Agree","Check"),IF(ISNUMBER(J73),"DGE only",IF(ISNUMBER(K73),"ILO only","Not scored"))) -> ILO only | O73: =IF(ISNUMBER(J73),J73,IF(ISNUMBER(K73),K73,"")) -> 0.125 | P73: =IF(ISNUMBER(J73),"DGE",IF(ISNUMBER(K73),"ILO table","")) -> ILO table
A74: 711 | B74: 811 | C74: Mining and mineral processing plant operators | D74: 711 754 811 | E74: 312 711 754 811 | F74: 711 754 811 | G74: 0.75 | H74: =SUMPRODUCT(('DGE links'!$F$2:$F$3451=A74)*1) -> 39 | I74: =SUMPRODUCT(('ILO links'!$G$2:$G$674=A74)*'ILO links'!$J$2:$J$674) -> 4 | J74: =IFERROR(SUMPRODUCT(('DGE links'!$F$2:$F$3451=A74)*'DGE links'!$H$2:$H$3451*'DGE links'!$I$2:$I$3451*'DGE links'!$J$2:$J$3451)/SUMPRODUCT(('DGE links'!$F$2:$F$3451=A74)*'DGE links'!$H$2:$H$3451*'DGE links'!$J$2:$J$3451),"") -> 0.182 | K74: =IFERROR(AVERAGEIFS('ILO links'!$H$2:$H$674,'ILO links'!$G$2:$G$674,A74,'ILO links'!$J$2:$J$674,1),"") -> 0.1725 | L74: =IF(AND(ISNUMBER(J74),ISNUMBER(K74)),J74-K74,"") -> 0.0095 | M74: =IF(ISNUMBER(L74),ABS(L74),"") -> 0.0095 | N74: =IF(ISNUMBER(M74),IF(M74<=Summary!$B$4,"Agree","Check"),IF(ISNUMBER(J74),"DGE only",IF(ISNUMBER(K74),"ILO only","Not scored"))) -> Agree | O74: =IF(ISNUMBER(J74),J74,IF(ISNUMBER(K74),K74,"")) -> 0.182 | P74: =IF(ISNUMBER(J74),"DGE",IF(ISNUMBER(K74),"ILO table","")) -> DGE
A75: 712 | B75: 711 | C75: Building frame and related trades workers | D75: 711 | E75: 312 711 | F75: 711 | G75: 0.5 | H75: =SUMPRODUCT(('DGE links'!$F$2:$F$3451=A75)*1) -> 27 | I75: =SUMPRODUCT(('ILO links'!$G$2:$G$674=A75)*'ILO links'!$J$2:$J$674) -> 7 | J75: =IFERROR(SUMPRODUCT(('DGE links'!$F$2:$F$3451=A75)*'DGE links'!$H$2:$H$3451*'DGE links'!$I$2:$I$3451*'DGE links'!$J$2:$J$3451)/SUMPRODUCT(('DGE links'!$F$2:$F$3451=A75)*'DGE links'!$H$2:$H$3451*'DGE links'!$J$2:$J$3451),"") -> 0.11 | K75: =IFERROR(AVERAGEIFS('ILO links'!$H$2:$H$674,'ILO links'!$G$2:$G$674,A75,'ILO links'!$J$2:$J$674,1),"") -> 0.13428571 | L75: =IF(AND(ISNUMBER(J75),ISNUMBER(K75)),J75-K75,"") -> -0.024285714 | M75: =IF(ISNUMBER(L75),ABS(L75),"") -> 0.024285714 | N75: =IF(ISNUMBER(M75),IF(M75<=Summary!$B$4,"Agree","Check"),IF(ISNUMBER(J75),"DGE only",IF(ISNUMBER(K75),"ILO only","Not scored"))) -> Agree | O75: =IF(ISNUMBER(J75),J75,IF(ISNUMBER(K75),K75,"")) -> 0.11 | P75: =IF(ISNUMBER(J75),"DGE",IF(ISNUMBER(K75),"ILO table","")) -> DGE
A76: 713 | B76: 712 | C76: Building finishers and related trades workers | D76: 312 712 741 | E76: 712 741 | F76: 712 741 | G76: 0.66666667 | H76: =SUMPRODUCT(('DGE links'!$F$2:$F$3451=A76)*1) -> 37 | I76: =SUMPRODUCT(('ILO links'!$G$2:$G$674=A76)*'ILO links'!$J$2:$J$674) -> 8 | J76: =IFERROR(SUMPRODUCT(('DGE links'!$F$2:$F$3451=A76)*'DGE links'!$H$2:$H$3451*'DGE links'!$I$2:$I$3451*'DGE links'!$J$2:$J$3451)/SUMPRODUCT(('DGE links'!$F$2:$F$3451=A76)*'DGE links'!$H$2:$H$3451*'DGE links'!$J$2:$J$3451),"") -> 0.1650027 | K76: =IFERROR(AVERAGEIFS('ILO links'!$H$2:$H$674,'ILO links'!$G$2:$G$674,A76,'ILO links'!$J$2:$J$674,1),"") -> 0.14875 | L76: =IF(AND(ISNUMBER(J76),ISNUMBER(K76)),J76-K76,"") -> 0.016252703 | M76: =IF(ISNUMBER(L76),ABS(L76),"") -> 0.016252703 | N76: =IF(ISNUMBER(M76),IF(M76<=Summary!$B$4,"Agree","Check"),IF(ISNUMBER(J76),"DGE only",IF(ISNUMBER(K76),"ILO only","Not scored"))) -> Agree | O76: =IF(ISNUMBER(J76),J76,IF(ISNUMBER(K76),K76,"")) -> 0.1650027 | P76: =IF(ISNUMBER(J76),"DGE",IF(ISNUMBER(K76),"ILO table","")) -> DGE
A77: 714 | B77: 713 | C77: Painters, building structure cleaners and related trades workers | D77: 312 713 | E77: 713 754 | F77: 713 | G77: 0.33333333 | H77: =SUMPRODUCT(('DGE links'!$F$2:$F$3451=A77)*1) -> 16 | I77: =SUMPRODUCT(('ILO links'!$G$2:$G$674=A77)*'ILO links'!$J$2:$J$674) -> 4 | J77: =IFERROR(SUMPRODUCT(('DGE links'!$F$2:$F$3451=A77)*'DGE links'!$H$2:$H$3451*'DGE links'!$I$2:$I$3451*'DGE links'!$J$2:$J$3451)/SUMPRODUCT(('DGE links'!$F$2:$F$3451=A77)*'DGE links'!$H$2:$H$3451*'DGE links'!$J$2:$J$3451),"") -> 0.137475 | K77: =IFERROR(AVERAGEIFS('ILO links'!$H$2:$H$674,'ILO links'!$G$2:$G$674,A77,'ILO links'!$J$2:$J$674,1),"") -> 0.1175 | L77: =IF(AND(ISNUMBER(J77),ISNUMBER(K77)),J77-K77,"") -> 0.019975 | M77: =IF(ISNUMBER(L77),ABS(L77),"") -> 0.019975 | N77: =IF(ISNUMBER(M77),IF(M77<=Summary!$B$4,"Agree","Check"),IF(ISNUMBER(J77),"DGE only",IF(ISNUMBER(K77),"ILO only","Not scored"))) -> Agree | O77: =IF(ISNUMBER(J77),J77,IF(ISNUMBER(K77),K77,"")) -> 0.137475 | P77: =IF(ISNUMBER(J77),"DGE",IF(ISNUMBER(K77),"ILO table","")) -> DGE
A78: 721 | B78: 721 | C78: Sheet and structural metal workers, moulders and welders, and related workers | D78: 312 721 754 | E78: 721 754 | F78: 721 754 | G78: 0.66666667 | H78: =SUMPRODUCT(('DGE links'!$F$2:$F$3451=A78)*1) -> 40 | I78: =SUMPRODUCT(('ILO links'!$G$2:$G$674=A78)*'ILO links'!$J$2:$J$674) -> 6 | J78: =IFERROR(SUMPRODUCT(('DGE links'!$F$2:$F$3451=A78)*'DGE links'!$H$2:$H$3451*'DGE links'!$I$2:$I$3451*'DGE links'!$J$2:$J$3451)/SUMPRODUCT(('DGE links'!$F$2:$F$3451=A78)*'DGE links'!$H$2:$H$3451*'DGE links'!$J$2:$J$3451),"") -> 0.152485 | K78: =IFERROR(AVERAGEIFS('ILO links'!$H$2:$H$674,'ILO links'!$G$2:$G$674,A78,'ILO links'!$J$2:$J$674,1),"") -> 0.145 | L78: =IF(AND(ISNUMBER(J78),ISNUMBER(K78)),J78-K78,"") -> 0.007485 | M78: =IF(ISNUMBER(L78),ABS(L78),"") -> 0.007485 | N78: =IF(ISNUMBER(M78),IF(M78<=Summary!$B$4,"Agree","Check"),IF(ISNUMBER(J78),"DGE only",IF(ISNUMBER(K78),"ILO only","Not scored"))) -> Agree | O78: =IF(ISNUMBER(J78),J78,IF(ISNUMBER(K78),K78,"")) -> 0.152485 | P78: =IF(ISNUMBER(J78),"DGE",IF(ISNUMBER(K78),"ILO table","")) -> DGE
A79: 722 | B79: 722 | C79: Blacksmiths, toolmakers and related trades workers | D79: 312 722 | E79: 722 | F79: 722 | G79: 0.5 | H79: =SUMPRODUCT(('DGE links'!$F$2:$F$3451=A79)*1) -> 35 | I79: =SUMPRODUCT(('ILO links'!$G$2:$G$674=A79)*'ILO links'!$J$2:$J$674) -> 4 | J79: =IFERROR(SUMPRODUCT(('DGE links'!$F$2:$F$3451=A79)*'DGE links'!$H$2:$H$3451*'DGE links'!$I$2:$I$3451*'DGE links'!$J$2:$J$3451)/SUMPRODUCT(('DGE links'!$F$2:$F$3451=A79)*'DGE links'!$H$2:$H$3451*'DGE links'!$J$2:$J$3451),"") -> 0.18724 | K79: =IFERROR(AVERAGEIFS('ILO links'!$H$2:$H$674,'ILO links'!$G$2:$G$674,A79,'ILO links'!$J$2:$J$674,1),"") -> 0.18 | L79: =IF(AND(ISNUMBER(J79),ISNUMBER(K79)),J79-K79,"") -> 0.00724 | M79: =IF(ISNUMBER(L79),ABS(L79),"") -> 0.00724 | N79: =IF(ISNUMBER(M79),IF(M79<=Summary!$B$4,"Agree","Check"),IF(ISNUMBER(J79),"DGE only",IF(ISNUMBER(K79),"ILO only","Not scored"))) -> Agree | O79: =IF(ISNUMBER(J79),J79,IF(ISNUMBER(K79),K79,"")) -> 0.18724 | P79: =IF(ISNUMBER(J79),"DGE",IF(ISNUMBER(K79),"ILO table","")) -> DGE
A80: 723 | B80: 723 | C80: Machinery mechanics and repairers | D80: 312 712 723 | E80: 712 723 | F80: 712 723 | G80: 0.66666667 | H80: =SUMPRODUCT(('DGE links'!$F$2:$F$3451=A80)*1) -> 47 | I80: =SUMPRODUCT(('ILO links'!$G$2:$G$674=A80)*'ILO links'!$J$2:$J$674) -> 5 | J80: =IFERROR(SUMPRODUCT(('DGE links'!$F$2:$F$3451=A80)*'DGE links'!$H$2:$H$3451*'DGE links'!$I$2:$I$3451*'DGE links'!$J$2:$J$3451)/SUMPRODUCT(('DGE links'!$F$2:$F$3451=A80)*'DGE links'!$H$2:$H$3451*'DGE links'!$J$2:$J$3451),"") -> 0.1758617 | K80: =IFERROR(AVERAGEIFS('ILO links'!$H$2:$H$674,'ILO links'!$G$2:$G$674,A80,'ILO links'!$J$2:$J$674,1),"") -> 0.176 | L80: =IF(AND(ISNUMBER(J80),ISNUMBER(K80)),J80-K80,"") -> -0.00013829787 | M80: =IF(ISNUMBER(L80),ABS(L80),"") -> 0.00013829787 | N80: =IF(ISNUMBER(M80),IF(M80<=Summary!$B$4,"Agree","Check"),IF(ISNUMBER(J80),"DGE only",IF(ISNUMBER(K80),"ILO only","Not scored"))) -> Agree | O80: =IF(ISNUMBER(J80),J80,IF(ISNUMBER(K80),K80,"")) -> 0.1758617 | P80: =IF(ISNUMBER(J80),"DGE",IF(ISNUMBER(K80),"ILO table","")) -> DGE
A81: 724 | B81: 742 | C81: Electronics and telecommunications installers and repairers | D81: 312 741 742 | E81: 741 742 | F81: 741 742 | G81: 0.66666667 | H81: =SUMPRODUCT(('DGE links'!$F$2:$F$3451=A81)*1) -> 40 | I81: =SUMPRODUCT(('ILO links'!$G$2:$G$674=A81)*'ILO links'!$J$2:$J$674) -> 4 | J81: =IFERROR(SUMPRODUCT(('DGE links'!$F$2:$F$3451=A81)*'DGE links'!$H$2:$H$3451*'DGE links'!$I$2:$I$3451*'DGE links'!$J$2:$J$3451)/SUMPRODUCT(('DGE links'!$F$2:$F$3451=A81)*'DGE links'!$H$2:$H$3451*'DGE links'!$J$2:$J$3451),"") -> 0.2208375 | K81: =IFERROR(AVERAGEIFS('ILO links'!$H$2:$H$674,'ILO links'!$G$2:$G$674,A81,'ILO links'!$J$2:$J$674,1),"") -> 0.2025 | L81: =IF(AND(ISNUMBER(J81),ISNUMBER(K81)),J81-K81,"") -> 0.0183375 | M81: =IF(ISNUMBER(L81),ABS(L81),"") -> 0.0183375 | N81: =IF(ISNUMBER(M81),IF(M81<=Summary!$B$4,"Agree","Check"),IF(ISNUMBER(J81),"DGE only",IF(ISNUMBER(K81),"ILO only","Not scored"))) -> Agree | O81: =IF(ISNUMBER(J81),J81,IF(ISNUMBER(K81),K81,"")) -> 0.2208375 | P81: =IF(ISNUMBER(J81),"DGE",IF(ISNUMBER(K81),"ILO table","")) -> DGE
A82: 731 | B82: 731 | C82: Handicraft workers | D82: 312 321 731 818 | E82: 321 731 | F82: 321 731 | G82: 0.5 | H82: =SUMPRODUCT(('DGE links'!$F$2:$F$3451=A82)*1) -> 53 | I82: =SUMPRODUCT(('ILO links'!$G$2:$G$674=A82)*'ILO links'!$J$2:$J$674) -> 4 | J82: =IFERROR(SUMPRODUCT(('DGE links'!$F$2:$F$3451=A82)*'DGE links'!$H$2:$H$3451*'DGE links'!$I$2:$I$3451*'DGE links'!$J$2:$J$3451)/SUMPRODUCT(('DGE links'!$F$2:$F$3451=A82)*'DGE links'!$H$2:$H$3451*'DGE links'!$J$2:$J$3451),"") -> 0.17871132 | K82: =IFERROR(AVERAGEIFS('ILO links'!$H$2:$H$674,'ILO links'!$G$2:$G$674,A82,'ILO links'!$J$2:$J$674,1),"") -> 0.1775 | L82: =IF(AND(ISNUMBER(J82),ISNUMBER(K82)),J82-K82,"") -> 0.0012113208 | M82: =IF(ISNUMBER(L82),ABS(L82),"") -> 0.0012113208 | N82: =IF(ISNUMBER(M82),IF(M82<=Summary!$B$4,"Agree","Check"),IF(ISNUMBER(J82),"DGE only",IF(ISNUMBER(K82),"ILO only","Not scored"))) -> Agree | O82: =IF(ISNUMBER(J82),J82,IF(ISNUMBER(K82),K82,"")) -> 0.17871132 | P82: =IF(ISNUMBER(J82),"DGE",IF(ISNUMBER(K82),"ILO table","")) -> DGE
A83: 732 | B83: 731 | C83: Handicraft workers | D83: 731 | E83: 731 754 | F83: 731 | G83: 0.5 | H83: =SUMPRODUCT(('DGE links'!$F$2:$F$3451=A83)*1) -> 51 | I83: =SUMPRODUCT(('ILO links'!$G$2:$G$674=A83)*'ILO links'!$J$2:$J$674) -> 4 | J83: =IFERROR(SUMPRODUCT(('DGE links'!$F$2:$F$3451=A83)*'DGE links'!$H$2:$H$3451*'DGE links'!$I$2:$I$3451*'DGE links'!$J$2:$J$3451)/SUMPRODUCT(('DGE links'!$F$2:$F$3451=A83)*'DGE links'!$H$2:$H$3451*'DGE links'!$J$2:$J$3451),"") -> 0.1688 | K83: =IFERROR(AVERAGEIFS('ILO links'!$H$2:$H$674,'ILO links'!$G$2:$G$674,A83,'ILO links'!$J$2:$J$674,1),"") -> 0.1725 | L83: =IF(AND(ISNUMBER(J83),ISNUMBER(K83)),J83-K83,"") -> -0.0037 | M83: =IF(ISNUMBER(L83),ABS(L83),"") -> 0.0037 | N83: =IF(ISNUMBER(M83),IF(M83<=Summary!$B$4,"Agree","Check"),IF(ISNUMBER(J83),"DGE only",IF(ISNUMBER(K83),"ILO only","Not scored"))) -> Agree | O83: =IF(ISNUMBER(J83),J83,IF(ISNUMBER(K83),K83,"")) -> 0.1688 | P83: =IF(ISNUMBER(J83),"DGE",IF(ISNUMBER(K83),"ILO table","")) -> DGE
A84: 733 | B84: 731 | C84: Handicraft workers | D84: 731 | E84: 731 | F84: 731 | G84: 1 | H84: =SUMPRODUCT(('DGE links'!$F$2:$F$3451=A84)*1) -> 8 | I84: =SUMPRODUCT(('ILO links'!$G$2:$G$674=A84)*'ILO links'!$J$2:$J$674) -> 3 | J84: =IFERROR(SUMPRODUCT(('DGE links'!$F$2:$F$3451=A84)*'DGE links'!$H$2:$H$3451*'DGE links'!$I$2:$I$3451*'DGE links'!$J$2:$J$3451)/SUMPRODUCT(('DGE links'!$F$2:$F$3451=A84)*'DGE links'!$H$2:$H$3451*'DGE links'!$J$2:$J$3451),"") -> 0.1688 | K84: =IFERROR(AVERAGEIFS('ILO links'!$H$2:$H$674,'ILO links'!$G$2:$G$674,A84,'ILO links'!$J$2:$J$674,1),"") -> 0.135 | L84: =IF(AND(ISNUMBER(J84),ISNUMBER(K84)),J84-K84,"") -> 0.0338 | M84: =IF(ISNUMBER(L84),ABS(L84),"") -> 0.0338 | N84: =IF(ISNUMBER(M84),IF(M84<=Summary!$B$4,"Agree","Check"),IF(ISNUMBER(J84),"DGE only",IF(ISNUMBER(K84),"ILO only","Not scored"))) -> Agree | O84: =IF(ISNUMBER(J84),J84,IF(ISNUMBER(K84),K84,"")) -> 0.1688 | P84: =IF(ISNUMBER(J84),"DGE",IF(ISNUMBER(K84),"ILO table","")) -> DGE
A85: 734 | B85: 732 | C85: Printing trades workers | D85: 312 732 813 | E85: 732 813 | F85: 732 813 | G85: 0.66666667 | H85: =SUMPRODUCT(('DGE links'!$F$2:$F$3451=A85)*1) -> 45 | I85: =SUMPRODUCT(('ILO links'!$G$2:$G$674=A85)*'ILO links'!$J$2:$J$674) -> 4 | J85: =IFERROR(SUMPRODUCT(('DGE links'!$F$2:$F$3451=A85)*'DGE links'!$H$2:$H$3451*'DGE links'!$I$2:$I$3451*'DGE links'!$J$2:$J$3451)/SUMPRODUCT(('DGE links'!$F$2:$F$3451=A85)*'DGE links'!$H$2:$H$3451*'DGE links'!$J$2:$J$3451),"") -> 0.28056667 | K85: =IFERROR(AVERAGEIFS('ILO links'!$H$2:$H$674,'ILO links'!$G$2:$G$674,A85,'ILO links'!$J$2:$J$674,1),"") -> 0.28 | L85: =IF(AND(ISNUMBER(J85),ISNUMBER(K85)),J85-K85,"") -> 0.00056666667 | M85: =IF(ISNUMBER(L85),ABS(L85),"") -> 0.00056666667 | N85: =IF(ISNUMBER(M85),IF(M85<=Summary!$B$4,"Agree","Check"),IF(ISNUMBER(J85),"DGE only",IF(ISNUMBER(K85),"ILO only","Not scored"))) -> Agree | O85: =IF(ISNUMBER(J85),J85,IF(ISNUMBER(K85),K85,"")) -> 0.28056667 | P85: =IF(ISNUMBER(J85),"DGE",IF(ISNUMBER(K85),"ILO table","")) -> DGE
... A115: 916 | B115: 961 | C115: Refuse workers | D115: 961 962 | E115: 961 962 | F115: 961 962 | G115: 1 | H115: =SUMPRODUCT(('DGE links'!$F$2:$F$3451=A115)*1) -> 7 | I115: =SUMPRODUCT(('ILO links'!$G$2:$G$674=A115)*'ILO links'!$J$2:$J$674) -> 5 | J115: =IFERROR(SUMPRODUCT(('DGE links'!$F$2:$F$3451=A115)*'DGE links'!$H$2:$H$3451*'DGE links'!$I$2:$I$3451*'DGE links'!$J$2:$J$3451)/SUMPRODUCT(('DGE links'!$F$2:$F$3451=A115)*'DGE links'!$H$2:$H$3451*'DGE links'!$J$2:$J$3451),"") -> 0.13828571 | K115: =IFERROR(AVERAGEIFS('ILO links'!$H$2:$H$674,'ILO links'!$G$2:$G$674,A115,'ILO links'!$J$2:$J$674,1),"") -> 0.112 | L115: =IF(AND(ISNUMBER(J115),ISNUMBER(K115)),J115-K115,"") -> 0.026285714 | M115: =IF(ISNUMBER(L115),ABS(L115),"") -> 0.026285714 | N115: =IF(ISNUMBER(M115),IF(M115<=Summary!$B$4,"Agree","Check"),IF(ISNUMBER(J115),"DGE only",IF(ISNUMBER(K115),"ILO only","Not scored"))) -> Agree | O115: =IF(ISNUMBER(J115),J115,IF(ISNUMBER(K115),K115,"")) -> 0.13828571 | P115: =IF(ISNUMBER(J115),"DGE",IF(ISNUMBER(K115),"ILO table","")) -> DGE
A116: 920 | B116: 921 | C116: Agricultural, forestry and fishery labourers | D116: 921 | H116: =SUMPRODUCT(('DGE links'!$F$2:$F$3451=A116)*1) -> 7 | I116: =SUMPRODUCT(('ILO links'!$G$2:$G$674=A116)*'ILO links'!$J$2:$J$674) -> 0 | J116: =IFERROR(SUMPRODUCT(('DGE links'!$F$2:$F$3451=A116)*'DGE links'!$H$2:$H$3451*'DGE links'!$I$2:$I$3451*'DGE links'!$J$2:$J$3451)/SUMPRODUCT(('DGE links'!$F$2:$F$3451=A116)*'DGE links'!$H$2:$H$3451*'DGE links'!$J$2:$J$3451),"") -> 0.1067 | K116: =IFERROR(AVERAGEIFS('ILO links'!$H$2:$H$674,'ILO links'!$G$2:$G$674,A116,'ILO links'!$J$2:$J$674,1),"") | L116: =IF(AND(ISNUMBER(J116),ISNUMBER(K116)),J116-K116,"") | M116: =IF(ISNUMBER(L116),ABS(L116),"") | N116: =IF(ISNUMBER(M116),IF(M116<=Summary!$B$4,"Agree","Check"),IF(ISNUMBER(J116),"DGE only",IF(ISNUMBER(K116),"ILO only","Not scored"))) -> DGE only | O116: =IF(ISNUMBER(J116),J116,IF(ISNUMBER(K116),K116,"")) -> 0.1067 | P116: =IF(ISNUMBER(J116),"DGE",IF(ISNUMBER(K116),"ILO table","")) -> DGE
A117: 921 | E117: 921 | H117: =SUMPRODUCT(('DGE links'!$F$2:$F$3451=A117)*1) -> 0 | I117: =SUMPRODUCT(('ILO links'!$G$2:$G$674=A117)*'ILO links'!$J$2:$J$674) -> 6 | J117: =IFERROR(SUMPRODUCT(('DGE links'!$F$2:$F$3451=A117)*'DGE links'!$H$2:$H$3451*'DGE links'!$I$2:$I$3451*'DGE links'!$J$2:$J$3451)/SUMPRODUCT(('DGE links'!$F$2:$F$3451=A117)*'DGE links'!$H$2:$H$3451*'DGE links'!$J$2:$J$3451),"") | K117: =IFERROR(AVERAGEIFS('ILO links'!$H$2:$H$674,'ILO links'!$G$2:$G$674,A117,'ILO links'!$J$2:$J$674,1),"") -> 0.10666667 | L117: =IF(AND(ISNUMBER(J117),ISNUMBER(K117)),J117-K117,"") | M117: =IF(ISNUMBER(L117),ABS(L117),"") | N117: =IF(ISNUMBER(M117),IF(M117<=Summary!$B$4,"Agree","Check"),IF(ISNUMBER(J117),"DGE only",IF(ISNUMBER(K117),"ILO only","Not scored"))) -> ILO only | O117: =IF(ISNUMBER(J117),J117,IF(ISNUMBER(K117),K117,"")) -> 0.10666667 | P117: =IF(ISNUMBER(J117),"DGE",IF(ISNUMBER(K117),"ILO table","")) -> ILO table
A118: 931 | B118: 931 | C118: Mining and construction labourers | D118: 931 | E118: 931 | F118: 931 | G118: 1 | H118: =SUMPRODUCT(('DGE links'!$F$2:$F$3451=A118)*1) -> 8 | I118: =SUMPRODUCT(('ILO links'!$G$2:$G$674=A118)*'ILO links'!$J$2:$J$674) -> 3 | J118: =IFERROR(SUMPRODUCT(('DGE links'!$F$2:$F$3451=A118)*'DGE links'!$H$2:$H$3451*'DGE links'!$I$2:$I$3451*'DGE links'!$J$2:$J$3451)/SUMPRODUCT(('DGE links'!$F$2:$F$3451=A118)*'DGE links'!$H$2:$H$3451*'DGE links'!$J$2:$J$3451),"") -> 0.0967 | K118: =IFERROR(AVERAGEIFS('ILO links'!$H$2:$H$674,'ILO links'!$G$2:$G$674,A118,'ILO links'!$J$2:$J$674,1),"") -> 0.096666667 | L118: =IF(AND(ISNUMBER(J118),ISNUMBER(K118)),J118-K118,"") -> 3.3333333e-05 | M118: =IF(ISNUMBER(L118),ABS(L118),"") -> 3.3333333e-05 | N118: =IF(ISNUMBER(M118),IF(M118<=Summary!$B$4,"Agree","Check"),IF(ISNUMBER(J118),"DGE only",IF(ISNUMBER(K118),"ILO only","Not scored"))) -> Agree | O118: =IF(ISNUMBER(J118),J118,IF(ISNUMBER(K118),K118,"")) -> 0.0967 | P118: =IF(ISNUMBER(J118),"DGE",IF(ISNUMBER(K118),"ILO table","")) -> DGE
A119: 932 | B119: 932 | C119: Manufacturing labourers | D119: 932 | E119: 932 961 | F119: 932 | G119: 0.5 | H119: =SUMPRODUCT(('DGE links'!$F$2:$F$3451=A119)*1) -> 14 | I119: =SUMPRODUCT(('ILO links'!$G$2:$G$674=A119)*'ILO links'!$J$2:$J$674) -> 3 | J119: =IFERROR(SUMPRODUCT(('DGE links'!$F$2:$F$3451=A119)*'DGE links'!$H$2:$H$3451*'DGE links'!$I$2:$I$3451*'DGE links'!$J$2:$J$3451)/SUMPRODUCT(('DGE links'!$F$2:$F$3451=A119)*'DGE links'!$H$2:$H$3451*'DGE links'!$J$2:$J$3451),"") -> 0.16 | K119: =IFERROR(AVERAGEIFS('ILO links'!$H$2:$H$674,'ILO links'!$G$2:$G$674,A119,'ILO links'!$J$2:$J$674,1),"") -> 0.16666667 | L119: =IF(AND(ISNUMBER(J119),ISNUMBER(K119)),J119-K119,"") -> -0.0066666667 | M119: =IF(ISNUMBER(L119),ABS(L119),"") -> 0.0066666667 | N119: =IF(ISNUMBER(M119),IF(M119<=Summary!$B$4,"Agree","Check"),IF(ISNUMBER(J119),"DGE only",IF(ISNUMBER(K119),"ILO only","Not scored"))) -> Agree | O119: =IF(ISNUMBER(J119),J119,IF(ISNUMBER(K119),K119,"")) -> 0.16 | P119: =IF(ISNUMBER(J119),"DGE",IF(ISNUMBER(K119),"ILO table","")) -> DGE
A120: 933 | B120: 933 | C120: Transport and storage labourers | D120: 933 | E120: 933 | F120: 933 | G120: 1 | H120: =SUMPRODUCT(('DGE links'!$F$2:$F$3451=A120)*1) -> 14 | I120: =SUMPRODUCT(('ILO links'!$G$2:$G$674=A120)*'ILO links'!$J$2:$J$674) -> 4 | J120: =IFERROR(SUMPRODUCT(('DGE links'!$F$2:$F$3451=A120)*'DGE links'!$H$2:$H$3451*'DGE links'!$I$2:$I$3451*'DGE links'!$J$2:$J$3451)/SUMPRODUCT(('DGE links'!$F$2:$F$3451=A120)*'DGE links'!$H$2:$H$3451*'DGE links'!$J$2:$J$3451),"") -> 0.17 | K120: =IFERROR(AVERAGEIFS('ILO links'!$H$2:$H$674,'ILO links'!$G$2:$G$674,A120,'ILO links'!$J$2:$J$674,1),"") -> 0.17 | L120: =IF(AND(ISNUMBER(J120),ISNUMBER(K120)),J120-K120,"") -> 0 | M120: =IF(ISNUMBER(L120),ABS(L120),"") -> 0 | N120: =IF(ISNUMBER(M120),IF(M120<=Summary!$B$4,"Agree","Check"),IF(ISNUMBER(J120),"DGE only",IF(ISNUMBER(K120),"ILO only","Not scored"))) -> Agree | O120: =IF(ISNUMBER(J120),J120,IF(ISNUMBER(K120),K120,"")) -> 0.17 | P120: =IF(ISNUMBER(J120),"DGE",IF(ISNUMBER(K120),"ILO table","")) -> DGE
A122: Each row is one NCO-2004 3-digit group (the codes PLFS used from 2017-18 to 2020-21). Columns J-P are formulas over the DGE links, ILO links and NCO-2015 scores sheets; columns B-G are text summaries computed when the workbook was built.

Sheet NCO-2015 scores
A1: NCO-2015 group | B1: Group title (ISCO-08) | C1: ILO exposure score (0-1) | D1: Share of jobs in ILO gradients 3-4
A2: 011 | B2: Commissioned armed forces officers
A3: 021 | B3: Non-commissioned armed forces officers
A4: 031 | B4: Armed forces occupations, other ranks
A5: 111 | B5: Legislators and senior officials | C5: 0.3225 | D5: 0
A6: 112 | B6: Managing directors and chief executives | C6: 0.38 | D6: 0
A7: 121 | B7: Business services and administration managers | C7: 0.3775 | D7: 0
A8: 122 | B8: Sales, marketing and development managers | C8: 0.4 | D8: 0
A9: 131 | B9: Production managers in agriculture, forestry and fisheries | C9: 0.245 | D9: 0
A10: 132 | B10: Manufacturing, mining, construction, and distribution managers | C10: 0.3625 | D10: 0
A11: 133 | B11: Information and communications technology service managers | C11: 0.44 | D11: 0
A12: 134 | B12: Professional services managers | C12: 0.3686 | D12: 0
A13: 141 | B13: Hotel and restaurant managers | C13: 0.365 | D13: 0
A14: 142 | B14: Retail and wholesale trade managers | C14: 0.44 | D14: 0
A15: 143 | B15: Other services managers | C15: 0.32 | D15: 0
A16: 211 | B16: Physical and earth science professionals | C16: 0.4175 | D16: 0.25
... A131: 962 | B131: Other elementary workers | C131: 0.248 | D131: 0
A133: Source: Mishra, nco2015-ai-exposure (github.com/Kpmishra1998/nco2015-ai-exposure), built from ILO WP140 (Gmyrek et al. 2025) Table A1. Blue = input values.

Sheet DGE links
A1: S.No. | B1: Occupational title | C1: NCO-2015 code | D1: NCO-2004 code | E1: NCO-2015 group | F1: NCO-2004 group | G1: Same 3-digit number? | H1: Weight (1 / links of this 2004 code) | I1: Exposure of NCO-2015 group | J1: Has score (1/0)
A2: 1 | B2: Accountant | C2: 2411.0100 | D2: 2411.10 | E2: =LEFT(C2,3) -> 241 | F2: =IF(D2="","",LEFT(D2,3)) -> 241 | G2: =IF(F2="","",IF(E2=F2,"Yes","No")) -> Yes | H2: =IF(D2="",0,1/COUNTIF($D$2:$D$3451,D2)) -> 1 | I2: =IFERROR(INDEX('NCO-2015 scores'!$C$2:$C$131,MATCH(E2,'NCO-2015 scores'!$A$2:$A$131,0)),0) -> 0.5667 | J2: =IF(ISNUMBER(MATCH(E2,'NCO-2015 scores'!$A$2:$A$131,0)),IF(ISNUMBER(INDEX('NCO-2015 scores'!$C$2:$C$131,MATCH(E2,'NCO-2015 scores'!$A$2:$A$131,0))),1,0),0) -> 1
A3: 2 | B3: Auditor | C3: 2411.0200 | D3: 2411.20 | E3: =LEFT(C3,3) -> 241 | F3: =IF(D3="","",LEFT(D3,3)) -> 241 | G3: =IF(F3="","",IF(E3=F3,"Yes","No")) -> Yes | H3: =IF(D3="",0,1/COUNTIF($D$2:$D$3451,D3)) -> 1 | I3: =IFERROR(INDEX('NCO-2015 scores'!$C$2:$C$131,MATCH(E3,'NCO-2015 scores'!$A$2:$A$131,0)),0) -> 0.5667 | J3: =IF(ISNUMBER(MATCH(E3,'NCO-2015 scores'!$A$2:$A$131,0)),IF(ISNUMBER(INDEX('NCO-2015 scores'!$C$2:$C$131,MATCH(E3,'NCO-2015 scores'!$A$2:$A$131,0))),1,0),0) -> 1
A4: 3 | B4: Cost Accountant | C4: 2411.0300 | D4: 2411.30 | E4: =LEFT(C4,3) -> 241 | F4: =IF(D4="","",LEFT(D4,3)) -> 241 | G4: =IF(F4="","",IF(E4=F4,"Yes","No")) -> Yes | H4: =IF(D4="",0,1/COUNTIF($D$2:$D$3451,D4)) -> 1 | I4: =IFERROR(INDEX('NCO-2015 scores'!$C$2:$C$131,MATCH(E4,'NCO-2015 scores'!$A$2:$A$131,0)),0) -> 0.5667 | J4: =IF(ISNUMBER(MATCH(E4,'NCO-2015 scores'!$A$2:$A$131,0)),IF(ISNUMBER(INDEX('NCO-2015 scores'!$C$2:$C$131,MATCH(E4,'NCO-2015 scores'!$A$2:$A$131,0))),1,0),0) -> 1
A5: 4 | B5: Associate – Transactional Finance & Accounting | C5: 2411.0101 | E5: =LEFT(C5,3) -> 241 | F5: =IF(D5="","",LEFT(D5,3)) | G5: =IF(F5="","",IF(E5=F5,"Yes","No")) | H5: =IF(D5="",0,1/COUNTIF($D$2:$D$3451,D5)) -> 0 | I5: =IFERROR(INDEX('NCO-2015 scores'!$C$2:$C$131,MATCH(E5,'NCO-2015 scores'!$A$2:$A$131,0)),0) -> 0.5667 | J5: =IF(ISNUMBER(MATCH(E5,'NCO-2015 scores'!$A$2:$A$131,0)),IF(ISNUMBER(INDEX('NCO-2015 scores'!$C$2:$C$131,MATCH(E5,'NCO-2015 scores'!$A$2:$A$131,0))),1,0),0) -> 1
A6: 5 | B6: Associate – Finance & Accounting Complex | C6: 2411.0201 | E6: =LEFT(C6,3) -> 241 | F6: =IF(D6="","",LEFT(D6,3)) | G6: =IF(F6="","",IF(E6=F6,"Yes","No")) | H6: =IF(D6="",0,1/COUNTIF($D$2:$D$3451,D6)) -> 0 | I6: =IFERROR(INDEX('NCO-2015 scores'!$C$2:$C$131,MATCH(E6,'NCO-2015 scores'!$A$2:$A$131,0)),0) -> 0.5667 | J6: =IF(ISNUMBER(MATCH(E6,'NCO-2015 scores'!$A$2:$A$131,0)),IF(ISNUMBER(INDEX('NCO-2015 scores'!$C$2:$C$131,MATCH(E6,'NCO-2015 scores'!$A$2:$A$131,0))),1,0),0) -> 1
A7: 6 | B7: Bookkeeper General/Accounts Executive (Recording and Reporting) | C7: 4311.0101 | D7: 4121.10 | E7: =LEFT(C7,3) -> 431 | F7: =IF(D7="","",LEFT(D7,3)) -> 412 | G7: =IF(F7="","",IF(E7=F7,"Yes","No")) -> No | H7: =IF(D7="",0,1/COUNTIF($D$2:$D$3451,D7)) -> 1 | I7: =IFERROR(INDEX('NCO-2015 scores'!$C$2:$C$131,MATCH(E7,'NCO-2015 scores'!$A$2:$A$131,0)),0) -> 0.63 | J7: =IF(ISNUMBER(MATCH(E7,'NCO-2015 scores'!$A$2:$A$131,0)),IF(ISNUMBER(INDEX('NCO-2015 scores'!$C$2:$C$131,MATCH(E7,'NCO-2015 scores'!$A$2:$A$131,0))),1,0),0) -> 1
A8: 7 | B8: Bank Clerk | C8: 4311.0200 | D8: 4121.30 | E8: =LEFT(C8,3) -> 431 | F8: =IF(D8="","",LEFT(D8,3)) -> 412 | G8: =IF(F8="","",IF(E8=F8,"Yes","No")) -> No | H8: =IF(D8="",0,1/COUNTIF($D$2:$D$3451,D8)) -> 1 | I8: =IFERROR(INDEX('NCO-2015 scores'!$C$2:$C$131,MATCH(E8,'NCO-2015 scores'!$A$2:$A$131,0)),0) -> 0.63 | J8: =IF(ISNUMBER(MATCH(E8,'NCO-2015 scores'!$A$2:$A$131,0)),IF(ISNUMBER(INDEX('NCO-2015 scores'!$C$2:$C$131,MATCH(E8,'NCO-2015 scores'!$A$2:$A$131,0))),1,0),0) -> 1
A9: 8 | B9: Ledger Clerk | C9: 4311.0300 | D9: 4121.40 | E9: =LEFT(C9,3) -> 431 | F9: =IF(D9="","",LEFT(D9,3)) -> 412 | G9: =IF(F9="","",IF(E9=F9,"Yes","No")) -> No | H9: =IF(D9="",0,1/COUNTIF($D$2:$D$3451,D9)) -> 1 | I9: =IFERROR(INDEX('NCO-2015 scores'!$C$2:$C$131,MATCH(E9,'NCO-2015 scores'!$A$2:$A$131,0)),0) -> 0.63 | J9: =IF(ISNUMBER(MATCH(E9,'NCO-2015 scores'!$A$2:$A$131,0)),IF(ISNUMBER(INDEX('NCO-2015 scores'!$C$2:$C$131,MATCH(E9,'NCO-2015 scores'!$A$2:$A$131,0))),1,0),0) -> 1
A10: 9 | B10: Accounts Executive (Accounts Payable & Receivable) | C10: 4311.0401 | E10: =LEFT(C10,3) -> 431 | F10: =IF(D10="","",LEFT(D10,3)) | G10: =IF(F10="","",IF(E10=F10,"Yes","No")) | H10: =IF(D10="",0,1/COUNTIF($D$2:$D$3451,D10)) -> 0 | I10: =IFERROR(INDEX('NCO-2015 scores'!$C$2:$C$131,MATCH(E10,'NCO-2015 scores'!$A$2:$A$131,0)),0) -> 0.63 | J10: =IF(ISNUMBER(MATCH(E10,'NCO-2015 scores'!$A$2:$A$131,0)),IF(ISNUMBER(INDEX('NCO-2015 scores'!$C$2:$C$131,MATCH(E10,'NCO-2015 scores'!$A$2:$A$131,0))),1,0),0) -> 1
A11: 10 | B11: Audit, Clerk | C11: 4311.0500 | D11: 4121.50 | E11: =LEFT(C11,3) -> 431 | F11: =IF(D11="","",LEFT(D11,3)) -> 412 | G11: =IF(F11="","",IF(E11=F11,"Yes","No")) -> No | H11: =IF(D11="",0,1/COUNTIF($D$2:$D$3451,D11)) -> 1 | I11: =IFERROR(INDEX('NCO-2015 scores'!$C$2:$C$131,MATCH(E11,'NCO-2015 scores'!$A$2:$A$131,0)),0) -> 0.63 | J11: =IF(ISNUMBER(MATCH(E11,'NCO-2015 scores'!$A$2:$A$131,0)),IF(ISNUMBER(INDEX('NCO-2015 scores'!$C$2:$C$131,MATCH(E11,'NCO-2015 scores'!$A$2:$A$131,0))),1,0),0) -> 1
A12: 11 | B12: Clerk, Cost Accounting | C12: 4311.0600 | D12: 4121.60 | E12: =LEFT(C12,3) -> 431 | F12: =IF(D12="","",LEFT(D12,3)) -> 412 | G12: =IF(F12="","",IF(E12=F12,"Yes","No")) -> No | H12: =IF(D12="",0,1/COUNTIF($D$2:$D$3451,D12)) -> 1 | I12: =IFERROR(INDEX('NCO-2015 scores'!$C$2:$C$131,MATCH(E12,'NCO-2015 scores'!$A$2:$A$131,0)),0) -> 0.63 | J12: =IF(ISNUMBER(MATCH(E12,'NCO-2015 scores'!$A$2:$A$131,0)),IF(ISNUMBER(INDEX('NCO-2015 scores'!$C$2:$C$131,MATCH(E12,'NCO-2015 scores'!$A$2:$A$131,0))),1,0),0) -> 1
A13: 12 | B13: Bill and Accounts Collector | C13: 4311.0700 | D13: 4121.70 | E13: =LEFT(C13,3) -> 431 | F13: =IF(D13="","",LEFT(D13,3)) -> 412 | G13: =IF(F13="","",IF(E13=F13,"Yes","No")) -> No | H13: =IF(D13="",0,1/COUNTIF($D$2:$D$3451,D13)) -> 1 | I13: =IFERROR(INDEX('NCO-2015 scores'!$C$2:$C$131,MATCH(E13,'NCO-2015 scores'!$A$2:$A$131,0)),0) -> 0.63 | J13: =IF(ISNUMBER(MATCH(E13,'NCO-2015 scores'!$A$2:$A$131,0)),IF(ISNUMBER(INDEX('NCO-2015 scores'!$C$2:$C$131,MATCH(E13,'NCO-2015 scores'!$A$2:$A$131,0))),1,0),0) -> 1
A14: 13 | B14: Rubber Nursery Office Assistant | C14: 4311.0801 | E14: =LEFT(C14,3) -> 431 | F14: =IF(D14="","",LEFT(D14,3)) | G14: =IF(F14="","",IF(E14=F14,"Yes","No")) | H14: =IF(D14="",0,1/COUNTIF($D$2:$D$3451,D14)) -> 0 | I14: =IFERROR(INDEX('NCO-2015 scores'!$C$2:$C$131,MATCH(E14,'NCO-2015 scores'!$A$2:$A$131,0)),0) -> 0.63 | J14: =IF(ISNUMBER(MATCH(E14,'NCO-2015 scores'!$A$2:$A$131,0)),IF(ISNUMBER(INDEX('NCO-2015 scores'!$C$2:$C$131,MATCH(E14,'NCO-2015 scores'!$A$2:$A$131,0))),1,0),0) -> 1
A15: 14 | B15: Accounting and Bookkeeping Clerks, Others | C15: 4311.9900 | D15: 4121.90 | E15: =LEFT(C15,3) -> 431 | F15: =IF(D15="","",LEFT(D15,3)) -> 412 | G15: =IF(F15="","",IF(E15=F15,"Yes","No")) -> No | H15: =IF(D15="",0,1/COUNTIF($D$2:$D$3451,D15)) -> 1 | I15: =IFERROR(INDEX('NCO-2015 scores'!$C$2:$C$131,MATCH(E15,'NCO-2015 scores'!$A$2:$A$131,0)),0) -> 0.63 | J15: =IF(ISNUMBER(MATCH(E15,'NCO-2015 scores'!$A$2:$A$131,0)),IF(ISNUMBER(INDEX('NCO-2015 scores'!$C$2:$C$131,MATCH(E15,'NCO-2015 scores'!$A$2:$A$131,0))),1,0),0) -> 1
A16: 15 | B16: Actor and Actress | C16: 2655.0100 | D16: 2455.50 | E16: =LEFT(C16,3) -> 265 | F16: =IF(D16="","",LEFT(D16,3)) -> 245 | G16: =IF(F16="","",IF(E16=F16,"Yes","No")) -> No | H16: =IF(D16="",0,1/COUNTIF($D$2:$D$3451,D16)) -> 1 | I16: =IFERROR(INDEX('NCO-2015 scores'!$C$2:$C$131,MATCH(E16,'NCO-2015 scores'!$A$2:$A$131,0)),0) -> 0.28 | J16: =IF(ISNUMBER(MATCH(E16,'NCO-2015 scores'!$A$2:$A$131,0)),IF(ISNUMBER(INDEX('NCO-2015 scores'!$C$2:$C$131,MATCH(E16,'NCO-2015 scores'!$A$2:$A$131,0))),1,0),0) -> 1
A17: 16 | B17: Extra | C17: 2655.0200 | D17: 2455.60 | E17: =LEFT(C17,3) -> 265 | F17: =IF(D17="","",LEFT(D17,3)) -> 245 | G17: =IF(F17="","",IF(E17=F17,"Yes","No")) -> No | H17: =IF(D17="",0,1/COUNTIF($D$2:$D$3451,D17)) -> 1 | I17: =IFERROR(INDEX('NCO-2015 scores'!$C$2:$C$131,MATCH(E17,'NCO-2015 scores'!$A$2:$A$131,0)),0) -> 0.28 | J17: =IF(ISNUMBER(MATCH(E17,'NCO-2015 scores'!$A$2:$A$131,0)),IF(ISNUMBER(INDEX('NCO-2015 scores'!$C$2:$C$131,MATCH(E17,'NCO-2015 scores'!$A$2:$A$131,0))),1,0),0) -> 1
A18: 17 | B18: Voice Over Artist | C18: 2655.0301 | E18: =LEFT(C18,3) -> 265 | F18: =IF(D18="","",LEFT(D18,3)) | G18: =IF(F18="","",IF(E18=F18,"Yes","No")) | H18: =IF(D18="",0,1/COUNTIF($D$2:$D$3451,D18)) -> 0 | I18: =IFERROR(INDEX('NCO-2015 scores'!$C$2:$C$131,MATCH(E18,'NCO-2015 scores'!$A$2:$A$131,0)),0) -> 0.28 | J18: =IF(ISNUMBER(MATCH(E18,'NCO-2015 scores'!$A$2:$A$131,0)),IF(ISNUMBER(INDEX('NCO-2015 scores'!$C$2:$C$131,MATCH(E18,'NCO-2015 scores'!$A$2:$A$131,0))),1,0),0) -> 1
A19: 18 | B19: Caption Writer | C19: 2431.0300 | D19: 2451.47 | E19: =LEFT(C19,3) -> 243 | F19: =IF(D19="","",LEFT(D19,3)) -> 245 | G19: =IF(F19="","",IF(E19=F19,"Yes","No")) -> No | H19: =IF(D19="",0,1/COUNTIF($D$2:$D$3451,D19)) -> 1 | I19: =IFERROR(INDEX('NCO-2015 scores'!$C$2:$C$131,MATCH(E19,'NCO-2015 scores'!$A$2:$A$131,0)),0) -> 0.4975 | J19: =IF(ISNUMBER(MATCH(E19,'NCO-2015 scores'!$A$2:$A$131,0)),IF(ISNUMBER(INDEX('NCO-2015 scores'!$C$2:$C$131,MATCH(E19,'NCO-2015 scores'!$A$2:$A$131,0))),1,0),0) -> 1
A20: 19 | B20: Advertisement Writer | C20: 2431.0400 | D20: 2451.50 | E20: =LEFT(C20,3) -> 243 | F20: =IF(D20="","",LEFT(D20,3)) -> 245 | G20: =IF(F20="","",IF(E20=F20,"Yes","No")) -> No | H20: =IF(D20="",0,1/COUNTIF($D$2:$D$3451,D20)) -> 1 | I20: =IFERROR(INDEX('NCO-2015 scores'!$C$2:$C$131,MATCH(E20,'NCO-2015 scores'!$A$2:$A$131,0)),0) -> 0.4975 | J20: =IF(ISNUMBER(MATCH(E20,'NCO-2015 scores'!$A$2:$A$131,0)),IF(ISNUMBER(INDEX('NCO-2015 scores'!$C$2:$C$131,MATCH(E20,'NCO-2015 scores'!$A$2:$A$131,0))),1,0),0) -> 1
A21: 20 | B21: Market Research Analyst | C21: 2431.0100 | D21: 2419.40 | E21: =LEFT(C21,3) -> 243 | F21: =IF(D21="","",LEFT(D21,3)) -> 241 | G21: =IF(F21="","",IF(E21=F21,"Yes","No")) -> No | H21: =IF(D21="",0,1/COUNTIF($D$2:$D$3451,D21)) -> 1 | I21: =IFERROR(INDEX('NCO-2015 scores'!$C$2:$C$131,MATCH(E21,'NCO-2015 scores'!$A$2:$A$131,0)),0) -> 0.4975 | J21: =IF(ISNUMBER(MATCH(E21,'NCO-2015 scores'!$A$2:$A$131,0)),IF(ISNUMBER(INDEX('NCO-2015 scores'!$C$2:$C$131,MATCH(E21,'NCO-2015 scores'!$A$2:$A$131,0))),1,0),0) -> 1
A22: 21 | B22: Regional Service Marketing Manager | C22: 2431.0101 | E22: =LEFT(C22,3) -> 243 | F22: =IF(D22="","",LEFT(D22,3)) | G22: =IF(F22="","",IF(E22=F22,"Yes","No")) | H22: =IF(D22="",0,1/COUNTIF($D$2:$D$3451,D22)) -> 0 | I22: =IFERROR(INDEX('NCO-2015 scores'!$C$2:$C$131,MATCH(E22,'NCO-2015 scores'!$A$2:$A$131,0)),0) -> 0.4975 | J22: =IF(ISNUMBER(MATCH(E22,'NCO-2015 scores'!$A$2:$A$131,0)),IF(ISNUMBER(INDEX('NCO-2015 scores'!$C$2:$C$131,MATCH(E22,'NCO-2015 scores'!$A$2:$A$131,0))),1,0),0) -> 1
A23: 22 | B23: Product Brand Manager (Automotive) | C23: 2431.0201 | E23: =LEFT(C23,3) -> 243 | F23: =IF(D23="","",LEFT(D23,3)) | G23: =IF(F23="","",IF(E23=F23,"Yes","No")) | H23: =IF(D23="",0,1/COUNTIF($D$2:$D$3451,D23)) -> 0 | I23: =IFERROR(INDEX('NCO-2015 scores'!$C$2:$C$131,MATCH(E23,'NCO-2015 scores'!$A$2:$A$131,0)),0) -> 0.4975 | J23: =IF(ISNUMBER(MATCH(E23,'NCO-2015 scores'!$A$2:$A$131,0)),IF(ISNUMBER(INDEX('NCO-2015 scores'!$C$2:$C$131,MATCH(E23,'NCO-2015 scores'!$A$2:$A$131,0))),1,0),0) -> 1
A24: 23 | B24: Account Executive (Advertising Agency) | C24: 2431.0202 | E24: =LEFT(C24,3) -> 243 | F24: =IF(D24="","",LEFT(D24,3)) | G24: =IF(F24="","",IF(E24=F24,"Yes","No")) | H24: =IF(D24="",0,1/COUNTIF($D$2:$D$3451,D24)) -> 0 | I24: =IFERROR(INDEX('NCO-2015 scores'!$C$2:$C$131,MATCH(E24,'NCO-2015 scores'!$A$2:$A$131,0)),0) -> 0.4975 | J24: =IF(ISNUMBER(MATCH(E24,'NCO-2015 scores'!$A$2:$A$131,0)),IF(ISNUMBER(INDEX('NCO-2015 scores'!$C$2:$C$131,MATCH(E24,'NCO-2015 scores'!$A$2:$A$131,0))),1,0),0) -> 1
A25: 24 | B25: Product Executive | C25: 2431.0601 | E25: =LEFT(C25,3) -> 243 | F25: =IF(D25="","",LEFT(D25,3)) | G25: =IF(F25="","",IF(E25=F25,"Yes","No")) | H25: =IF(D25="",0,1/COUNTIF($D$2:$D$3451,D25)) -> 0 | I25: =IFERROR(INDEX('NCO-2015 scores'!$C$2:$C$131,MATCH(E25,'NCO-2015 scores'!$A$2:$A$131,0)),0) -> 0.4975 | J25: =IF(ISNUMBER(MATCH(E25,'NCO-2015 scores'!$A$2:$A$131,0)),IF(ISNUMBER(INDEX('NCO-2015 scores'!$C$2:$C$131,MATCH(E25,'NCO-2015 scores'!$A$2:$A$131,0))),1,0),0) -> 1
A26: 25 | B26: Sales Executive (Media Org) | C26: 2431.0651 | E26: =LEFT(C26,3) -> 243 | F26: =IF(D26="","",LEFT(D26,3)) | G26: =IF(F26="","",IF(E26=F26,"Yes","No")) | H26: =IF(D26="",0,1/COUNTIF($D$2:$D$3451,D26)) -> 0 | I26: =IFERROR(INDEX('NCO-2015 scores'!$C$2:$C$131,MATCH(E26,'NCO-2015 scores'!$A$2:$A$131,0)),0) -> 0.4975 | J26: =IF(ISNUMBER(MATCH(E26,'NCO-2015 scores'!$A$2:$A$131,0)),IF(ISNUMBER(INDEX('NCO-2015 scores'!$C$2:$C$131,MATCH(E26,'NCO-2015 scores'!$A$2:$A$131,0))),1,0),0) -> 1
A27: 26 | B27: Traffic Co-Ordinator | C27: 2431.0671 | E27: =LEFT(C27,3) -> 243 | F27: =IF(D27="","",LEFT(D27,3)) | G27: =IF(F27="","",IF(E27=F27,"Yes","No")) | H27: =IF(D27="",0,1/COUNTIF($D$2:$D$3451,D27)) -> 0 | I27: =IFERROR(INDEX('NCO-2015 scores'!$C$2:$C$131,MATCH(E27,'NCO-2015 scores'!$A$2:$A$131,0)),0) -> 0.4975 | J27: =IF(ISNUMBER(MATCH(E27,'NCO-2015 scores'!$A$2:$A$131,0)),IF(ISNUMBER(INDEX('NCO-2015 scores'!$C$2:$C$131,MATCH(E27,'NCO-2015 scores'!$A$2:$A$131,0))),1,0),0) -> 1
A28: 27 | B28: Creative Writer | C28: 2431.0700 | D28: 2451.52 | E28: =LEFT(C28,3) -> 243 | F28: =IF(D28="","",LEFT(D28,3)) -> 245 | G28: =IF(F28="","",IF(E28=F28,"Yes","No")) -> No | H28: =IF(D28="",0,1/COUNTIF($D$2:$D$3451,D28)) -> 1 | I28: =IFERROR(INDEX('NCO-2015 scores'!$C$2:$C$131,MATCH(E28,'NCO-2015 scores'!$A$2:$A$131,0)),0) -> 0.4975 | J28: =IF(ISNUMBER(MATCH(E28,'NCO-2015 scores'!$A$2:$A$131,0)),IF(ISNUMBER(INDEX('NCO-2015 scores'!$C$2:$C$131,MATCH(E28,'NCO-2015 scores'!$A$2:$A$131,0))),1,0),0) -> 1
A29: 28 | B29: Propagandist | C29: 2431.0800 | D29: 3411.30 | E29: =LEFT(C29,3) -> 243 | F29: =IF(D29="","",LEFT(D29,3)) -> 341 | G29: =IF(F29="","",IF(E29=F29,"Yes","No")) -> No | H29: =IF(D29="",0,1/COUNTIF($D$2:$D$3451,D29)) -> 1 | I29: =IFERROR(INDEX('NCO-2015 scores'!$C$2:$C$131,MATCH(E29,'NCO-2015 scores'!$A$2:$A$131,0)),0) -> 0.4975 | J29: =IF(ISNUMBER(MATCH(E29,'NCO-2015 scores'!$A$2:$A$131,0)),IF(ISNUMBER(INDEX('NCO-2015 scores'!$C$2:$C$131,MATCH(E29,'NCO-2015 scores'!$A$2:$A$131,0))),1,0),0) -> 1
A30: 29 | B30: Advertising and Marketing Professionals, Other | C30: 2431.9900 | E30: =LEFT(C30,3) -> 243 | F30: =IF(D30="","",LEFT(D30,3)) | G30: =IF(F30="","",IF(E30=F30,"Yes","No")) | H30: =IF(D30="",0,1/COUNTIF($D$2:$D$3451,D30)) -> 0 | I30: =IFERROR(INDEX('NCO-2015 scores'!$C$2:$C$131,MATCH(E30,'NCO-2015 scores'!$A$2:$A$131,0)),0) -> 0.4975 | J30: =IF(ISNUMBER(MATCH(E30,'NCO-2015 scores'!$A$2:$A$131,0)),IF(ISNUMBER(INDEX('NCO-2015 scores'!$C$2:$C$131,MATCH(E30,'NCO-2015 scores'!$A$2:$A$131,0))),1,0),0) -> 1
A31: 30 | B31: Regional Service Process Manager | C31: 2431.0102 | E31: =LEFT(C31,3) -> 243 | F31: =IF(D31="","",LEFT(D31,3)) | G31: =IF(F31="","",IF(E31=F31,"Yes","No")) | H31: =IF(D31="",0,1/COUNTIF($D$2:$D$3451,D31)) -> 0 | I31: =IFERROR(INDEX('NCO-2015 scores'!$C$2:$C$131,MATCH(E31,'NCO-2015 scores'!$A$2:$A$131,0)),0) -> 0.4975 | J31: =IF(ISNUMBER(MATCH(E31,'NCO-2015 scores'!$A$2:$A$131,0)),IF(ISNUMBER(INDEX('NCO-2015 scores'!$C$2:$C$131,MATCH(E31,'NCO-2015 scores'!$A$2:$A$131,0))),1,0),0) -> 1
A32: 31 | B32: Market Research Associate – Sales & Marketing/Business Development | C32: 2431.0501 | E32: =LEFT(C32,3) -> 243 | F32: =IF(D32="","",LEFT(D32,3)) | G32: =IF(F32="","",IF(E32=F32,"Yes","No")) | H32: =IF(D32="",0,1/COUNTIF($D$2:$D$3451,D32)) -> 0 | I32: =IFERROR(INDEX('NCO-2015 scores'!$C$2:$C$131,MATCH(E32,'NCO-2015 scores'!$A$2:$A$131,0)),0) -> 0.4975 | J32: =IF(ISNUMBER(MATCH(E32,'NCO-2015 scores'!$A$2:$A$131,0)),IF(ISNUMBER(INDEX('NCO-2015 scores'!$C$2:$C$131,MATCH(E32,'NCO-2015 scores'!$A$2:$A$131,0))),1,0),0) -> 1
A33: 32 | B33: Management Trainee – Sales & Marketing/Business Development | C33: 2431.0502 | E33: =LEFT(C33,3) -> 243 | F33: =IF(D33="","",LEFT(D33,3)) | G33: =IF(F33="","",IF(E33=F33,"Yes","No")) | H33: =IF(D33="",0,1/COUNTIF($D$2:$D$3451,D33)) -> 0 | I33: =IFERROR(INDEX('NCO-2015 scores'!$C$2:$C$131,MATCH(E33,'NCO-2015 scores'!$A$2:$A$131,0)),0) -> 0.4975 | J33: =IF(ISNUMBER(MATCH(E33,'NCO-2015 scores'!$A$2:$A$131,0)),IF(ISNUMBER(INDEX('NCO-2015 scores'!$C$2:$C$131,MATCH(E33,'NCO-2015 scores'!$A$2:$A$131,0))),1,0),0) -> 1
A34: 33 | B34: Market Research Associate – Product Marketing | C34: 2431.0503 | E34: =LEFT(C34,3) -> 243 | F34: =IF(D34="","",LEFT(D34,3)) | G34: =IF(F34="","",IF(E34=F34,"Yes","No")) | H34: =IF(D34="",0,1/COUNTIF($D$2:$D$3451,D34)) -> 0 | I34: =IFERROR(INDEX('NCO-2015 scores'!$C$2:$C$131,MATCH(E34,'NCO-2015 scores'!$A$2:$A$131,0)),0) -> 0.4975 | J34: =IF(ISNUMBER(MATCH(E34,'NCO-2015 scores'!$A$2:$A$131,0)),IF(ISNUMBER(INDEX('NCO-2015 scores'!$C$2:$C$131,MATCH(E34,'NCO-2015 scores'!$A$2:$A$131,0))),1,0),0) -> 1
A35: 34 | B35: Management Trainee – Product Marketing | C35: 2431.0504 | E35: =LEFT(C35,3) -> 243 | F35: =IF(D35="","",LEFT(D35,3)) | G35: =IF(F35="","",IF(E35=F35,"Yes","No")) | H35: =IF(D35="",0,1/COUNTIF($D$2:$D$3451,D35)) -> 0 | I35: =IFERROR(INDEX('NCO-2015 scores'!$C$2:$C$131,MATCH(E35,'NCO-2015 scores'!$A$2:$A$131,0)),0) -> 0.4975 | J35: =IF(ISNUMBER(MATCH(E35,'NCO-2015 scores'!$A$2:$A$131,0)),IF(ISNUMBER(INDEX('NCO-2015 scores'!$C$2:$C$131,MATCH(E35,'NCO-2015 scores'!$A$2:$A$131,0))),1,0),0) -> 1
A36: 35 | B36: Manager, Advertising and Promotion | C36: 1222.0100 | D36: 1234.10 | E36: =LEFT(C36,3) -> 122 | F36: =IF(D36="","",LEFT(D36,3)) -> 123 | G36: =IF(F36="","",IF(E36=F36,"Yes","No")) -> No | H36: =IF(D36="",0,1/COUNTIF($D$2:$D$3451,D36)) -> 1 | I36: =IFERROR(INDEX('NCO-2015 scores'!$C$2:$C$131,MATCH(E36,'NCO-2015 scores'!$A$2:$A$131,0)),0) -> 0.4 | J36: =IF(ISNUMBER(MATCH(E36,'NCO-2015 scores'!$A$2:$A$131,0)),IF(ISNUMBER(INDEX('NCO-2015 scores'!$C$2:$C$131,MATCH(E36,'NCO-2015 scores'!$A$2:$A$131,0))),1,0),0) -> 1
A37: 36 | B37: Advertising Operations Co-Ordinator (Digital) | C37: 1222.0102 | E37: =LEFT(C37,3) -> 122 | F37: =IF(D37="","",LEFT(D37,3)) | G37: =IF(F37="","",IF(E37=F37,"Yes","No")) | H37: =IF(D37="",0,1/COUNTIF($D$2:$D$3451,D37)) -> 0 | I37: =IFERROR(INDEX('NCO-2015 scores'!$C$2:$C$131,MATCH(E37,'NCO-2015 scores'!$A$2:$A$131,0)),0) -> 0.4 | J37: =IF(ISNUMBER(MATCH(E37,'NCO-2015 scores'!$A$2:$A$131,0)),IF(ISNUMBER(INDEX('NCO-2015 scores'!$C$2:$C$131,MATCH(E37,'NCO-2015 scores'!$A$2:$A$131,0))),1,0),0) -> 1
A38: 37 | B38: Manager, Fashion/Fashion Manager | C38: 1222.0200 | D38: 1234.20 | E38: =LEFT(C38,3) -> 122 | F38: =IF(D38="","",LEFT(D38,3)) -> 123 | G38: =IF(F38="","",IF(E38=F38,"Yes","No")) -> No | H38: =IF(D38="",0,1/COUNTIF($D$2:$D$3451,D38)) -> 1 | I38: =IFERROR(INDEX('NCO-2015 scores'!$C$2:$C$131,MATCH(E38,'NCO-2015 scores'!$A$2:$A$131,0)),0) -> 0.4 | J38: =IF(ISNUMBER(MATCH(E38,'NCO-2015 scores'!$A$2:$A$131,0)),IF(ISNUMBER(INDEX('NCO-2015 scores'!$C$2:$C$131,MATCH(E38,'NCO-2015 scores'!$A$2:$A$131,0))),1,0),0) -> 1
A39: 38 | B39: Advertising and Public Relations Department Managers, Others | C39: 1222.9900 | D39: 1234.90 | E39: =LEFT(C39,3) -> 122 | F39: =IF(D39="","",LEFT(D39,3)) -> 123 | G39: =IF(F39="","",IF(E39=F39,"Yes","No")) -> No | H39: =IF(D39="",0,1/COUNTIF($D$2:$D$3451,D39)) -> 1 | I39: =IFERROR(INDEX('NCO-2015 scores'!$C$2:$C$131,MATCH(E39,'NCO-2015 scores'!$A$2:$A$131,0)),0) -> 0.4 | J39: =IF(ISNUMBER(MATCH(E39,'NCO-2015 scores'!$A$2:$A$131,0)),IF(ISNUMBER(INDEX('NCO-2015 scores'!$C$2:$C$131,MATCH(E39,'NCO-2015 scores'!$A$2:$A$131,0))),1,0),0) -> 1
A40: 39 | B40: General Manager, Plantation | C40: 1311.0100 | D40: 1301.20 | E40: =LEFT(C40,3) -> 131 | F40: =IF(D40="","",LEFT(D40,3)) -> 130 | G40: =IF(F40="","",IF(E40=F40,"Yes","No")) -> No | H40: =IF(D40="",0,1/COUNTIF($D$2:$D$3451,D40)) -> 1 | I40: =IFERROR(INDEX('NCO-2015 scores'!$C$2:$C$131,MATCH(E40,'NCO-2015 scores'!$A$2:$A$131,0)),0) -> 0.245 | J40: =IF(ISNUMBER(MATCH(E40,'NCO-2015 scores'!$A$2:$A$131,0)),IF(ISNUMBER(INDEX('NCO-2015 scores'!$C$2:$C$131,MATCH(E40,'NCO-2015 scores'!$A$2:$A$131,0))),1,0),0) -> 1
A41: 40 | B41: General Manager, Horticulture | C41: 1311.0200 | D41: 1301.30 | E41: =LEFT(C41,3) -> 131 | F41: =IF(D41="","",LEFT(D41,3)) -> 130 | G41: =IF(F41="","",IF(E41=F41,"Yes","No")) -> No | H41: =IF(D41="",0,1/COUNTIF($D$2:$D$3451,D41)) -> 1 | I41: =IFERROR(INDEX('NCO-2015 scores'!$C$2:$C$131,MATCH(E41,'NCO-2015 scores'!$A$2:$A$131,0)),0) -> 0.245 | J41: =IF(ISNUMBER(MATCH(E41,'NCO-2015 scores'!$A$2:$A$131,0)),IF(ISNUMBER(INDEX('NCO-2015 scores'!$C$2:$C$131,MATCH(E41,'NCO-2015 scores'!$A$2:$A$131,0))),1,0),0) -> 1
A42: 41 | B42: General Manager, Agricultural Farm | C42: 1311.0300 | D42: 1301.10 | E42: =LEFT(C42,3) -> 131 | F42: =IF(D42="","",LEFT(D42,3)) -> 130 | G42: =IF(F42="","",IF(E42=F42,"Yes","No")) -> No | H42: =IF(D42="",0,1/COUNTIF($D$2:$D$3451,D42)) -> 1 | I42: =IFERROR(INDEX('NCO-2015 scores'!$C$2:$C$131,MATCH(E42,'NCO-2015 scores'!$A$2:$A$131,0)),0) -> 0.245 | J42: =IF(ISNUMBER(MATCH(E42,'NCO-2015 scores'!$A$2:$A$131,0)),IF(ISNUMBER(INDEX('NCO-2015 scores'!$C$2:$C$131,MATCH(E42,'NCO-2015 scores'!$A$2:$A$131,0))),1,0),0) -> 1
A43: 42 | B43: General Manager, Livestock Farm | C43: 1311.0400 | D43: 1301.40 | E43: =LEFT(C43,3) -> 131 | F43: =IF(D43="","",LEFT(D43,3)) -> 130 | G43: =IF(F43="","",IF(E43=F43,"Yes","No")) -> No | H43: =IF(D43="",0,1/COUNTIF($D$2:$D$3451,D43)) -> 1 | I43: =IFERROR(INDEX('NCO-2015 scores'!$C$2:$C$131,MATCH(E43,'NCO-2015 scores'!$A$2:$A$131,0)),0) -> 0.245 | J43: =IF(ISNUMBER(MATCH(E43,'NCO-2015 scores'!$A$2:$A$131,0)),IF(ISNUMBER(INDEX('NCO-2015 scores'!$C$2:$C$131,MATCH(E43,'NCO-2015 scores'!$A$2:$A$131,0))),1,0),0) -> 1
A44: 43 | B44: General Manager, Dairy Farm | C44: 1311.0500 | D44: 1301.50 | E44: =LEFT(C44,3) -> 131 | F44: =IF(D44="","",LEFT(D44,3)) -> 130 | G44: =IF(F44="","",IF(E44=F44,"Yes","No")) -> No | H44: =IF(D44="",0,1/COUNTIF($D$2:$D$3451,D44)) -> 1 | I44: =IFERROR(INDEX('NCO-2015 scores'!$C$2:$C$131,MATCH(E44,'NCO-2015 scores'!$A$2:$A$131,0)),0) -> 0.245 | J44: =IF(ISNUMBER(MATCH(E44,'NCO-2015 scores'!$A$2:$A$131,0)),IF(ISNUMBER(INDEX('NCO-2015 scores'!$C$2:$C$131,MATCH(E44,'NCO-2015 scores'!$A$2:$A$131,0))),1,0),0) -> 1
A45: 44 | B45: General Manager, Poultry | C45: 1311.0600 | D45: 1301.60 | E45: =LEFT(C45,3) -> 131 | F45: =IF(D45="","",LEFT(D45,3)) -> 130 | G45: =IF(F45="","",IF(E45=F45,"Yes","No")) -> No | H45: =IF(D45="",0,1/COUNTIF($D$2:$D$3451,D45)) -> 1 | I45: =IFERROR(INDEX('NCO-2015 scores'!$C$2:$C$131,MATCH(E45,'NCO-2015 scores'!$A$2:$A$131,0)),0) -> 0.245 | J45: =IF(ISNUMBER(MATCH(E45,'NCO-2015 scores'!$A$2:$A$131,0)),IF(ISNUMBER(INDEX('NCO-2015 scores'!$C$2:$C$131,MATCH(E45,'NCO-2015 scores'!$A$2:$A$131,0))),1,0),0) -> 1
A46: 45 | B46: Rubber Nursery Manager | C46: 1311.0901 | E46: =LEFT(C46,3) -> 131 | F46: =IF(D46="","",LEFT(D46,3)) | G46: =IF(F46="","",IF(E46=F46,"Yes","No")) | H46: =IF(D46="",0,1/COUNTIF($D$2:$D$3451,D46)) -> 0 | I46: =IFERROR(INDEX('NCO-2015 scores'!$C$2:$C$131,MATCH(E46,'NCO-2015 scores'!$A$2:$A$131,0)),0) -> 0.245 | J46: =IF(ISNUMBER(MATCH(E46,'NCO-2015 scores'!$A$2:$A$131,0)),IF(ISNUMBER(INDEX('NCO-2015 scores'!$C$2:$C$131,MATCH(E46,'NCO-2015 scores'!$A$2:$A$131,0))),1,0),0) -> 1
A47: 46 | B47: Manager, Aerial Planting and Cultivation | C47: 1311.1000 | D47: 1221.24 | E47: =LEFT(C47,3) -> 131 | F47: =IF(D47="","",LEFT(D47,3)) -> 122 | G47: =IF(F47="","",IF(E47=F47,"Yes","No")) -> No | H47: =IF(D47="",0,1/COUNTIF($D$2:$D$3451,D47)) -> 1 | I47: =IFERROR(INDEX('NCO-2015 scores'!$C$2:$C$131,MATCH(E47,'NCO-2015 scores'!$A$2:$A$131,0)),0) -> 0.245 | J47: =IF(ISNUMBER(MATCH(E47,'NCO-2015 scores'!$A$2:$A$131,0)),IF(ISNUMBER(INDEX('NCO-2015 scores'!$C$2:$C$131,MATCH(E47,'NCO-2015 scores'!$A$2:$A$131,0))),1,0),0) -> 1
A48: 47 | B48: Manager, Orchard | C48: 1311.1100 | D48: 1221.26 | E48: =LEFT(C48,3) -> 131 | F48: =IF(D48="","",LEFT(D48,3)) -> 122 | G48: =IF(F48="","",IF(E48=F48,"Yes","No")) -> No | H48: =IF(D48="",0,1/COUNTIF($D$2:$D$3451,D48)) -> 1 | I48: =IFERROR(INDEX('NCO-2015 scores'!$C$2:$C$131,MATCH(E48,'NCO-2015 scores'!$A$2:$A$131,0)),0) -> 0.245 | J48: =IF(ISNUMBER(MATCH(E48,'NCO-2015 scores'!$A$2:$A$131,0)),IF(ISNUMBER(INDEX('NCO-2015 scores'!$C$2:$C$131,MATCH(E48,'NCO-2015 scores'!$A$2:$A$131,0))),1,0),0) -> 1
A49: 48 | B49: Manager, Horticulture Farm | C49: 1311.1200 | D49: 1221.30 | E49: =LEFT(C49,3) -> 131 | F49: =IF(D49="","",LEFT(D49,3)) -> 122 | G49: =IF(F49="","",IF(E49=F49,"Yes","No")) -> No | H49: =IF(D49="",0,1/COUNTIF($D$2:$D$3451,D49)) -> 1 | I49: =IFERROR(INDEX('NCO-2015 scores'!$C$2:$C$131,MATCH(E49,'NCO-2015 scores'!$A$2:$A$131,0)),0) -> 0.245 | J49: =IF(ISNUMBER(MATCH(E49,'NCO-2015 scores'!$A$2:$A$131,0)),IF(ISNUMBER(INDEX('NCO-2015 scores'!$C$2:$C$131,MATCH(E49,'NCO-2015 scores'!$A$2:$A$131,0))),1,0),0) -> 1
A50: 49 | B50: Manager, Livestock Farm | C50: 1311.1300 | D50: 1221.40 | E50: =LEFT(C50,3) -> 131 | F50: =IF(D50="","",LEFT(D50,3)) -> 122 | G50: =IF(F50="","",IF(E50=F50,"Yes","No")) -> No | H50: =IF(D50="",0,1/COUNTIF($D$2:$D$3451,D50)) -> 1 | I50: =IFERROR(INDEX('NCO-2015 scores'!$C$2:$C$131,MATCH(E50,'NCO-2015 scores'!$A$2:$A$131,0)),0) -> 0.245 | J50: =IF(ISNUMBER(MATCH(E50,'NCO-2015 scores'!$A$2:$A$131,0)),IF(ISNUMBER(INDEX('NCO-2015 scores'!$C$2:$C$131,MATCH(E50,'NCO-2015 scores'!$A$2:$A$131,0))),1,0),0) -> 1
A51: 50 | B51: Manager, Dairy Farm | C51: 1311.1400 | D51: 1221.50 | E51: =LEFT(C51,3) -> 131 | F51: =IF(D51="","",LEFT(D51,3)) -> 122 | G51: =IF(F51="","",IF(E51=F51,"Yes","No")) -> No | H51: =IF(D51="",0,1/COUNTIF($D$2:$D$3451,D51)) -> 1 | I51: =IFERROR(INDEX('NCO-2015 scores'!$C$2:$C$131,MATCH(E51,'NCO-2015 scores'!$A$2:$A$131,0)),0) -> 0.245 | J51: =IF(ISNUMBER(MATCH(E51,'NCO-2015 scores'!$A$2:$A$131,0)),IF(ISNUMBER(INDEX('NCO-2015 scores'!$C$2:$C$131,MATCH(E51,'NCO-2015 scores'!$A$2:$A$131,0))),1,0),0) -> 1
A52: 51 | B52: Manager, Poultry Farm | C52: 1311.1500 | D52: 1221.60 | E52: =LEFT(C52,3) -> 131 | F52: =IF(D52="","",LEFT(D52,3)) -> 122 | G52: =IF(F52="","",IF(E52=F52,"Yes","No")) -> No | H52: =IF(D52="",0,1/COUNTIF($D$2:$D$3451,D52)) -> 1 | I52: =IFERROR(INDEX('NCO-2015 scores'!$C$2:$C$131,MATCH(E52,'NCO-2015 scores'!$A$2:$A$131,0)),0) -> 0.245 | J52: =IF(ISNUMBER(MATCH(E52,'NCO-2015 scores'!$A$2:$A$131,0)),IF(ISNUMBER(INDEX('NCO-2015 scores'!$C$2:$C$131,MATCH(E52,'NCO-2015 scores'!$A$2:$A$131,0))),1,0),0) -> 1
A53: 52 | B53: Agricultural and Forestry Production Managers, Others | C53: 1311.9900 | D53: 1221.90 | E53: =LEFT(C53,3) -> 131 | F53: =IF(D53="","",LEFT(D53,3)) -> 122 | G53: =IF(F53="","",IF(E53=F53,"Yes","No")) -> No | H53: =IF(D53="",0,1/COUNTIF($D$2:$D$3451,D53)) -> 1 | I53: =IFERROR(INDEX('NCO-2015 scores'!$C$2:$C$131,MATCH(E53,'NCO-2015 scores'!$A$2:$A$131,0)),0) -> 0.245 | J53: =IF(ISNUMBER(MATCH(E53,'NCO-2015 scores'!$A$2:$A$131,0)),IF(ISNUMBER(INDEX('NCO-2015 scores'!$C$2:$C$131,MATCH(E53,'NCO-2015 scores'!$A$2:$A$131,0))),1,0),0) -> 1
A54: 53 | B54: Manager, Agricultural Farm | C54: 1311.0700 | D54: 1221.10 | E54: =LEFT(C54,3) -> 131 | F54: =IF(D54="","",LEFT(D54,3)) -> 122 | G54: =IF(F54="","",IF(E54=F54,"Yes","No")) -> No | H54: =IF(D54="",0,1/COUNTIF($D$2:$D$3451,D54)) -> 1 | I54: =IFERROR(INDEX('NCO-2015 scores'!$C$2:$C$131,MATCH(E54,'NCO-2015 scores'!$A$2:$A$131,0)),0) -> 0.245 | J54: =IF(ISNUMBER(MATCH(E54,'NCO-2015 scores'!$A$2:$A$131,0)),IF(ISNUMBER(INDEX('NCO-2015 scores'!$C$2:$C$131,MATCH(E54,'NCO-2015 scores'!$A$2:$A$131,0))),1,0),0) -> 1
A55: 54 | B55: Manager, Plantation | C55: 1311.0800 | D55: 1221.20 | E55: =LEFT(C55,3) -> 131 | F55: =IF(D55="","",LEFT(D55,3)) -> 122 | G55: =IF(F55="","",IF(E55=F55,"Yes","No")) -> No | H55: =IF(D55="",0,1/COUNTIF($D$2:$D$3451,D55)) -> 1 | I55: =IFERROR(INDEX('NCO-2015 scores'!$C$2:$C$131,MATCH(E55,'NCO-2015 scores'!$A$2:$A$131,0)),0) -> 0.245 | J55: =IF(ISNUMBER(MATCH(E55,'NCO-2015 scores'!$A$2:$A$131,0)),IF(ISNUMBER(INDEX('NCO-2015 scores'!$C$2:$C$131,MATCH(E55,'NCO-2015 scores'!$A$2:$A$131,0))),1,0),0) -> 1
A56: 55 | B56: Manager, Nursery | C56: 1311.0900 | D56: 1221.22 | E56: =LEFT(C56,3) -> 131 | F56: =IF(D56="","",LEFT(D56,3)) -> 122 | G56: =IF(F56="","",IF(E56=F56,"Yes","No")) -> No | H56: =IF(D56="",0,1/COUNTIF($D$2:$D$3451,D56)) -> 1 | I56: =IFERROR(INDEX('NCO-2015 scores'!$C$2:$C$131,MATCH(E56,'NCO-2015 scores'!$A$2:$A$131,0)),0) -> 0.245 | J56: =IF(ISNUMBER(MATCH(E56,'NCO-2015 scores'!$A$2:$A$131,0)),IF(ISNUMBER(INDEX('NCO-2015 scores'!$C$2:$C$131,MATCH(E56,'NCO-2015 scores'!$A$2:$A$131,0))),1,0),0) -> 1
A57: 56 | B57: Fitter, General | C57: 7233.0100 | D57: 7233.10 | E57: =LEFT(C57,3) -> 723 | F57: =IF(D57="","",LEFT(D57,3)) -> 723 | G57: =IF(F57="","",IF(E57=F57,"Yes","No")) -> Yes | H57: =IF(D57="",0,1/COUNTIF($D$2:$D$3451,D57)) -> 1 | I57: =IFERROR(INDEX('NCO-2015 scores'!$C$2:$C$131,MATCH(E57,'NCO-2015 scores'!$A$2:$A$131,0)),0) -> 0.1675 | J57: =IF(ISNUMBER(MATCH(E57,'NCO-2015 scores'!$A$2:$A$131,0)),IF(ISNUMBER(INDEX('NCO-2015 scores'!$C$2:$C$131,MATCH(E57,'NCO-2015 scores'!$A$2:$A$131,0))),1,0),0) -> 1
A58: 57 | B58: Machinist | C58: 7233.0102 | E58: =LEFT(C58,3) -> 723 | F58: =IF(D58="","",LEFT(D58,3)) | G58: =IF(F58="","",IF(E58=F58,"Yes","No")) | H58: =IF(D58="",0,1/COUNTIF($D$2:$D$3451,D58)) -> 0 | I58: =IFERROR(INDEX('NCO-2015 scores'!$C$2:$C$131,MATCH(E58,'NCO-2015 scores'!$A$2:$A$131,0)),0) -> 0.1675 | J58: =IF(ISNUMBER(MATCH(E58,'NCO-2015 scores'!$A$2:$A$131,0)),IF(ISNUMBER(INDEX('NCO-2015 scores'!$C$2:$C$131,MATCH(E58,'NCO-2015 scores'!$A$2:$A$131,0))),1,0),0) -> 1
A59: 58 | B59: Fitter Levelling, Alignment & Balancing | C59: 7233.0121 | E59: =LEFT(C59,3) -> 723 | F59: =IF(D59="","",LEFT(D59,3)) | G59: =IF(F59="","",IF(E59=F59,"Yes","No")) | H59: =IF(D59="",0,1/COUNTIF($D$2:$D$3451,D59)) -> 0 | I59: =IFERROR(INDEX('NCO-2015 scores'!$C$2:$C$131,MATCH(E59,'NCO-2015 scores'!$A$2:$A$131,0)),0) -> 0.1675 | J59: =IF(ISNUMBER(MATCH(E59,'NCO-2015 scores'!$A$2:$A$131,0)),IF(ISNUMBER(INDEX('NCO-2015 scores'!$C$2:$C$131,MATCH(E59,'NCO-2015 scores'!$A$2:$A$131,0))),1,0),0) -> 1
A60: 59 | B60: Fitter, Bench | C60: 7233.0200 | D60: 7233.20 | E60: =LEFT(C60,3) -> 723 | F60: =IF(D60="","",LEFT(D60,3)) -> 723 | G60: =IF(F60="","",IF(E60=F60,"Yes","No")) -> Yes | H60: =IF(D60="",0,1/COUNTIF($D$2:$D$3451,D60)) -> 1 | I60: =IFERROR(INDEX('NCO-2015 scores'!$C$2:$C$131,MATCH(E60,'NCO-2015 scores'!$A$2:$A$131,0)),0) -> 0.1675 | J60: =IF(ISNUMBER(MATCH(E60,'NCO-2015 scores'!$A$2:$A$131,0)),IF(ISNUMBER(INDEX('NCO-2015 scores'!$C$2:$C$131,MATCH(E60,'NCO-2015 scores'!$A$2:$A$131,0))),1,0),0) -> 1
A61: 60 | B61: Mechanic, Petrol Engine | C61: 7233.0300 | D61: 7233.22 | E61: =LEFT(C61,3) -> 723 | F61: =IF(D61="","",LEFT(D61,3)) -> 723 | G61: =IF(F61="","",IF(E61=F61,"Yes","No")) -> Yes | H61: =IF(D61="",0,1/COUNTIF($D$2:$D$3451,D61)) -> 1 | I61: =IFERROR(INDEX('NCO-2015 scores'!$C$2:$C$131,MATCH(E61,'NCO-2015 scores'!$A$2:$A$131,0)),0) -> 0.1675 | J61: =IF(ISNUMBER(MATCH(E61,'NCO-2015 scores'!$A$2:$A$131,0)),IF(ISNUMBER(INDEX('NCO-2015 scores'!$C$2:$C$131,MATCH(E61,'NCO-2015 scores'!$A$2:$A$131,0))),1,0),0) -> 1
A62: 61 | B62: Millwright | C62: 7233.1200 | D62: 7233.38 | E62: =LEFT(C62,3) -> 723 | F62: =IF(D62="","",LEFT(D62,3)) -> 723 | G62: =IF(F62="","",IF(E62=F62,"Yes","No")) -> Yes | H62: =IF(D62="",0,1/COUNTIF($D$2:$D$3451,D62)) -> 1 | I62: =IFERROR(INDEX('NCO-2015 scores'!$C$2:$C$131,MATCH(E62,'NCO-2015 scores'!$A$2:$A$131,0)),0) -> 0.1675 | J62: =IF(ISNUMBER(MATCH(E62,'NCO-2015 scores'!$A$2:$A$131,0)),IF(ISNUMBER(INDEX('NCO-2015 scores'!$C$2:$C$131,MATCH(E62,'NCO-2015 scores'!$A$2:$A$131,0))),1,0),0) -> 1
A63: 62 | B63: Mechanic, Diesel Engine | C63: 7233.0400 | D63: 7233.24 | E63: =LEFT(C63,3) -> 723 | F63: =IF(D63="","",LEFT(D63,3)) -> 723 | G63: =IF(F63="","",IF(E63=F63,"Yes","No")) -> Yes | H63: =IF(D63="",0,1/COUNTIF($D$2:$D$3451,D63)) -> 1 | I63: =IFERROR(INDEX('NCO-2015 scores'!$C$2:$C$131,MATCH(E63,'NCO-2015 scores'!$A$2:$A$131,0)),0) -> 0.1675 | J63: =IF(ISNUMBER(MATCH(E63,'NCO-2015 scores'!$A$2:$A$131,0)),IF(ISNUMBER(INDEX('NCO-2015 scores'!$C$2:$C$131,MATCH(E63,'NCO-2015 scores'!$A$2:$A$131,0))),1,0),0) -> 1
A64: 63 | B64: Mechanic, Pump | C64: 7233.1300 | D64: 7233.40 | E64: =LEFT(C64,3) -> 723 | F64: =IF(D64="","",LEFT(D64,3)) -> 723 | G64: =IF(F64="","",IF(E64=F64,"Yes","No")) -> Yes | H64: =IF(D64="",0,1/COUNTIF($D$2:$D$3451,D64)) -> 1 | I64: =IFERROR(INDEX('NCO-2015 scores'!$C$2:$C$131,MATCH(E64,'NCO-2015 scores'!$A$2:$A$131,0)),0) -> 0.1675 | J64: =IF(ISNUMBER(MATCH(E64,'NCO-2015 scores'!$A$2:$A$131,0)),IF(ISNUMBER(INDEX('NCO-2015 scores'!$C$2:$C$131,MATCH(E64,'NCO-2015 scores'!$A$2:$A$131,0))),1,0),0) -> 1
A65: 64 | B65: Belt Conveyor Maintenance | C65: 7233.0401 | E65: =LEFT(C65,3) -> 723 | F65: =IF(D65="","",LEFT(D65,3)) | G65: =IF(F65="","",IF(E65=F65,"Yes","No")) | H65: =IF(D65="",0,1/COUNTIF($D$2:$D$3451,D65)) -> 0 | I65: =IFERROR(INDEX('NCO-2015 scores'!$C$2:$C$131,MATCH(E65,'NCO-2015 scores'!$A$2:$A$131,0)),0) -> 0.1675 | J65: =IF(ISNUMBER(MATCH(E65,'NCO-2015 scores'!$A$2:$A$131,0)),IF(ISNUMBER(INDEX('NCO-2015 scores'!$C$2:$C$131,MATCH(E65,'NCO-2015 scores'!$A$2:$A$131,0))),1,0),0) -> 1
A66: 65 | B66: Plumber (Pumps & E/M Mechanic) | C66: 7233.1301 | E66: =LEFT(C66,3) -> 723 | F66: =IF(D66="","",LEFT(D66,3)) | G66: =IF(F66="","",IF(E66=F66,"Yes","No")) | H66: =IF(D66="",0,1/COUNTIF($D$2:$D$3451,D66)) -> 0 | I66: =IFERROR(INDEX('NCO-2015 scores'!$C$2:$C$131,MATCH(E66,'NCO-2015 scores'!$A$2:$A$131,0)),0) -> 0.1675 | J66: =IF(ISNUMBER(MATCH(E66,'NCO-2015 scores'!$A$2:$A$131,0)),IF(ISNUMBER(INDEX('NCO-2015 scores'!$C$2:$C$131,MATCH(E66,'NCO-2015 scores'!$A$2:$A$131,0))),1,0),0) -> 1
A67: 66 | B67: Conveyor Operation and Maintenance | C67: 7233.0402 | E67: =LEFT(C67,3) -> 723 | F67: =IF(D67="","",LEFT(D67,3)) | G67: =IF(F67="","",IF(E67=F67,"Yes","No")) | H67: =IF(D67="",0,1/COUNTIF($D$2:$D$3451,D67)) -> 0 | I67: =IFERROR(INDEX('NCO-2015 scores'!$C$2:$C$131,MATCH(E67,'NCO-2015 scores'!$A$2:$A$131,0)),0) -> 0.1675 | J67: =IF(ISNUMBER(MATCH(E67,'NCO-2015 scores'!$A$2:$A$131,0)),IF(ISNUMBER(INDEX('NCO-2015 scores'!$C$2:$C$131,MATCH(E67,'NCO-2015 scores'!$A$2:$A$131,0))),1,0),0) -> 1
A68: 67 | B68: Mechanic, Dairy Maintenance | C68: 7233.1400 | D68: 7233.42 | E68: =LEFT(C68,3) -> 723 | F68: =IF(D68="","",LEFT(D68,3)) -> 723 | G68: =IF(F68="","",IF(E68=F68,"Yes","No")) -> Yes | H68: =IF(D68="",0,1/COUNTIF($D$2:$D$3451,D68)) -> 1 | I68: =IFERROR(INDEX('NCO-2015 scores'!$C$2:$C$131,MATCH(E68,'NCO-2015 scores'!$A$2:$A$131,0)),0) -> 0.1675 | J68: =IF(ISNUMBER(MATCH(E68,'NCO-2015 scores'!$A$2:$A$131,0)),IF(ISNUMBER(INDEX('NCO-2015 scores'!$C$2:$C$131,MATCH(E68,'NCO-2015 scores'!$A$2:$A$131,0))),1,0),0) -> 1
A69: 68 | B69: Mechanic, Gas/Diesel Engine | C69: 7233.0600 | D69: 7233.26 | E69: =LEFT(C69,3) -> 723 | F69: =IF(D69="","",LEFT(D69,3)) -> 723 | G69: =IF(F69="","",IF(E69=F69,"Yes","No")) -> Yes | H69: =IF(D69="",0,1/COUNTIF($D$2:$D$3451,D69)) -> 1 | I69: =IFERROR(INDEX('NCO-2015 scores'!$C$2:$C$131,MATCH(E69,'NCO-2015 scores'!$A$2:$A$131,0)),0) -> 0.1675 | J69: =IF(ISNUMBER(MATCH(E69,'NCO-2015 scores'!$A$2:$A$131,0)),IF(ISNUMBER(INDEX('NCO-2015 scores'!$C$2:$C$131,MATCH(E69,'NCO-2015 scores'!$A$2:$A$131,0))),1,0),0) -> 1
A70: 69 | B70: Mechanic, Earth Moving Machinery | C70: 7233.0700 | D70: 7233.28 | E70: =LEFT(C70,3) -> 723 | F70: =IF(D70="","",LEFT(D70,3)) -> 723 | G70: =IF(F70="","",IF(E70=F70,"Yes","No")) -> Yes | H70: =IF(D70="",0,1/COUNTIF($D$2:$D$3451,D70)) -> 1 | I70: =IFERROR(INDEX('NCO-2015 scores'!$C$2:$C$131,MATCH(E70,'NCO-2015 scores'!$A$2:$A$131,0)),0) -> 0.1675 | J70: =IF(ISNUMBER(MATCH(E70,'NCO-2015 scores'!$A$2:$A$131,0)),IF(ISNUMBER(INDEX('NCO-2015 scores'!$C$2:$C$131,MATCH(E70,'NCO-2015 scores'!$A$2:$A$131,0))),1,0),0) -> 1
A71: 70 | B71: Mobile Equipment Maintenance | C71: 7233.0701 | E71: =LEFT(C71,3) -> 723 | F71: =IF(D71="","",LEFT(D71,3)) | G71: =IF(F71="","",IF(E71=F71,"Yes","No")) | H71: =IF(D71="",0,1/COUNTIF($D$2:$D$3451,D71)) -> 0 | I71: =IFERROR(INDEX('NCO-2015 scores'!$C$2:$C$131,MATCH(E71,'NCO-2015 scores'!$A$2:$A$131,0)),0) -> 0.1675 | J71: =IF(ISNUMBER(MATCH(E71,'NCO-2015 scores'!$A$2:$A$131,0)),IF(ISNUMBER(INDEX('NCO-2015 scores'!$C$2:$C$131,MATCH(E71,'NCO-2015 scores'!$A$2:$A$131,0))),1,0),0) -> 1
A72: 71 | B72: Mechanic, Road Roller | C72: 7233.0800 | D72: 7233.30 | E72: =LEFT(C72,3) -> 723 | F72: =IF(D72="","",LEFT(D72,3)) -> 723 | G72: =IF(F72="","",IF(E72=F72,"Yes","No")) -> Yes | H72: =IF(D72="",0,1/COUNTIF($D$2:$D$3451,D72)) -> 1 | I72: =IFERROR(INDEX('NCO-2015 scores'!$C$2:$C$131,MATCH(E72,'NCO-2015 scores'!$A$2:$A$131,0)),0) -> 0.1675 | J72: =IF(ISNUMBER(MATCH(E72,'NCO-2015 scores'!$A$2:$A$131,0)),IF(ISNUMBER(INDEX('NCO-2015 scores'!$C$2:$C$131,MATCH(E72,'NCO-2015 scores'!$A$2:$A$131,0))),1,0),0) -> 1
A73: 72 | B73: Mechanic, Turbine | C73: 7233.0900 | D73: 7233.32 | E73: =LEFT(C73,3) -> 723 | F73: =IF(D73="","",LEFT(D73,3)) -> 723 | G73: =IF(F73="","",IF(E73=F73,"Yes","No")) -> Yes | H73: =IF(D73="",0,1/COUNTIF($D$2:$D$3451,D73)) -> 1 | I73: =IFERROR(INDEX('NCO-2015 scores'!$C$2:$C$131,MATCH(E73,'NCO-2015 scores'!$A$2:$A$131,0)),0) -> 0.1675 | J73: =IF(ISNUMBER(MATCH(E73,'NCO-2015 scores'!$A$2:$A$131,0)),IF(ISNUMBER(INDEX('NCO-2015 scores'!$C$2:$C$131,MATCH(E73,'NCO-2015 scores'!$A$2:$A$131,0))),1,0),0) -> 1
A74: 73 | B74: Mechanic, Stationery Steam Engine | C74: 7233.1000 | D74: 7233.34 | E74: =LEFT(C74,3) -> 723 | F74: =IF(D74="","",LEFT(D74,3)) -> 723 | G74: =IF(F74="","",IF(E74=F74,"Yes","No")) -> Yes | H74: =IF(D74="",0,1/COUNTIF($D$2:$D$3451,D74)) -> 1 | I74: =IFERROR(INDEX('NCO-2015 scores'!$C$2:$C$131,MATCH(E74,'NCO-2015 scores'!$A$2:$A$131,0)),0) -> 0.1675 | J74: =IF(ISNUMBER(MATCH(E74,'NCO-2015 scores'!$A$2:$A$131,0)),IF(ISNUMBER(INDEX('NCO-2015 scores'!$C$2:$C$131,MATCH(E74,'NCO-2015 scores'!$A$2:$A$131,0))),1,0),0) -> 1
A75: 74 | B75: Mechanic, Maintenance, Chemical Plant/Technician, Maintenance, Chemical Plant | C75: 7233.1100 | D75: 7233.36 | E75: =LEFT(C75,3) -> 723 | F75: =IF(D75="","",LEFT(D75,3)) -> 723 | G75: =IF(F75="","",IF(E75=F75,"Yes","No")) -> Yes | H75: =IF(D75="",0,1/COUNTIF($D$2:$D$3451,D75)) -> 1 | I75: =IFERROR(INDEX('NCO-2015 scores'!$C$2:$C$131,MATCH(E75,'NCO-2015 scores'!$A$2:$A$131,0)),0) -> 0.1675 | J75: =IF(ISNUMBER(MATCH(E75,'NCO-2015 scores'!$A$2:$A$131,0)),IF(ISNUMBER(INDEX('NCO-2015 scores'!$C$2:$C$131,MATCH(E75,'NCO-2015 scores'!$A$2:$A$131,0))),1,0),0) -> 1
A76: 75 | B76: Bearing Maintenance | C76: 7233.0301 | E76: =LEFT(C76,3) -> 723 | F76: =IF(D76="","",LEFT(D76,3)) | G76: =IF(F76="","",IF(E76=F76,"Yes","No")) | H76: =IF(D76="",0,1/COUNTIF($D$2:$D$3451,D76)) -> 0 | I76: =IFERROR(INDEX('NCO-2015 scores'!$C$2:$C$131,MATCH(E76,'NCO-2015 scores'!$A$2:$A$131,0)),0) -> 0.1675 | J76: =IF(ISNUMBER(MATCH(E76,'NCO-2015 scores'!$A$2:$A$131,0)),IF(ISNUMBER(INDEX('NCO-2015 scores'!$C$2:$C$131,MATCH(E76,'NCO-2015 scores'!$A$2:$A$131,0))),1,0),0) -> 1
A77: 76 | B77: Fitter, Marine | C77: 7233.2200 | D77: 7233.62 | E77: =LEFT(C77,3) -> 723 | F77: =IF(D77="","",LEFT(D77,3)) -> 723 | G77: =IF(F77="","",IF(E77=F77,"Yes","No")) -> Yes | H77: =IF(D77="",0,1/COUNTIF($D$2:$D$3451,D77)) -> 1 | I77: =IFERROR(INDEX('NCO-2015 scores'!$C$2:$C$131,MATCH(E77,'NCO-2015 scores'!$A$2:$A$131,0)),0) -> 0.1675 | J77: =IF(ISNUMBER(MATCH(E77,'NCO-2015 scores'!$A$2:$A$131,0)),IF(ISNUMBER(INDEX('NCO-2015 scores'!$C$2:$C$131,MATCH(E77,'NCO-2015 scores'!$A$2:$A$131,0))),1,0),0) -> 1
A78: 77 | B78: Fitter, Railway Carriage and Wagon | C78: 7233.2300 | D78: 7233.63 | E78: =LEFT(C78,3) -> 723 | F78: =IF(D78="","",LEFT(D78,3)) -> 723 | G78: =IF(F78="","",IF(E78=F78,"Yes","No")) -> Yes | H78: =IF(D78="",0,1/COUNTIF($D$2:$D$3451,D78)) -> 1 | I78: =IFERROR(INDEX('NCO-2015 scores'!$C$2:$C$131,MATCH(E78,'NCO-2015 scores'!$A$2:$A$131,0)),0) -> 0.1675 | J78: =IF(ISNUMBER(MATCH(E78,'NCO-2015 scores'!$A$2:$A$131,0)),IF(ISNUMBER(INDEX('NCO-2015 scores'!$C$2:$C$131,MATCH(E78,'NCO-2015 scores'!$A$2:$A$131,0))),1,0),0) -> 1
A79: 78 | B79: Fitter, Loco | C79: 7233.2400 | D79: 7233.64 | E79: =LEFT(C79,3) -> 723 | F79: =IF(D79="","",LEFT(D79,3)) -> 723 | G79: =IF(F79="","",IF(E79=F79,"Yes","No")) -> Yes | H79: =IF(D79="",0,1/COUNTIF($D$2:$D$3451,D79)) -> 1 | I79: =IFERROR(INDEX('NCO-2015 scores'!$C$2:$C$131,MATCH(E79,'NCO-2015 scores'!$A$2:$A$131,0)),0) -> 0.1675 | J79: =IF(ISNUMBER(MATCH(E79,'NCO-2015 scores'!$A$2:$A$131,0)),IF(ISNUMBER(INDEX('NCO-2015 scores'!$C$2:$C$131,MATCH(E79,'NCO-2015 scores'!$A$2:$A$131,0))),1,0),0) -> 1
A80: 79 | B80: Loco Cleaner | C80: 7233.2500 | D80: 7233.65 | E80: =LEFT(C80,3) -> 723 | F80: =IF(D80="","",LEFT(D80,3)) -> 723 | G80: =IF(F80="","",IF(E80=F80,"Yes","No")) -> Yes | H80: =IF(D80="",0,1/COUNTIF($D$2:$D$3451,D80)) -> 1 | I80: =IFERROR(INDEX('NCO-2015 scores'!$C$2:$C$131,MATCH(E80,'NCO-2015 scores'!$A$2:$A$131,0)),0) -> 0.1675 | J80: =IF(ISNUMBER(MATCH(E80,'NCO-2015 scores'!$A$2:$A$131,0)),IF(ISNUMBER(INDEX('NCO-2015 scores'!$C$2:$C$131,MATCH(E80,'NCO-2015 scores'!$A$2:$A$131,0))),1,0),0) -> 1
A81: 80 | B81: Mechanic, Mining Machinery | C81: 7233.1500 | D81: 7233.44 | E81: =LEFT(C81,3) -> 723 | F81: =IF(D81="","",LEFT(D81,3)) -> 723 | G81: =IF(F81="","",IF(E81=F81,"Yes","No")) -> Yes | H81: =IF(D81="",0,1/COUNTIF($D$2:$D$3451,D81)) -> 1 | I81: =IFERROR(INDEX('NCO-2015 scores'!$C$2:$C$131,MATCH(E81,'NCO-2015 scores'!$A$2:$A$131,0)),0) -> 0.1675 | J81: =IF(ISNUMBER(MATCH(E81,'NCO-2015 scores'!$A$2:$A$131,0)),IF(ISNUMBER(INDEX('NCO-2015 scores'!$C$2:$C$131,MATCH(E81,'NCO-2015 scores'!$A$2:$A$131,0))),1,0),0) -> 1
A82: 81 | B82: Fitter, Bicycle | C82: 7233.2600 | D82: 7233.66 | E82: =LEFT(C82,3) -> 723 | F82: =IF(D82="","",LEFT(D82,3)) -> 723 | G82: =IF(F82="","",IF(E82=F82,"Yes","No")) -> Yes | H82: =IF(D82="",0,1/COUNTIF($D$2:$D$3451,D82)) -> 1 | I82: =IFERROR(INDEX('NCO-2015 scores'!$C$2:$C$131,MATCH(E82,'NCO-2015 scores'!$A$2:$A$131,0)),0) -> 0.1675 | J82: =IF(ISNUMBER(MATCH(E82,'NCO-2015 scores'!$A$2:$A$131,0)),IF(ISNUMBER(INDEX('NCO-2015 scores'!$C$2:$C$131,MATCH(E82,'NCO-2015 scores'!$A$2:$A$131,0))),1,0),0) -> 1
A83: 82 | B83: Mechanic, Textile Machinery | C83: 7233.1600 | D83: 7233.46 | E83: =LEFT(C83,3) -> 723 | F83: =IF(D83="","",LEFT(D83,3)) -> 723 | G83: =IF(F83="","",IF(E83=F83,"Yes","No")) -> Yes | H83: =IF(D83="",0,1/COUNTIF($D$2:$D$3451,D83)) -> 1 | I83: =IFERROR(INDEX('NCO-2015 scores'!$C$2:$C$131,MATCH(E83,'NCO-2015 scores'!$A$2:$A$131,0)),0) -> 0.1675 | J83: =IF(ISNUMBER(MATCH(E83,'NCO-2015 scores'!$A$2:$A$131,0)),IF(ISNUMBER(INDEX('NCO-2015 scores'!$C$2:$C$131,MATCH(E83,'NCO-2015 scores'!$A$2:$A$131,0))),1,0),0) -> 1
A84: 83 | B84: Fitter, Signal | C84: 7233.2700 | D84: 7233.70 | E84: =LEFT(C84,3) -> 723 | F84: =IF(D84="","",LEFT(D84,3)) -> 723 | G84: =IF(F84="","",IF(E84=F84,"Yes","No")) -> Yes | H84: =IF(D84="",0,1/COUNTIF($D$2:$D$3451,D84)) -> 1 | I84: =IFERROR(INDEX('NCO-2015 scores'!$C$2:$C$131,MATCH(E84,'NCO-2015 scores'!$A$2:$A$131,0)),0) -> 0.1675 | J84: =IF(ISNUMBER(MATCH(E84,'NCO-2015 scores'!$A$2:$A$131,0)),IF(ISNUMBER(INDEX('NCO-2015 scores'!$C$2:$C$131,MATCH(E84,'NCO-2015 scores'!$A$2:$A$131,0))),1,0),0) -> 1
A85: 84 | B85: Mechanic, Printing Machinery | C85: 7233.1700 | D85: 7233.48 | E85: =LEFT(C85,3) -> 723 | F85: =IF(D85="","",LEFT(D85,3)) -> 723 | G85: =IF(F85="","",IF(E85=F85,"Yes","No")) -> Yes | H85: =IF(D85="",0,1/COUNTIF($D$2:$D$3451,D85)) -> 1 | I85: =IFERROR(INDEX('NCO-2015 scores'!$C$2:$C$131,MATCH(E85,'NCO-2015 scores'!$A$2:$A$131,0)),0) -> 0.1675 | J85: =IF(ISNUMBER(MATCH(E85,'NCO-2015 scores'!$A$2:$A$131,0)),IF(ISNUMBER(INDEX('NCO-2015 scores'!$C$2:$C$131,MATCH(E85,'NCO-2015 scores'!$A$2:$A$131,0))),1,0),0) -> 1
A86: 85 | B86: Mechanic, Sewing Machine | C86: 7233.1800 | D86: 7233.52 | E86: =LEFT(C86,3) -> 723 | F86: =IF(D86="","",LEFT(D86,3)) -> 723 | G86: =IF(F86="","",IF(E86=F86,"Yes","No")) -> Yes | H86: =IF(D86="",0,1/COUNTIF($D$2:$D$3451,D86)) -> 1 | I86: =IFERROR(INDEX('NCO-2015 scores'!$C$2:$C$131,MATCH(E86,'NCO-2015 scores'!$A$2:$A$131,0)),0) -> 0.1675 | J86: =IF(ISNUMBER(MATCH(E86,'NCO-2015 scores'!$A$2:$A$131,0)),IF(ISNUMBER(INDEX('NCO-2015 scores'!$C$2:$C$131,MATCH(E86,'NCO-2015 scores'!$A$2:$A$131,0))),1,0),0) -> 1
A87: 86 | B87: Lamp Repairman, Mines | C87: 7233.1900 | D87: 7233.55 | E87: =LEFT(C87,3) -> 723 | F87: =IF(D87="","",LEFT(D87,3)) -> 723 | G87: =IF(F87="","",IF(E87=F87,"Yes","No")) -> Yes | H87: =IF(D87="",0,1/COUNTIF($D$2:$D$3451,D87)) -> 1 | I87: =IFERROR(INDEX('NCO-2015 scores'!$C$2:$C$131,MATCH(E87,'NCO-2015 scores'!$A$2:$A$131,0)),0) -> 0.1675 | J87: =IF(ISNUMBER(MATCH(E87,'NCO-2015 scores'!$A$2:$A$131,0)),IF(ISNUMBER(INDEX('NCO-2015 scores'!$C$2:$C$131,MATCH(E87,'NCO-2015 scores'!$A$2:$A$131,0))),1,0),0) -> 1
A88: 87 | B88: Mechanic, Repairman (Domestic Appliances) | C88: 7233.2000 | D88: 7233.58 | E88: =LEFT(C88,3) -> 723 | F88: =IF(D88="","",LEFT(D88,3)) -> 723 | G88: =IF(F88="","",IF(E88=F88,"Yes","No")) -> Yes | H88: =IF(D88="",0,1/COUNTIF($D$2:$D$3451,D88)) -> 1 | I88: =IFERROR(INDEX('NCO-2015 scores'!$C$2:$C$131,MATCH(E88,'NCO-2015 scores'!$A$2:$A$131,0)),0) -> 0.1675 | J88: =IF(ISNUMBER(MATCH(E88,'NCO-2015 scores'!$A$2:$A$131,0)),IF(ISNUMBER(INDEX('NCO-2015 scores'!$C$2:$C$131,MATCH(E88,'NCO-2015 scores'!$A$2:$A$131,0))),1,0),0) -> 1
... A90: 89 | B90: Agriculture Engineering Technician | C90: 7233.2800 | D90: 7233.80 | E90: =LEFT(C90,3) -> 723 | F90: =IF(D90="","",LEFT(D90,3)) -> 723 | G90: =IF(F90="","",IF(E90=F90,"Yes","No")) -> Yes | H90: =IF(D90="",0,1/COUNTIF($D$2:$D$3451,D90)) -> 1 | I90: =IFERROR(INDEX('NCO-2015 scores'!$C$2:$C$131,MATCH(E90,'NCO-2015 scores'!$A$2:$A$131,0)),0) -> 0.1675 | J90: =IF(ISNUMBER(MATCH(E90,'NCO-2015 scores'!$A$2:$A$131,0)),IF(ISNUMBER(INDEX('NCO-2015 scores'!$C$2:$C$131,MATCH(E90,'NCO-2015 scores'!$A$2:$A$131,0))),1,0),0) -> 1
A91: 90 | B91: Fitter: Hydraulic and Pneumatic System | C91: 7233.2901 | E91: =LEFT(C91,3) -> 723 | F91: =IF(D91="","",LEFT(D91,3)) | G91: =IF(F91="","",IF(E91=F91,"Yes","No")) | H91: =IF(D91="",0,1/COUNTIF($D$2:$D$3451,D91)) -> 0 | I91: =IFERROR(INDEX('NCO-2015 scores'!$C$2:$C$131,MATCH(E91,'NCO-2015 scores'!$A$2:$A$131,0)),0) -> 0.1675 | J91: =IF(ISNUMBER(MATCH(E91,'NCO-2015 scores'!$A$2:$A$131,0)),IF(ISNUMBER(INDEX('NCO-2015 scores'!$C$2:$C$131,MATCH(E91,'NCO-2015 scores'!$A$2:$A$131,0))),1,0),0) -> 1
A92: 91 | B92: Machinery Mechanics and Fitters, Other | C92: 7233.9900 | D92: 7233.90 | E92: =LEFT(C92,3) -> 723 | F92: =IF(D92="","",LEFT(D92,3)) -> 723 | G92: =IF(F92="","",IF(E92=F92,"Yes","No")) -> Yes | H92: =IF(D92="",0,1/COUNTIF($D$2:$D$3451,D92)) -> 1 | I92: =IFERROR(INDEX('NCO-2015 scores'!$C$2:$C$131,MATCH(E92,'NCO-2015 scores'!$A$2:$A$131,0)),0) -> 0.1675 | J92: =IF(ISNUMBER(MATCH(E92,'NCO-2015 scores'!$A$2:$A$131,0)),IF(ISNUMBER(INDEX('NCO-2015 scores'!$C$2:$C$131,MATCH(E92,'NCO-2015 scores'!$A$2:$A$131,0))),1,0),0) -> 1
A93: 92 | B93: Micro Irrigation Technician | C93: 3142.0101 | E93: =LEFT(C93,3) -> 314 | F93: =IF(D93="","",LEFT(D93,3)) | G93: =IF(F93="","",IF(E93=F93,"Yes","No")) | H93: =IF(D93="",0,1/COUNTIF($D$2:$D$3451,D93)) -> 0 | I93: =IFERROR(INDEX('NCO-2015 scores'!$C$2:$C$131,MATCH(E93,'NCO-2015 scores'!$A$2:$A$131,0)),0) -> 0.2833 | J93: =IF(ISNUMBER(MATCH(E93,'NCO-2015 scores'!$A$2:$A$131,0)),IF(ISNUMBER(INDEX('NCO-2015 scores'!$C$2:$C$131,MATCH(E93,'NCO-2015 scores'!$A$2:$A$131,0))),1,0),0) -> 1
A94: 93 | B94: Bare Foot Technician (BFT) | C94: 3142.0201 | E94: =LEFT(C94,3) -> 314 | F94: =IF(D94="","",LEFT(D94,3)) | G94: =IF(F94="","",IF(E94=F94,"Yes","No")) | H94: =IF(D94="",0,1/COUNTIF($D$2:$D$3451,D94)) -> 0 | I94: =IFERROR(INDEX('NCO-2015 scores'!$C$2:$C$131,MATCH(E94,'NCO-2015 scores'!$A$2:$A$131,0)),0) -> 0.2833 | J94: =IF(ISNUMBER(MATCH(E94,'NCO-2015 scores'!$A$2:$A$131,0)),IF(ISNUMBER(INDEX('NCO-2015 scores'!$C$2:$C$131,MATCH(E94,'NCO-2015 scores'!$A$2:$A$131,0))),1,0),0) -> 1
A95: 94 | B95: Agricultural Technicians, Others | C95: 3142.9900 | E95: =LEFT(C95,3) -> 314 | F95: =IF(D95="","",LEFT(D95,3)) | G95: =IF(F95="","",IF(E95=F95,"Yes","No")) | H95: =IF(D95="",0,1/COUNTIF($D$2:$D$3451,D95)) -> 0 | I95: =IFERROR(INDEX('NCO-2015 scores'!$C$2:$C$131,MATCH(E95,'NCO-2015 scores'!$A$2:$A$131,0)),0) -> 0.2833 | J95: =IF(ISNUMBER(MATCH(E95,'NCO-2015 scores'!$A$2:$A$131,0)),IF(ISNUMBER(INDEX('NCO-2015 scores'!$C$2:$C$131,MATCH(E95,'NCO-2015 scores'!$A$2:$A$131,0))),1,0),0) -> 1
A96: 95 | B96: Community Service Provider | C96: 6116.0112 | E96: =LEFT(C96,3) -> 611 | F96: =IF(D96="","",LEFT(D96,3)) | G96: =IF(F96="","",IF(E96=F96,"Yes","No")) | H96: =IF(D96="",0,1/COUNTIF($D$2:$D$3451,D96)) -> 0 | I96: =IFERROR(INDEX('NCO-2015 scores'!$C$2:$C$131,MATCH(E96,'NCO-2015 scores'!$A$2:$A$131,0)),0) -> 0.175 | J96: =IF(ISNUMBER(MATCH(E96,'NCO-2015 scores'!$A$2:$A$131,0)),IF(ISNUMBER(INDEX('NCO-2015 scores'!$C$2:$C$131,MATCH(E96,'NCO-2015 scores'!$A$2:$A$131,0))),1,0),0) -> 1
A97: 96 | B97: Agriculture Extension Executive | C97: 6116.0101 | E97: =LEFT(C97,3) -> 611 | F97: =IF(D97="","",LEFT(D97,3)) | G97: =IF(F97="","",IF(E97=F97,"Yes","No")) | H97: =IF(D97="",0,1/COUNTIF($D$2:$D$3451,D97)) -> 0 | I97: =IFERROR(INDEX('NCO-2015 scores'!$C$2:$C$131,MATCH(E97,'NCO-2015 scores'!$A$2:$A$131,0)),0) -> 0.175 | J97: =IF(ISNUMBER(MATCH(E97,'NCO-2015 scores'!$A$2:$A$131,0)),IF(ISNUMBER(INDEX('NCO-2015 scores'!$C$2:$C$131,MATCH(E97,'NCO-2015 scores'!$A$2:$A$131,0))),1,0),0) -> 1
A98: 97 | B98: Agriculture Extension Service Provider | C98: 6116.0102 | E98: =LEFT(C98,3) -> 611 | F98: =IF(D98="","",LEFT(D98,3)) | G98: =IF(F98="","",IF(E98=F98,"Yes","No")) | H98: =IF(D98="",0,1/COUNTIF($D$2:$D$3451,D98)) -> 0 | I98: =IFERROR(INDEX('NCO-2015 scores'!$C$2:$C$131,MATCH(E98,'NCO-2015 scores'!$A$2:$A$131,0)),0) -> 0.175 | J98: =IF(ISNUMBER(MATCH(E98,'NCO-2015 scores'!$A$2:$A$131,0)),IF(ISNUMBER(INDEX('NCO-2015 scores'!$C$2:$C$131,MATCH(E98,'NCO-2015 scores'!$A$2:$A$131,0))),1,0),0) -> 1
A99: 98 | B99: Air Traffic Controller Specialist | C99: 3154.0100 | D99: 3144.10 | E99: =LEFT(C99,3) -> 315 | F99: =IF(D99="","",LEFT(D99,3)) -> 314 | G99: =IF(F99="","",IF(E99=F99,"Yes","No")) -> No | H99: =IF(D99="",0,1/COUNTIF($D$2:$D$3451,D99)) -> 1 | I99: =IFERROR(INDEX('NCO-2015 scores'!$C$2:$C$131,MATCH(E99,'NCO-2015 scores'!$A$2:$A$131,0)),0) -> 0.288 | J99: =IF(ISNUMBER(MATCH(E99,'NCO-2015 scores'!$A$2:$A$131,0)),IF(ISNUMBER(INDEX('NCO-2015 scores'!$C$2:$C$131,MATCH(E99,'NCO-2015 scores'!$A$2:$A$131,0))),1,0),0) -> 1
A100: 99 | B100: Traffic Controller, Air Service | C100: 3154.0200 | D100: 3144.20 | E100: =LEFT(C100,3) -> 315 | F100: =IF(D100="","",LEFT(D100,3)) -> 314 | G100: =IF(F100="","",IF(E100=F100,"Yes","No")) -> No | H100: =IF(D100="",0,1/COUNTIF($D$2:$D$3451,D100)) -> 1 | I100: =IFERROR(INDEX('NCO-2015 scores'!$C$2:$C$131,MATCH(E100,'NCO-2015 scores'!$A$2:$A$131,0)),0) -> 0.288 | J100: =IF(ISNUMBER(MATCH(E100,'NCO-2015 scores'!$A$2:$A$131,0)),IF(ISNUMBER(INDEX('NCO-2015 scores'!$C$2:$C$131,MATCH(E100,'NCO-2015 scores'!$A$2:$A$131,0))),1,0),0) -> 1
A101: 100 | B101: Air Traffic Controllers, Other | C101: 3154.9900 | D101: 3144.90 | E101: =LEFT(C101,3) -> 315 | F101: =IF(D101="","",LEFT(D101,3)) -> 314 | G101: =IF(F101="","",IF(E101=F101,"Yes","No")) -> No | H101: =IF(D101="",0,1/COUNTIF($D$2:$D$3451,D101)) -> 1 | I101: =IFERROR(INDEX('NCO-2015 scores'!$C$2:$C$131,MATCH(E101,'NCO-2015 scores'!$A$2:$A$131,0)),0) -> 0.288 | J101: =IF(ISNUMBER(MATCH(E101,'NCO-2015 scores'!$A$2:$A$131,0)),IF(ISNUMBER(INDEX('NCO-2015 scores'!$C$2:$C$131,MATCH(E101,'NCO-2015 scores'!$A$2:$A$131,0))),1,0),0) -> 1
...

Sheet ILO links
A1: ISCO-08 code | B1: ISCO-08 title | C1: ISCO-88 code | D1: ISCO-88 title | E1: Partial match (p) | F1: ILO comment (as printed; may be clipped) | G1: NCO-2004 group (= ISCO-88 first 3 digits) | H1: ILO exposure score of ISCO-08 job | I1: ILO exposure gradient | J1: First link of this job to this group (1/0)
A2: 1111 | B2: Legislators | C2: 1110 | D2: Legislators | G2: =LEFT(C2,3) -> 111 | H2: 0.31 | I2: Not Exposed | J2: =IF(COUNTIFS($G$2:G2,G2,$A$2:A2,A2)=1,1,0) -> 1
A3: 1112 | B3: Senior Government Officials | C3: 1120 | D3: Senior government officials | G3: =LEFT(C3,3) -> 112 | H3: 0.38 | I3: Minimal Exposure | J3: =IF(COUNTIFS($G$2:G3,G3,$A$2:A3,A3)=1,1,0) -> 1
A4: 1113 | B4: Traditional Chiefs and Heads of Villages | C4: 1130 | D4: Traditional chiefs and heads of villages | G4: =LEFT(C4,3) -> 113 | H4: 0.23 | I4: Not Exposed | J4: =IF(COUNTIFS($G$2:G4,G4,$A$2:A4,A4)=1,1,0) -> 1
A5: 1114 | B5: Senior Officials of Special-interest Organizations | C5: 1141 | D5: Senior officials of political-party organisations | G5: =LEFT(C5,3) -> 114 | H5: 0.37 | I5: Minimal Exposure | J5: =IF(COUNTIFS($G$2:G5,G5,$A$2:A5,A5)=1,1,0) -> 1
A6: 1114 | B6: Senior Officials of Special-interest Organizations | C6: 1142 | D6: Senior officials of employers', workers' and other economic-interest organisations | G6: =LEFT(C6,3) -> 114 | H6: 0.37 | I6: Minimal Exposure | J6: =IF(COUNTIFS($G$2:G6,G6,$A$2:A6,A6)=1,1,0) -> 0
A7: 1114 | B7: Senior Officials of Special-interest Organizations | C7: 1143 | D7: Senior officials of humanitarian and other special- interest organisations | G7: =LEFT(C7,3) -> 114 | H7: 0.37 | I7: Minimal Exposure | J7: =IF(COUNTIFS($G$2:G7,G7,$A$2:A7,A7)=1,1,0) -> 0
A8: 1120 | B8: Managing Directors and Chief Executives | C8: 1210 | D8: Directors and chief executives | G8: =LEFT(C8,3) -> 121 | H8: 0.38 | I8: Minimal Exposure | J8: =IF(COUNTIFS($G$2:G8,G8,$A$2:A8,A8)=1,1,0) -> 1
A9: 1211 | B9: Finance Managers | C9: 1231 | D9: Finance and administration department managers | E9: p | G9: =LEFT(C9,3) -> 123 | H9: 0.37 | I9: Minimal Exposure | J9: =IF(COUNTIFS($G$2:G9,G9,$A$2:A9,A9)=1,1,0) -> 1
A10: 1211 | B10: Finance Managers | C10: 1317 | D10: General managers of business services | E10: p | F10: Managers of establishments | G10: =LEFT(C10,3) -> 131 | H10: 0.37 | I10: Minimal Exposure | J10: =IF(COUNTIFS($G$2:G10,G10,$A$2:A10,A10)=1,1,0) -> 1
A11: 1212 | B11: Human Resource Managers | C11: 1232 | D11: Personnel and industrial relations department | F11: Managers of establishments | G11: =LEFT(C11,3) -> 123 | H11: 0.36 | I11: Minimal Exposure | J11: =IF(COUNTIFS($G$2:G11,G11,$A$2:A11,A11)=1,1,0) -> 1
A12: 1212 | B12: Human Resource Managers | C12: 1317 | D12: General managers of business services | E12: p | F12: providing human resource | G12: =LEFT(C12,3) -> 131 | H12: 0.36 | I12: Minimal Exposure | J12: =IF(COUNTIFS($G$2:G12,G12,$A$2:A12,A12)=1,1,0) -> 1
A13: 1213 | B13: Policy and Planning Managers | C13: 1229 | D13: Production and operations department managers not elsewhere classified | E13: p | G13: =LEFT(C13,3) -> 122 | H13: 0.36 | I13: Not Exposed | J13: =IF(COUNTIFS($G$2:G13,G13,$A$2:A13,A13)=1,1,0) -> 1
A14: 1213 | B14: Policy and Planning Managers | C14: 1239 | D14: Other department managers not elsewhere | F14: IR managers? | G14: =LEFT(C14,3) -> 123 | H14: 0.36 | I14: Not Exposed | J14: =IF(COUNTIFS($G$2:G14,G14,$A$2:A14,A14)=1,1,0) -> 1
A15: 1219 | B15: Business Services and Administration Managers Not Elsewhere Classified | C15: 1227 | D15: Production and operations department managers in business services | F15: Building services and | G15: =LEFT(C15,3) -> 122 | H15: 0.42 | I15: Gradient 2 | J15: =IF(COUNTIFS($G$2:G15,G15,$A$2:A15,A15)=1,1,0) -> 1
A16: 1219 | B16: Business Services and Administration Managers Not Elsewhere Classified | C16: 1228 | D16: Production and operations department managers in personal care, cleaning and related services | F16: cleaning department | G16: =LEFT(C16,3) -> 122 | H16: 0.42 | I16: Gradient 2 | J16: =IF(COUNTIFS($G$2:G16,G16,$A$2:A16,A16)=1,1,0) -> 0
A17: 1219 | B17: Business Services and Administration Managers Not Elsewhere Classified | C17: 1229 | D17: Production and operations department managers not elsewhere classified | E17: p | F17: Administration department | G17: =LEFT(C17,3) -> 122 | H17: 0.42 | I17: Gradient 2 | J17: =IF(COUNTIFS($G$2:G17,G17,$A$2:A17,A17)=1,1,0) -> 0
A18: 1219 | B18: Business Services and Administration Managers Not Elsewhere Classified | C18: 1231 | D18: Finance and administration department managers | E18: p | F18: managers | G18: =LEFT(C18,3) -> 123 | H18: 0.42 | I18: Gradient 2 | J18: =IF(COUNTIFS($G$2:G18,G18,$A$2:A18,A18)=1,1,0) -> 1
A19: 1219 | B19: Business Services and Administration Managers Not Elsewhere Classified | C19: 1317 | D19: General managers of business services | E19: p | F19: Managers of contract cleaning | G19: =LEFT(C19,3) -> 131 | H19: 0.42 | I19: Gradient 2 | J19: =IF(COUNTIFS($G$2:G19,G19,$A$2:A19,A19)=1,1,0) -> 1
A20: 1219 | B20: Business Services and Administration Managers Not Elsewhere Classified | C20: 1318 | D20: General managers in personal care, cleaning and related services | F20: companies? For review | G20: =LEFT(C20,3) -> 131 | H20: 0.42 | I20: Gradient 2 | J20: =IF(COUNTIFS($G$2:G20,G20,$A$2:A20,A20)=1,1,0) -> 0
A21: 1221 | B21: Sales and Marketing Managers | C21: 1233 | D21: Sales and marketing department managers | G21: =LEFT(C21,3) -> 123 | H21: 0.41 | I21: Gradient 2 | J21: =IF(COUNTIFS($G$2:G21,G21,$A$2:A21,A21)=1,1,0) -> 1
A22: 1221 | B22: Sales and Marketing Managers | C22: 1317 | D22: General managers of business services | E22: p | F22: Managers of marketing | G22: =LEFT(C22,3) -> 131 | H22: 0.41 | I22: Gradient 2 | J22: =IF(COUNTIFS($G$2:G22,G22,$A$2:A22,A22)=1,1,0) -> 1
A23: 1222 | B23: Advertising and Public Relations Managers | C23: 1234 | D23: Advertising and public relations department | G23: =LEFT(C23,3) -> 123 | H23: 0.39 | I23: Minimal Exposure | J23: =IF(COUNTIFS($G$2:G23,G23,$A$2:A23,A23)=1,1,0) -> 1
A24: 1222 | B24: Advertising and Public Relations Managers | C24: 1317 | D24: General managers of business services | E24: p | F24: Managers of advertising and | G24: =LEFT(C24,3) -> 131 | H24: 0.39 | I24: Minimal Exposure | J24: =IF(COUNTIFS($G$2:G24,G24,$A$2:A24,A24)=1,1,0) -> 1
A25: 1223 | B25: Research and Development Managers | C25: 1237 | D25: Research and development department | G25: =LEFT(C25,3) -> 123 | H25: 0.4 | I25: Minimal Exposure | J25: =IF(COUNTIFS($G$2:G25,G25,$A$2:A25,A25)=1,1,0) -> 1
A26: 1223 | B26: Research and Development Managers | C26: 1319 | D26: General managers not elsewhere classified | E26: p | F26: Research and development | G26: =LEFT(C26,3) -> 131 | H26: 0.4 | I26: Minimal Exposure | J26: =IF(COUNTIFS($G$2:G26,G26,$A$2:A26,A26)=1,1,0) -> 1
A27: 1311 | B27: Agricultural and Forestry Production Managers | C27: 1221 | D27: Production and operations department managers in agriculture, hunting, forestry and fishing | E27: p | G27: =LEFT(C27,3) -> 122 | H27: 0.27 | I27: Minimal Exposure | J27: =IF(COUNTIFS($G$2:G27,G27,$A$2:A27,A27)=1,1,0) -> 1
A28: 1312 | B28: Aquaculture and Fisheries Production Managers | C28: 1221 | D28: Production and operations department managers in agriculture, hunting, forestry and fishing | E28: p | G28: =LEFT(C28,3) -> 122 | H28: 0.22 | I28: Not Exposed | J28: =IF(COUNTIFS($G$2:G28,G28,$A$2:A28,A28)=1,1,0) -> 1
A29: 1321 | B29: Manufacturing Managers | C29: 1222 | D29: Production and operations department managers in manufacturing | E29: p | G29: =LEFT(C29,3) -> 122 | H29: 0.38 | I29: Minimal Exposure | J29: =IF(COUNTIFS($G$2:G29,G29,$A$2:A29,A29)=1,1,0) -> 1
A30: 1321 | B30: Manufacturing Managers | C30: 1312 | D30: General managers in manufacturing | E30: p | G30: =LEFT(C30,3) -> 131 | H30: 0.38 | I30: Minimal Exposure | J30: =IF(COUNTIFS($G$2:G30,G30,$A$2:A30,A30)=1,1,0) -> 1
A31: 1322 | B31: Mining Managers | C31: 1222 | D31: Production and operations department managers in manufacturing | E31: p | G31: =LEFT(C31,3) -> 122 | H31: 0.35 | I31: Minimal Exposure | J31: =IF(COUNTIFS($G$2:G31,G31,$A$2:A31,A31)=1,1,0) -> 1
A32: 1322 | B32: Mining Managers | C32: 1312 | D32: General managers in manufacturing | E32: p | F32: Managers of small mining and | G32: =LEFT(C32,3) -> 131 | H32: 0.35 | I32: Minimal Exposure | J32: =IF(COUNTIFS($G$2:G32,G32,$A$2:A32,A32)=1,1,0) -> 1
A33: 1323 | B33: Construction Managers | C33: 1223 | D33: Production and operations department managers in construction | E33: p | G33: =LEFT(C33,3) -> 122 | H33: 0.34 | I33: Minimal Exposure | J33: =IF(COUNTIFS($G$2:G33,G33,$A$2:A33,A33)=1,1,0) -> 1
A34: 1323 | B34: Construction Managers | C34: 1313 | D34: General managers in construction | G34: =LEFT(C34,3) -> 131 | H34: 0.34 | I34: Minimal Exposure | J34: =IF(COUNTIFS($G$2:G34,G34,$A$2:A34,A34)=1,1,0) -> 1
A35: 1324 | B35: Supply, Distribution and Related Managers | C35: 1226 | D35: Production and operations department managers in transport, storage and communications | E35: p | F35: Postmasters, station masters, transport, storage | G35: =LEFT(C35,3) -> 122 | H35: 0.38 | I35: Minimal Exposure | J35: =IF(COUNTIFS($G$2:G35,G35,$A$2:A35,A35)=1,1,0) -> 1
A36: 1324 | B36: Supply, Distribution and Related Managers | C36: 1235 | D36: Supply and distribution department managers | G36: =LEFT(C36,3) -> 123 | H36: 0.38 | I36: Minimal Exposure | J36: =IF(COUNTIFS($G$2:G36,G36,$A$2:A36,A36)=1,1,0) -> 1
A37: 1324 | B37: Supply, Distribution and Related Managers | C37: 1316 | D37: General managers in transport, storage and communications | E37: p | G37: =LEFT(C37,3) -> 131 | H37: 0.38 | I37: Minimal Exposure | J37: =IF(COUNTIFS($G$2:G37,G37,$A$2:A37,A37)=1,1,0) -> 1
A38: 1330 | B38: Information and Communications Technology Service Managers | C38: 1226 | D38: Production and operations department managers in transport, storage and communications | E38: p | F38: Telecommunications department managers | G38: =LEFT(C38,3) -> 122 | H38: 0.44 | I38: Gradient 2 | J38: =IF(COUNTIFS($G$2:G38,G38,$A$2:A38,A38)=1,1,0) -> 1
A39: 1330 | B39: Information and Communications Technology Service Managers | C39: 1236 | D39: Computing services department managers | G39: =LEFT(C39,3) -> 123 | H39: 0.44 | I39: Gradient 2 | J39: =IF(COUNTIFS($G$2:G39,G39,$A$2:A39,A39)=1,1,0) -> 1
A40: 1330 | B40: Information and Communications Technology Service Managers | C40: 1316 | D40: General managers in transport, storage and communications | E40: p | F40: Managers of small computing | G40: =LEFT(C40,3) -> 131 | H40: 0.44 | I40: Gradient 2 | J40: =IF(COUNTIFS($G$2:G40,G40,$A$2:A40,A40)=1,1,0) -> 1
A41: 1330 | B41: Information and Communications Technology Service Managers | C41: 1317 | D41: General managers of business services | E41: p | F41: and telecommunications | G41: =LEFT(C41,3) -> 131 | H41: 0.44 | I41: Gradient 2 | J41: =IF(COUNTIFS($G$2:G41,G41,$A$2:A41,A41)=1,1,0) -> 0
A42: 1341 | B42: Child Care Service Managers | C42: 1229 | D42: Production and operations department managers not elsewhere classified | E42: p | G42: =LEFT(C42,3) -> 122 | H42: 0.3 | I42: Minimal Exposure | J42: =IF(COUNTIFS($G$2:G42,G42,$A$2:A42,A42)=1,1,0) -> 1
A43: 1341 | B43: Child Care Service Managers | C43: 1319 | D43: General managers not elsewhere classified | E43: p | G43: =LEFT(C43,3) -> 131 | H43: 0.3 | I43: Minimal Exposure | J43: =IF(COUNTIFS($G$2:G43,G43,$A$2:A43,A43)=1,1,0) -> 1
A44: 1342 | B44: Health Service Managers | C44: 1229 | D44: Production and operations department managers not elsewhere classified | E44: p | G44: =LEFT(C44,3) -> 122 | H44: 0.36 | I44: Minimal Exposure | J44: =IF(COUNTIFS($G$2:G44,G44,$A$2:A44,A44)=1,1,0) -> 1
A45: 1342 | B45: Health Service Managers | C45: 1319 | D45: General managers not elsewhere classified | E45: p | G45: =LEFT(C45,3) -> 131 | H45: 0.36 | I45: Minimal Exposure | J45: =IF(COUNTIFS($G$2:G45,G45,$A$2:A45,A45)=1,1,0) -> 1
A46: 1342 | B46: Health Service Managers | C46: 2230 | D46: Nursing and midwifery professionals | E46: p | F46: Hospital matrons and | G46: =LEFT(C46,3) -> 223 | H46: 0.36 | I46: Minimal Exposure | J46: =IF(COUNTIFS($G$2:G46,G46,$A$2:A46,A46)=1,1,0) -> 1
A47: 1343 | B47: Aged Care Service Managers | C47: 1229 | D47: Production and operations department managers not elsewhere classified | E47: p | G47: =LEFT(C47,3) -> 122 | H47: 0.34 | I47: Minimal Exposure | J47: =IF(COUNTIFS($G$2:G47,G47,$A$2:A47,A47)=1,1,0) -> 1
A48: 1343 | B48: Aged Care Service Managers | C48: 1319 | D48: General managers not elsewhere classified | E48: p | G48: =LEFT(C48,3) -> 131 | H48: 0.34 | I48: Minimal Exposure | J48: =IF(COUNTIFS($G$2:G48,G48,$A$2:A48,A48)=1,1,0) -> 1
A49: 1343 | B49: Aged Care Service Managers | C49: 2230 | D49: Nursing and midwifery professionals | E49: p | F49: Matrons and principal nursing | G49: =LEFT(C49,3) -> 223 | H49: 0.34 | I49: Minimal Exposure | J49: =IF(COUNTIFS($G$2:G49,G49,$A$2:A49,A49)=1,1,0) -> 1
A50: 1344 | B50: Social Welfare Managers | C50: 1229 | D50: Production and operations department managers not elsewhere classified | E50: p | G50: =LEFT(C50,3) -> 122 | H50: 0.37 | I50: Minimal Exposure | J50: =IF(COUNTIFS($G$2:G50,G50,$A$2:A50,A50)=1,1,0) -> 1
A51: 1344 | B51: Social Welfare Managers | C51: 1319 | D51: General managers not elsewhere classified | E51: p | G51: =LEFT(C51,3) -> 131 | H51: 0.37 | I51: Minimal Exposure | J51: =IF(COUNTIFS($G$2:G51,G51,$A$2:A51,A51)=1,1,0) -> 1
A52: 1345 | B52: Education Managers | C52: 1229 | D52: Production and operations department managers not elsewhere classified | E52: p | G52: =LEFT(C52,3) -> 122 | H52: 0.36 | I52: Minimal Exposure | J52: =IF(COUNTIFS($G$2:G52,G52,$A$2:A52,A52)=1,1,0) -> 1
A53: 1345 | B53: Education Managers | C53: 1319 | D53: General managers not elsewhere classified | E53: p | G53: =LEFT(C53,3) -> 131 | H53: 0.36 | I53: Minimal Exposure | J53: =IF(COUNTIFS($G$2:G53,G53,$A$2:A53,A53)=1,1,0) -> 1
A54: 1346 | B54: Financial and Insurance Services Branch managers | C54: 1227 | D54: Production and operations department managers in business services | G54: =LEFT(C54,3) -> 122 | H54: 0.47 | I54: Gradient 2 | J54: =IF(COUNTIFS($G$2:G54,G54,$A$2:A54,A54)=1,1,0) -> 1
A55: 1346 | B55: Financial and Insurance Services Branch managers | C55: 1317 | D55: General managers of business services | E55: p | G55: =LEFT(C55,3) -> 131 | H55: 0.47 | I55: Gradient 2 | J55: =IF(COUNTIFS($G$2:G55,G55,$A$2:A55,A55)=1,1,0) -> 1
A56: 1349 | B56: Professional Services Managers Not Elsewhere Classified | C56: 1229 | D56: Production and operations department managers not elsewhere classified | E56: p | G56: =LEFT(C56,3) -> 122 | H56: 0.38 | I56: Minimal Exposure | J56: =IF(COUNTIFS($G$2:G56,G56,$A$2:A56,A56)=1,1,0) -> 1
A57: 1349 | B57: Professional Services Managers Not Elsewhere Classified | C57: 1319 | D57: General managers not elsewhere classified | E57: p | G57: =LEFT(C57,3) -> 131 | H57: 0.38 | I57: Minimal Exposure | J57: =IF(COUNTIFS($G$2:G57,G57,$A$2:A57,A57)=1,1,0) -> 1
A58: 1411 | B58: Hotel Managers | C58: 1225 | D58: Production and operations department managers in restaurants and hotels | E58: p | G58: =LEFT(C58,3) -> 122 | H58: 0.37 | I58: Gradient 1 | J58: =IF(COUNTIFS($G$2:G58,G58,$A$2:A58,A58)=1,1,0) -> 1
A59: 1411 | B59: Hotel Managers | C59: 1315 | D59: General managers of restaurants and hotels | E59: p | F59: Production and operations | G59: =LEFT(C59,3) -> 131 | H59: 0.37 | I59: Gradient 1 | J59: =IF(COUNTIFS($G$2:G59,G59,$A$2:A59,A59)=1,1,0) -> 1
A60: 1412 | B60: Restaurant Managers | C60: 1225 | D60: Production and operations department managers in restaurants and hotels | E60: p | F60: managers in restaurants | G60: =LEFT(C60,3) -> 122 | H60: 0.36 | I60: Minimal Exposure | J60: =IF(COUNTIFS($G$2:G60,G60,$A$2:A60,A60)=1,1,0) -> 1
A61: 1412 | B61: Restaurant Managers | C61: 1315 | D61: General managers of restaurants and hotels | E61: p | G61: =LEFT(C61,3) -> 131 | H61: 0.36 | I61: Minimal Exposure | J61: =IF(COUNTIFS($G$2:G61,G61,$A$2:A61,A61)=1,1,0) -> 1
A62: 1420 | B62: Retail and Wholesale Trade Managers | C62: 1224 | D62: Production and operations department managers in wholesale and retail trade | G62: =LEFT(C62,3) -> 122 | H62: 0.44 | I62: Gradient 2 | J62: =IF(COUNTIFS($G$2:G62,G62,$A$2:A62,A62)=1,1,0) -> 1
A63: 1420 | B63: Retail and Wholesale Trade Managers | C63: 1314 | D63: General managers in wholesale and retail trade | E63: p | G63: =LEFT(C63,3) -> 131 | H63: 0.44 | I63: Gradient 2 | J63: =IF(COUNTIFS($G$2:G63,G63,$A$2:A63,A63)=1,1,0) -> 1
A64: 1431 | B64: Sports, Recreation and Cultural Centre Managers | C64: 1319 | D64: General managers not elsewhere classified | E64: p | G64: =LEFT(C64,3) -> 131 | H64: 0.32 | I64: Minimal Exposure | J64: =IF(COUNTIFS($G$2:G64,G64,$A$2:A64,A64)=1,1,0) -> 1
A65: 1439 | B65: classified | C65: 1229 | D65: Production and operations department managers not elsewhere classified | E65: p | G65: =LEFT(C65,3) -> 122 | I65: Not scored by ILO | J65: =IF(COUNTIFS($G$2:G65,G65,$A$2:A65,A65)=1,1,0) -> 1
A66: 1439 | B66: Services managers not elsewhere | C66: 1319 | D66: General managers not elsewhere classified | E66: p | G66: =LEFT(C66,3) -> 131 | I66: Not scored by ILO | J66: =IF(COUNTIFS($G$2:G66,G66,$A$2:A66,A66)=1,1,0) -> 1
A67: 2111 | B67: Physicists and Astronomers | C67: 2111 | D67: Physicists and astronomers | G67: =LEFT(C67,3) -> 211 | H67: 0.38 | I67: Gradient 1 | J67: =IF(COUNTIFS($G$2:G67,G67,$A$2:A67,A67)=1,1,0) -> 1
A68: 2112 | B68: Meteorologists | C68: 2112 | D68: Meteorologists | G68: =LEFT(C68,3) -> 211 | H68: 0.54 | I68: Gradient 3 | J68: =IF(COUNTIFS($G$2:G68,G68,$A$2:A68,A68)=1,1,0) -> 1
A69: 2113 | B69: Chemists | C69: 2113 | D69: Chemists | E69: p | G69: =LEFT(C69,3) -> 211 | H69: 0.39 | I69: Minimal Exposure | J69: =IF(COUNTIFS($G$2:G69,G69,$A$2:A69,A69)=1,1,0) -> 1
A70: 2114 | B70: Geologists and geophysicists | C70: 2114 | D70: Geologists and geophysicists | G70: =LEFT(C70,3) -> 211 | H70: 0.36 | I70: Minimal Exposure | J70: =IF(COUNTIFS($G$2:G70,G70,$A$2:A70,A70)=1,1,0) -> 1
A71: 2120 | B71: Mathematicians, Actuaries and Statisticians | C71: 2121 | D71: Mathematicians and related professionals | G71: =LEFT(C71,3) -> 212 | H71: 0.56 | I71: Gradient 3 | J71: =IF(COUNTIFS($G$2:G71,G71,$A$2:A71,A71)=1,1,0) -> 1
A72: 2120 | B72: Mathematicians, Actuaries and Statisticians | C72: 2122 | D72: Statisticians | G72: =LEFT(C72,3) -> 212 | H72: 0.56 | I72: Gradient 3 | J72: =IF(COUNTIFS($G$2:G72,G72,$A$2:A72,A72)=1,1,0) -> 0
A73: 2131 | B73: Biologists, Botanists, Zoologists and Related Professionals | C73: 2211 | D73: Biologists, botanists, zoologists and related | E73: p | G73: =LEFT(C73,3) -> 221 | H73: 0.4 | I73: Gradient 2 | J73: =IF(COUNTIFS($G$2:G73,G73,$A$2:A73,A73)=1,1,0) -> 1
A74: 2131 | B74: Biologists, Botanists, Zoologists and Related Professionals | C74: 2212 | D74: Pharmacologists, pathologists and related | E74: p | F74: Plant pathologists, | G74: =LEFT(C74,3) -> 221 | H74: 0.4 | I74: Gradient 2 | J74: =IF(COUNTIFS($G$2:G74,G74,$A$2:A74,A74)=1,1,0) -> 0
A75: 2132 | B75: Farming, Forestry and Fisheries Advisers | C75: 2213 | D75: Agronomists and related professionals | G75: =LEFT(C75,3) -> 221 | H75: 0.29 | I75: Not Exposed | J75: =IF(COUNTIFS($G$2:G75,G75,$A$2:A75,A75)=1,1,0) -> 1
A76: 2132 | B76: Farming, Forestry and Fisheries Advisers | C76: 3213 | D76: Farming and forestry advisers | G76: =LEFT(C76,3) -> 321 | H76: 0.29 | I76: Not Exposed | J76: =IF(COUNTIFS($G$2:G76,G76,$A$2:A76,A76)=1,1,0) -> 1
A77: 2133 | B77: Environmental Protection Professionals | C77: 2211 | D77: Biologists, botanists, zoologists and related | E77: p | G77: =LEFT(C77,3) -> 221 | H77: 0.38 | I77: Minimal Exposure | J77: =IF(COUNTIFS($G$2:G77,G77,$A$2:A77,A77)=1,1,0) -> 1
A78: 2141 | B78: Industrial and Production Engineers | C78: 2149 | D78: Architects, engineers and related professionals not elsewhere classified | E78: p | G78: =LEFT(C78,3) -> 214 | H78: 0.37 | I78: Minimal Exposure | J78: =IF(COUNTIFS($G$2:G78,G78,$A$2:A78,A78)=1,1,0) -> 1
A79: 2142 | B79: Civil Engineers | C79: 2142 | D79: Civil engineers | G79: =LEFT(C79,3) -> 214 | H79: 0.3 | I79: Not Exposed | J79: =IF(COUNTIFS($G$2:G79,G79,$A$2:A79,A79)=1,1,0) -> 1
A80: 2143 | B80: Environmental Engineers | C80: 2149 | D80: Architects, engineers and related professionals not elsewhere classified | E80: p | G80: =LEFT(C80,3) -> 214 | H80: 0.38 | I80: Minimal Exposure | J80: =IF(COUNTIFS($G$2:G80,G80,$A$2:A80,A80)=1,1,0) -> 1
A81: 2144 | B81: Mechanical Engineers | C81: 2145 | D81: Mechanical engineers | G81: =LEFT(C81,3) -> 214 | H81: 0.32 | I81: Not Exposed | J81: =IF(COUNTIFS($G$2:G81,G81,$A$2:A81,A81)=1,1,0) -> 1
A82: 2145 | B82: Chemical Engineers | C82: 2146 | D82: Chemical engineers | G82: =LEFT(C82,3) -> 214 | H82: 0.35 | I82: Minimal Exposure | J82: =IF(COUNTIFS($G$2:G82,G82,$A$2:A82,A82)=1,1,0) -> 1
A83: 2146 | B83: Mining Engineers, Metallurgists and Related Professionals | C83: 2147 | D83: Mining engineers, metallurgists and related | G83: =LEFT(C83,3) -> 214 | H83: 0.29 | I83: Not Exposed | J83: =IF(COUNTIFS($G$2:G83,G83,$A$2:A83,A83)=1,1,0) -> 1
A84: 2149 | B84: Engineering Professionals Not Elsewhere Classified | C84: 2149 | D84: Architects, engineers and related professionals not elsewhere classified | E84: p | G84: =LEFT(C84,3) -> 214 | H84: 0.3 | I84: Not Exposed | J84: =IF(COUNTIFS($G$2:G84,G84,$A$2:A84,A84)=1,1,0) -> 1
A85: 2151 | B85: Electrical Engineers | C85: 2143 | D85: Electrical engineers | G85: =LEFT(C85,3) -> 214 | H85: 0.31 | I85: Not Exposed | J85: =IF(COUNTIFS($G$2:G85,G85,$A$2:A85,A85)=1,1,0) -> 1
A86: 2152 | B86: Electronics Engineers | C86: 2144 | D86: Electronics and telecommunications engineers | E86: p | G86: =LEFT(C86,3) -> 214 | H86: 0.42 | I86: Gradient 2 | J86: =IF(COUNTIFS($G$2:G86,G86,$A$2:A86,A86)=1,1,0) -> 1
A87: 2153 | B87: Telecommunications Engineers | C87: 2144 | D87: Electronics and telecommunications engineers | E87: p | G87: =LEFT(C87,3) -> 214 | H87: 0.48 | I87: Gradient 2 | J87: =IF(COUNTIFS($G$2:G87,G87,$A$2:A87,A87)=1,1,0) -> 1
A88: 2161 | B88: Building Architects | C88: 2141 | D88: Architects, town and traffic planners | E88: p | G88: =LEFT(C88,3) -> 214 | H88: 0.37 | I88: Minimal Exposure | J88: =IF(COUNTIFS($G$2:G88,G88,$A$2:A88,A88)=1,1,0) -> 1
A89: 2162 | B89: Landscape Architects | C89: 2141 | D89: Architects, town and traffic planners | E89: p | G89: =LEFT(C89,3) -> 214 | H89: 0.37 | I89: Minimal Exposure | J89: =IF(COUNTIFS($G$2:G89,G89,$A$2:A89,A89)=1,1,0) -> 1
A90: 2163 | B90: Product and Garment Designers | C90: 3471 | D90: Decorators and commercial designers | E90: p | G90: =LEFT(C90,3) -> 347 | H90: 0.35 | I90: Minimal Exposure | J90: =IF(COUNTIFS($G$2:G90,G90,$A$2:A90,A90)=1,1,0) -> 1
A91: 2164 | B91: Town and Traffic Planners | C91: 2141 | D91: Architects, town and traffic planners | E91: p | G91: =LEFT(C91,3) -> 214 | H91: 0.41 | I91: Minimal Exposure | J91: =IF(COUNTIFS($G$2:G91,G91,$A$2:A91,A91)=1,1,0) -> 1
A92: 2165 | B92: Cartographers and Surveyors | C92: 2148 | D92: Cartographers and surveyors | G92: =LEFT(C92,3) -> 214 | H92: 0.44 | I92: Gradient 2 | J92: =IF(COUNTIFS($G$2:G92,G92,$A$2:A92,A92)=1,1,0) -> 1
A93: 2166 | B93: Graphic and Multimedia Designers | C93: 3471 | D93: Decorators and commercial designers | E93: p | G93: =LEFT(C93,3) -> 347 | H93: 0.49 | I93: Gradient 2 | J93: =IF(COUNTIFS($G$2:G93,G93,$A$2:A93,A93)=1,1,0) -> 1
A94: 2211 | B94: Generalist Medical Practitioners | C94: 2221 | D94: Medical doctors Pharmacologists, pathologists and related | E94: p | F94: Human pathologists, | G94: =LEFT(C94,3) -> 222 | H94: 0.29 | I94: Not Exposed | J94: =IF(COUNTIFS($G$2:G94,G94,$A$2:A94,A94)=1,1,0) -> 1
A95: 2212 | B95: Specialist Medical Practitioners | C95: 2212 | D95: Pharmacologists, pathologists and related | E95: p | F95: histopathologists, endocrinologists, | G95: =LEFT(C95,3) -> 221 | H95: 0.27 | I95: Not Exposed | J95: =IF(COUNTIFS($G$2:G95,G95,$A$2:A95,A95)=1,1,0) -> 1
A96: 2212 | B96: Specialist Medical Practitioners | C96: 2221 | D96: Medical doctors Pharmacologists, pathologists and related | E96: p | G96: =LEFT(C96,3) -> 222 | H96: 0.27 | I96: Not Exposed | J96: =IF(COUNTIFS($G$2:G96,G96,$A$2:A96,A96)=1,1,0) -> 1
A97: 2221 | B97: Nursing Professionals | C97: 2230 | D97: Nursing and midwifery professionals | E97: p | G97: =LEFT(C97,3) -> 223 | H97: 0.25 | I97: Not Exposed | J97: =IF(COUNTIFS($G$2:G97,G97,$A$2:A97,A97)=1,1,0) -> 1
A98: 2222 | B98: Midwifery Professionals | C98: 2230 | D98: Nursing and midwifery professionals | E98: p | G98: =LEFT(C98,3) -> 223 | H98: 0.3 | I98: Minimal Exposure | J98: =IF(COUNTIFS($G$2:G98,G98,$A$2:A98,A98)=1,1,0) -> 1
A99: 2230 | B99: Traditional and Complementary Medicine Professionals | C99: 3229 | D99: Modern health associate professionals (except nursing) not elsewhere classified | E99: p | F99: Homeopaths | G99: =LEFT(C99,3) -> 322 | H99: 0.32 | I99: Minimal Exposure | J99: =IF(COUNTIFS($G$2:G99,G99,$A$2:A99,A99)=1,1,0) -> 1
A100: 2230 | B100: Traditional and Complementary Medicine Professionals | C100: 3241 | D100: Traditional medicine practitioners | E100: p | G100: =LEFT(C100,3) -> 324 | H100: 0.32 | I100: Minimal Exposure | J100: =IF(COUNTIFS($G$2:G100,G100,$A$2:A100,A100)=1,1,0) -> 1
...
